Lab3/verilog/alu_behvaioral/Adder_Behav/Adder_32_Behav.v
// Title:  32-bit adder
// Author: David Dolengewicz
// A 32-bit adder


module Adder_32_Behav(a, b, sum, zero, overflow, carryOut, negative);

input wire [31:0] a, b;
output reg [31:0] sum;
output reg zero, overflow, carryOut, negative;

reg [32:0] overflowCheck;

reg msbA, msbB, msbSum;


always @(*) begin 

	overflowCheck = (a + b);

	sum = a + b;
	
	msbA = a[31];
	msbB = b[31];
	msbSum = sum[31];
	
	overflow = (msbA & msbB & ~msbSum) + (~msbA & ~msbB & msbSum); 
	carryOut = overflowCheck[32];
	negative = sum[31];
	zero = (sum == 0);
	
end

endmodule

Lab3/verilog/alu_behvaioral/Adder_Behav/Adder_32_Behav_Tester.v
// Title:  32-bit adder Tester
// Author: David Dolengewicz
// A test bench module for the 32-bit adder
// that makes sure it works to spec


module Adder_32_Behav_Tester(a, b, sum, zero, overflow, carryOut, negative);

output reg [31:0] a, b;
input wire [31:0] sum;
input wire zero, overflow, carryOut, negative;

integer i;

parameter stimDelay = 1;

initial // Response
	begin
	// Displays the labels and data
	$display("\t\t\t a \t\t\t b \t\t\t sum \t\t zero \t overflow carryOut \t negative \t Time ");
	$monitor("\t\t %d \t\t %d \t\t %d \t\t %d \t %b \t     %b \t\t %b \t %g",a, b, sum, zero, overflow, carryOut, negative, $time );
	end

	initial // Stimulus
	begin
	#stimDelay;
	a = 32; b = 32;
	#stimDelay;
	a = 320; b = 32;
	#stimDelay;
	a = 3200; b = 32;
	#stimDelay;
	a = 32000; b = 32;
	#stimDelay;
	a = 320000; b = 32;
	#stimDelay;
	a = 3200000; b = 32;
	#stimDelay;
	a = 32000000; b = 32;
	#stimDelay;
	a = 320000000; b = 32;
	#stimDelay;
	
	a = 320000000; b = 320;
	#stimDelay;
	a = 320000000; b = 3200;
	#stimDelay;
	a = 320000000; b = 320000000;
	#stimDelay;
	
	a = 32'h7FFFFFFF; b = 15;
	#stimDelay;
	
	a = 3200000000; b = 3200000000;
	#stimDelay;
	
	a = 32000000000; b = 32;
	#stimDelay;
	a = 320000000000; b = 32;
	#stimDelay;
	a = 3200000000000; b = 32;
	#stimDelay;
	a = 32000000000000; b = 32;
	#stimDelay;
	
	
	#stimDelay;
	a = 32; b = -32;
	#stimDelay;
	a = 320; b = -320;
	#stimDelay;
	a = -3200; b = -32;
	#stimDelay;
	a = -32000; b = 32000;
	#stimDelay;
	a = -32000; b = 320000;
	#stimDelay;
	a = 3200000; b = 32;
	#stimDelay;
	a = 32000000; b = 32;
	
	a = 32'h80000000; b = -3200000;
	#stimDelay;
	
	a = 3200000000; b = 32;
	#stimDelay;
	a = -3200000000; b = -3200000000;
	#stimDelay;


	#(2*stimDelay); // needed to see END of simulation
	$finish; // finish simulation
	end



endmodule

Lab3/verilog/alu_behvaioral/Adder_Behav/Adder_tb.v
// Title:  32-bit adder testbench
// Author: David Dolengewicz
// A test bench module for the 32-bit adder
// that makes sure it works to spec

//All files Used
`include "Adder_32_Behav.v"
`include "Adder_32_Behav_Tester.v"

module Adder_tb();

wire [31:0] a, b;
wire [31:0] sum;
wire zero, overflow, carryOut, negative;



Adder_32_Behav_Tester tester (	.a(a), 
								.b(b), 
								.sum(sum), 
								.zero(zero), 
								.overflow(overflow), 
								.carryOut(carryOut), 
								.negative(negative) 	);
								
Adder_32_Behav dut ( 			.a(a), 
								.b(b), 
								.sum(sum), 
								.zero(zero), 
								.overflow(overflow), 
								.carryOut(carryOut), 
								.negative(negative) 	);
								
									// File for gtkwave
	initial begin
		$dumpfile("AdderTest.vcd");
		$dumpvars(1, dut);
		
	end
						


endmodule

Lab3/verilog/alu_behvaioral/Adder_Behav/AdderTest.vcd
$date
	Wed Apr 27 15:56:36 2016
$end
$version
	Icarus Verilog
$end
$timescale
	1s
$end
$scope module Adder_tb $end
$scope module dut $end
$var wire 32 ! b [31:0] $end
$var wire 32 " a [31:0] $end
$var reg 1 # carryOut $end
$var reg 1 $ msbA $end
$var reg 1 % msbB $end
$var reg 1 & msbSum $end
$var reg 1 ' negative $end
$var reg 1 ( overflow $end
$var reg 33 ) overflowCheck [32:0] $end
$var reg 32 * sum [31:0] $end
$var reg 1 + zero $end
$upscope $end
$upscope $end
$enddefinitions $end
#0
$dumpvars
x+
bx *
bx )
x(
x'
x&
x%
x$
x#
bx "
bx !
$end
#1
0+
0'
0#
0(
0&
0%
0$
b1000000 *
b1000000 )
b100000 !
b100000 "
#2
b101100000 *
b101100000 )
b101000000 "
#3
b110010100000 *
b110010100000 )
b110010000000 "
#4
b111110100100000 *
b111110100100000 )
b111110100000000 "
#5
b1001110001000100000 *
b1001110001000100000 )
b1001110001000000000 "
#6
b1100001101010000100000 *
b1100001101010000100000 )
b1100001101010000000000 "
#7
b1111010000100100000100000 *
b1111010000100100000100000 )
b1111010000100100000000000 "
#8
b10011000100101101000000100000 *
b10011000100101101000000100000 )
b10011000100101101000000000000 "
#9
b10011000100101101000101000000 *
b10011000100101101000101000000 )
b101000000 !
#10
b10011000100101101110010000000 *
b10011000100101101110010000000 )
b110010000000 !
#11
b100110001001011010000000000000 *
b100110001001011010000000000000 )
b10011000100101101000000000000 !
#12
1'
1(
1&
b10000000000000000000000000001110 *
b10000000000000000000000000001110 )
b1111 !
b1111111111111111111111111111111 "
#13
0'
1#
0&
1%
1$
b1111101011110000100000000000000 *
b101111101011110000100000000000000 )
b10111110101111000010000000000000 !
b10111110101111000010000000000000 "
#14
0#
0(
0%
0$
b1110011010110010100000000100000 *
b1110011010110010100000000100000 )
b100000 !
b1110011010110010100000000000000 "
#15
1'
1&
1$
b10000001011111001000000000100000 *
b10000001011111001000000000100000 )
b10000001011111001000000000000000 "
#16
0'
0&
0$
b1110110111010000000000100000 *
b1110110111010000000000100000 )
b1110110111010000000000000000 "
#17
1'
1&
1$
b10010100101000100000000000100000 *
b10010100101000100000000000100000 )
b10010100101000100000000000000000 "
#19
1+
0'
1#
0&
1%
0$
b0 *
b100000000000000000000000000000000 )
b11111111111111111111111111100000 !
b100000 "
#20
b11111111111111111111111011000000 !
b101000000 "
#21
0+
1'
1&
1$
b11111111111111111111001101100000 *
b111111111111111111111001101100000 )
b11111111111111111111111111100000 !
b11111111111111111111001110000000 "
#22
1+
0'
0&
0%
b0 *
b100000000000000000000000000000000 )
b111110100000000 !
b11111111111111111000001100000000 "
#23
0+
b1000110010100000000 *
b100000000000001000110010100000000 )
b1001110001000000000 !
#24
0#
0$
b1100001101010000100000 *
b1100001101010000100000 )
b100000 !
b1100001101010000000000 "
#25
1#
1(
1%
1$
b1111111110011110010110000000000 *
b101111111110011110010110000000000 )
b11111111110011110010110000000000 !
b10000000000000000000000000000000 "
#26
1'
0#
0(
1&
0%
b10111110101111000010000000100000 *
b10111110101111000010000000100000 )
b100000 !
b10111110101111000010000000000000 "
#27
1(
0$
b10000010100001111100000000000000 *
b10000010100001111100000000000000 )
b1000001010000111110000000000000 !
b1000001010000111110000000000000 "
