Lab5/verilog/sram/sram.v

/*
Author: Adolfo Pineda and Ian Gilman
Title: 2kx16 SRAM 
Summary: 2k memory registers of 16 bits memory with data-in & data-out with
   chip select, output enable, write enable
*/

module sram(clk, cs, oe, rw, wr_fwd, addr, write_data, forward, read_data);
	// I/O
   input wire clk, cs, oe, rw,  // clock, !chip select, !out enable, read/!write
              wr_fwd;  // whether data is forwarded to mem
	input wire [31:0] addr,  // address of sram to index (only first 11 bits)
                     write_data,  // data to sram (only first 16 bits)
                     forward;  // data to forward to the sram
   output reg [31:0] read_data;  // data from sram
	reg [15:0] memory [0:2047];  // sram array of 16-bit registers
   // Internal
   wire [15:0] data_to_mem;
   
   
   /////  SRAM READ  /////
   always @(*) begin
      if(!cs && (rw && !oe)) begin
         // sign extend data from memory
         read_data = {{16{memory[addr[10:0]][15]}}, {memory[addr[10:0]]}};
      end
      else
         read_data = 32'bz;
   end
   
   /////  SRAM WRITE  /////
	assign data_to_mem = wr_fwd ? forward[15:0] : write_data[15:0];
   always @(posedge clk) begin
      if (!cs && (!rw && oe))
         memory[addr[10:0]] = data_to_mem[15:0];
      else
         memory[addr[10:0]] = memory[addr[10:0]];
	end
endmodule

Lab5/verilog/sram/sram_tb.v

// All files used
`include "sram.v"

// Title: SRAM Testbench
// Author: Adolfo Pineda
// A test bench module

module sram_tb;
	wire clk, cs, oe, rw, wr_fwd;
	wire [31:0] addr,
               write_data,
               forward,
               read_data;
	
	// dut
	sram dut(clk, cs, oe, rw, wr_fwd, addr, write_data, forward, read_data);

	// tester
	sramTester Tester(clk, cs, oe, rw, wr_fwd, addr, write_data, forward, read_data);

	// File for gtkwave
	initial begin
		$dumpfile("sram.vcd");
		$dumpvars(1, dut);
	end
endmodule



// Title: SRAM Tester
// Author: Adolfo Pineda
// A testing module

module sramTester (clk, cs, oe, rw, wr_fwd, addr, write_data, forward, read_data);
	output reg clk, cs, oe, rw,  // clock, !chip select, !out enable, read/!write
              wr_fwd;  // whether data is forwarded to mem
   output reg [31:0] addr,  // address of sram to index
                     write_data,  // data to sram
                     forward;  // data to forward to mem
   input wire [31:0] read_data;  // data from sram
	parameter stimDelay = 10;
	
	initial // Response
	begin
	
	// Displays the labels and data
	$display("\t\t cs rw oe  wr_fwd     adr \t wrd\t\tfwd\t\trdd\t\tclk  time");
	$monitor("\t\t %b  %b  %b   %b          %h   %h \t%h \t%h  \t%b    %g",
			cs, rw, oe, wr_fwd, addr, write_data, forward, read_data, clk, $time);
	end

   integer i;
	initial // Stimulus
	begin
   
   // initial
	clk = 1; 
	cs = 1;
	rw = 0;
	oe = 0;
   wr_fwd = 1'b0;
	write_data = 32'b0;
   forward = 32'b0;
	addr = 0;
   clk = 1;
	
   // write values to first 16 addresses
   for(i=0; i<2; i=i+1) begin
      clk = ~clk; #stimDelay; 
   end
   cs = 1'b0;
   oe = 1'b1;
	for (i = 0; i < 32; i = i + 1) begin
			write_data = write_data + (i+1)%2;
         addr = addr + (i+1)%2;
         clk = ~clk; #stimDelay; 
   end
	
	
   // read
   for(i=0; i<2; i=i+1) begin
      clk = ~clk; #stimDelay; 
   end
   addr = 0;
	rw = 1;
	oe = 0;
   for (i = 0; i < 32; i = i + 1) begin
      addr = addr + (i+1)%2;
      clk = ~clk; #stimDelay; 
	end
   for(i=0; i<2; i=i+1) begin
      clk = ~clk; #stimDelay; 
   end
	
   // write
   rw = 0;
   oe = 1;
   addr = 11'h200;
   wr_fwd = 1'b1;
   forward = 32'h7AAA;
   for(i=0; i<2; i=i+1) begin
      clk = ~clk; #stimDelay; 
   end
   forward = 32'hAAAA;
	addr = 11'h201;
   for(i=0; i<2; i=i+1) begin
      clk = ~clk; #stimDelay; 
   end
   forward = 32'h0;
   
   // read again
	addr = 11'h200;
   rw = 1;
	oe = 0;
	for(i=0; i<2; i=i+1) begin
      clk = ~clk; #stimDelay; 
   end
   addr = 11'h201;
	for(i=0; i<2; i=i+1) begin
      clk = ~clk; #stimDelay; 
   end
   
	$finish; // finish simulation
	end
	
endmodule

Lab5/verilog/sram/sram.vcd
$date
	Wed Jun 01 21:49:52 2016
$end
$version
	Icarus Verilog
$end
$timescale
	1s
$end
$scope module sram_tb $end
$scope module dut $end
$var wire 32 ! addr [31:0] $end
$var wire 1 " clk $end
$var wire 1 # cs $end
$var wire 32 $ forward [31:0] $end
$var wire 1 % oe $end
$var wire 1 & rw $end
$var wire 1 ' wr_fwd $end
$var wire 32 ( write_data [31:0] $end
$var wire 16 ) data_to_mem [15:0] $end
$var reg 32 * read_data [31:0] $end
$upscope $end
$upscope $end
$enddefinitions $end
#0
$dumpvars
bz *
b0 )
b0 (
0'
0&
0%
b0 $
1#
0"
b0 !
$end
#10
1"
#20
b1 )
0"
b1 !
b1 (
1%
0#
#30
1"
#40
b10 )
0"
b10 !
b10 (
#50
1"
#60
b11 )
0"
b11 !
b11 (
#70
1"
#80
b100 )
0"
b100 !
b100 (
#90
1"
#100
b101 )
0"
b101 !
b101 (
#110
1"
#120
b110 )
0"
b110 !
b110 (
#130
1"
#140
b111 )
0"
b111 !
b111 (
#150
1"
#160
b1000 )
0"
b1000 !
b1000 (
#170
1"
#180
b1001 )
0"
b1001 !
b1001 (
#190
1"
#200
b1010 )
0"
b1010 !
b1010 (
#210
1"
#220
b1011 )
0"
b1011 !
b1011 (
#230
1"
#240
b1100 )
0"
b1100 !
b1100 (
#250
1"
#260
b1101 )
0"
b1101 !
b1101 (
#270
1"
#280
b1110 )
0"
b1110 !
b1110 (
#290
1"
#300
b1111 )
0"
b1111 !
b1111 (
#310
1"
#320
b10000 )
0"
b10000 !
b10000 (
#330
1"
#340
0"
#350
1"
#360
b1 *
0"
0%
1&
b1 !
#370
1"
#380
b10 *
0"
b10 !
#390
1"
#400
b11 *
0"
b11 !
#410
1"
#420
b100 *
0"
b100 !
#430
1"
#440
b101 *
0"
b101 !
#450
1"
#460
b110 *
0"
b110 !
#470
1"
#480
b111 *
0"
b111 !
#490
1"
#500
b1000 *
0"
b1000 !
#510
1"
#520
b1001 *
0"
b1001 !
#530
1"
#540
b1010 *
0"
b1010 !
#550
1"
#560
b1011 *
0"
b1011 !
#570
1"
#580
b1100 *
0"
b1100 !
#590
1"
#600
b1101 *
0"
b1101 !
#610
1"
#620
b1110 *
0"
b1110 !
#630
1"
#640
b1111 *
0"
b1111 !
#650
1"
#660
b10000 *
0"
b10000 !
#670
1"
#680
0"
#690
1"
#700
b111101010101010 )
bz *
0"
b111101010101010 $
1'
b1000000000 !
1%
0&
#710
1"
#720
b1010101010101010 )
0"
b1000000001 !
b1010101010101010 $
#730
1"
#740
b0 )
b111101010101010 *
0"
0%
1&
b1000000000 !
b0 $
#750
1"
#760
b11111111111111111010101010101010 *
0"
b1000000001 !
