Lab3/verilog/alu_gate/adder_gate/adder_tester.v
/*
Author: Ian Gilman
Title: Adder Tester
Summary: Provides stimulus to test a signed binary adder, prints test data
*/

module adder_tester(addend0, addend1, sum, Z, V, C, N);
// I/O
   output reg [31:0] addend0, addend1;
   input wire [31:0] sum;
   input wire Z, V, C, N;
// Internal
   parameter delay = 1;
   
   // display data
   initial begin
      $display("\tC\tZ\tV\tN\t     sum\t addend0\t  addend1\ttime");
      $monitor(
               "\t%b\t%b\t%b\t%b\t%h\t%h\t%h\t%g",
               C, Z, V, N, sum, addend0, addend1, $time
              );
   end
   integer k = -1;
   // stimulus
   integer i, j;
   initial begin
      // start
      #delay;
      addend0 <= 32'h0;
      addend1 <= 32'h0;
      #delay;
      
      // test regular
      addend0 <= 32'h12;
      addend1 <= 32'h38;
      #delay;
      
      // test zero
      addend0 <= 32'h80007655;
      addend1 <= 32'h7FFF89AA + 32'h1;
      #delay;
      
      // test overflow
      addend0 <= 32'h7FFFFFFF;
      addend1 <= 32'h2;
      #delay;
      
      // test negative
      addend0 <= 32'h80000001;
      addend1 <= 32'hF;
      #delay;
      
      // loop test
      for(i=0; i<16; i=i+1) begin
         addend1 <= i;
         for(j=0; j<16; j=j+1) begin
            addend0 <= -j;
            #delay;
         end
      end
      
   end
   
endmodule

Lab3/verilog/gate_level/adder_gate/half_adder_gate.v
/*
Author: Ian Gilman
Title: Half-Adder
Summary: Logic for adding addend0, addend1, and carry_in to produce sum and carry
*/

module half_adder(addend0, addend1, carry_in, sum, carry_out);
   // I/O
   input wire addend0, addend1, carry_in;
   output wire sum, carry_out;
   // Internal
   wire carry0, carry1, carry2;
   
   // find sum
   xor xor0(sum, addend0, addend1, carry_in);
   
   // find carry_out
   and and0(carry0, addend0, addend1);
   and and1(carry1, addend0, carry_in);
   and and2(carry2, addend1, carry_in);
   or or0(carry_out, carry0, carry1, carry2);
endmodule

Lab3/verilog/gate_level/adder_gate/adder_gate.v
/*
Author: Ian Gilman
Title: 32-bit Full Adder
Summary: adds signed addends together into sum. Controls flags: zero value (Z),
   overflow (V), carry (C), and negative value (N)
*/

// Module Dependencies
//`include "half_adder_gate.v"

module adder_gate(addend0, addend1, sum, Z, V, C, N);
// I/O
   input wire [31:0] addend0, addend1;  // signed values to add
   output wire [31:0] sum;  // sum of addends
   output wire Z, V, C, N;  // zero, overflow, carry_out, negative value
// Internal
   // adder flag wires
   wire [30:0] pre_zero;
   wire msb_addend_same, msb_sum_diff, not_overflow;
   // look-ahead carry wires
   wire [31:0] and_addend_pairs,
               carry,
               prop_carry,
               carry_propogate;
   
    
   //// ADDER FLAG LOGIC ////
   // zero flag
   // Z = sum[n] + sum[n-1] + ... + sum[1] + sum[0]
   not define_zero(Z, pre_zero[30]);
   buf init_prezero(pre_zero[0], sum[0]);
   genvar k;
   generate for(k=1; k<31; k=k+1) begin: ZERO_FLAG
      or prezero_or(pre_zero[k], pre_zero[k-1], sum[k]);
   end
   endgenerate
   // overflow flag
   // addend0 = A, addend1 = B
   // V = (A[31] x^ B[31]) * (A[31] x sum[31])
   xnor same_addend_msb(msb_addend_same, addend0[31], addend1[31]);
   xor diff_sum_msb(msb_sum_diff, sum[31], addend0[31]);
   and overflow_check(V, msb_addend_same, msb_sum_diff);
   // carry out flag
   // Cout = carry[31] * ^V
   not negate_overflow(not_overflow, V);
   and carry_out_and(C, not_overflow, carry[31]);
   // negative value flag
   // V = sum[31] * ~V
   and negative_val_and(N, not_overflow, sum[31]);
   
   
   // HALF_ADDERS
   // Produce sums using half-adders
   half_adder bit0_summation(  // first sum is an exception (no carry)
                           .addend0(addend0[0]),
                           .addend1(addend1[0]),
                           .carry_in(1'b0),
                           .sum(sum[0]),
                           .carry_out(carry[0]) // 1st carry calc'd here
                        );
   genvar j;
   generate for(j=1; j<32; j=j+1) begin: HALF_ADDERS
      half_adder summation(
                           .addend0(addend0[j]),
                           .addend1(addend1[j]),
                           .carry_in(carry[j-1]),
                           .sum(sum[j]),
                           .carry_out()
                          );
   end
   endgenerate
   
   
   // Determine carry using several stages of combinational logic
   // LOOK AHEAD CARRY
   /* carry = C, addend0 = A, addend1 = B 
      for n=(1-31) bits: C[n] = A[n]*B[n] + (A[n] + B[n])*C([n]-1)
      special case: C[0] = A[0]*B[0],
   */
   buf(prop_carry[0], 1'b0);
   genvar i;
   generate for(i=0; i<32; i=i+1) begin: CARRY_CALC
      // determine definite carry from anding addend pairs
      and and_pairs(and_addend_pairs[i], addend0[i], addend1[i]);
      // determine if carry propogates (oring or xoring addends)
      or or_pairs(carry_propogate[i], addend0[i], addend1[i]);
      if(i>0) begin
         // determine final carry value
         or carry_or(carry[i], prop_carry[i], and_addend_pairs[i]);
         // determine propogation carry (prop_carry)
         and pre_carry_and(prop_carry[i], carry[i-1], carry_propogate[i]);
      end
   end
   endgenerate
endmodule

Lab3/verilog/gate_level/adder_gate/adder_testbench.v
/*
Author: Ian Gilman
Title: Adder Testebench
Summary: Test bench for signed adder test, dumps waveform data
*/

// Module Dependencies
`include "half_adder_gate.v"
`include "adder_gate.v"
`include "adder_tester.v"

module adder_testbench();
   wire [31:0] addend0, addend1;
   wire [31:0] sum;
   wire Z, V, C, N;

   // dut
   adder_gate addition(
                        .addend0(addend0),
                        .addend1(addend1),
                        .sum(sum), 
                        .Z(Z), 
                        .V(V), 
                        .C(C), 
                        .N(N)
                       );
   // tester
   adder_tester addition_tester(
                        .addend0(addend0),
                        .addend1(addend1),
                        .sum(sum), 
                        .Z(Z), 
                        .V(V), 
                        .C(C), 
                        .N(N)
                       );

   // create waveform data file
   initial begin
      $dumpfile("adder_gate.vcd");
      $dumpvars(1, addition);
   end
endmodule

Lab3/verilog/alu_gate/adder_gate/adder_gate.vcd
$date
	Tue Apr 26 14:06:08 2016
$end
$version
	Icarus Verilog
$end
$timescale
	1s
$end
$scope module adder_testbench $end
$scope module addition $end
$var wire 1 ! C $end
$var wire 1 " N $end
$var wire 1 # V $end
$var wire 1 $ Z $end
$var wire 1 % msb_addend_same $end
$var wire 1 & msb_sum_diff $end
$var wire 1 ' not_overflow $end
$var wire 32 ( sum [31:0] $end
$var wire 32 ) prop_carry [31:0] $end
$var wire 31 * pre_zero [30:0] $end
$var wire 32 + carry_propogate [31:0] $end
$var wire 32 , carry [31:0] $end
$var wire 32 - and_addend_pairs [31:0] $end
$var wire 32 . addend1 [31:0] $end
$var wire 32 / addend0 [31:0] $end
$upscope $end
$upscope $end
$enddefinitions $end
#0
$dumpvars
bx /
bx .
bx -
bx ,
bx +
bx *
bx0 )
bx (
x'
x&
x%
x$
x#
x"
x!
$end
#1
1$
1'
0#
0"
0&
0!
b0 *
b0 )
b0 ,
b0 (
1%
b0 +
b0 -
b0 .
b0 /
#2
0$
b100000 )
b110000 ,
b1111111111111111111111111111110 *
b10000 -
b111010 +
b1001010 (
b111000 .
b10010 /
#3
1$
1!
b0 *
b11111111111111111111111111111110 )
0"
b11111111111111111111111111111111 ,
1&
0%
b11111111111111111111111111111111 +
b1 -
b0 (
b1111111111111111000100110101011 .
b10000000000000000111011001010101 /
#4
0$
0!
0'
1#
b1111111111111111111111111111100 )
0"
b1111111111111111111111111111111 *
b1111111111111111111111111111110 ,
1&
1%
b1111111111111111111111111111111 +
b10 -
b10000000000000000000000000000001 (
b10 .
b1111111111111111111111111111111 /
#5
0$
1"
0!
b1111111111111111111111111110000 *
1'
b1110 )
b1111 ,
0#
0&
0%
b10000000000000000000000000001111 +
b1 -
b10000000000000000000000000010000 (
b1111 .
b10000000000000000000000000000001 /
#6
1$
1'
0"
b0 )
b0 *
0#
b0 ,
0&
1%
b0 +
b0 -
b0 (
b0 /
b0 .
#7
0$
1"
b1111111111111111111111111111111 *
0&
0%
b11111111111111111111111111111111 +
b11111111111111111111111111111111 (
b11111111111111111111111111111111 /
#8
b1111111111111111111111111111110 *
b11111111111111111111111111111110 (
b11111111111111111111111111111110 +
b11111111111111111111111111111110 /
#9
b1111111111111111111111111111111 *
b11111111111111111111111111111101 +
b11111111111111111111111111111101 (
b11111111111111111111111111111101 /
#10
b1111111111111111111111111111100 *
b11111111111111111111111111111100 (
b11111111111111111111111111111100 +
b11111111111111111111111111111100 /
#11
b1111111111111111111111111111111 *
b11111111111111111111111111111011 +
b11111111111111111111111111111011 (
b11111111111111111111111111111011 /
#12
b1111111111111111111111111111110 *
b11111111111111111111111111111010 (
b11111111111111111111111111111010 +
b11111111111111111111111111111010 /
#13
b1111111111111111111111111111111 *
b11111111111111111111111111111001 +
b11111111111111111111111111111001 (
b11111111111111111111111111111001 /
#14
b1111111111111111111111111111000 *
b11111111111111111111111111111000 (
b11111111111111111111111111111000 +
b11111111111111111111111111111000 /
#15
b1111111111111111111111111111111 *
b11111111111111111111111111110111 +
b11111111111111111111111111110111 (
b11111111111111111111111111110111 /
#16
b1111111111111111111111111111110 *
b11111111111111111111111111110110 (
b11111111111111111111111111110110 +
b11111111111111111111111111110110 /
#17
b1111111111111111111111111111111 *
b11111111111111111111111111110101 +
b11111111111111111111111111110101 (
b11111111111111111111111111110101 /
#18
b1111111111111111111111111111100 *
b11111111111111111111111111110100 (
b11111111111111111111111111110100 +
b11111111111111111111111111110100 /
#19
b1111111111111111111111111111111 *
b11111111111111111111111111110011 +
b11111111111111111111111111110011 (
b11111111111111111111111111110011 /
#20
b1111111111111111111111111111110 *
b11111111111111111111111111110010 (
b11111111111111111111111111110010 +
b11111111111111111111111111110010 /
#21
b1111111111111111111111111111111 *
b11111111111111111111111111110001 +
b11111111111111111111111111110001 (
b11111111111111111111111111110001 /
#22
1'
0"
0#
0&
1%
b1 +
b1 (
b0 /
b1 .
#23
1!
1$
b11111111111111111111111111111110 )
b0 *
0"
b11111111111111111111111111111111 ,
1&
0%
b11111111111111111111111111111111 +
b1 -
b0 (
b11111111111111111111111111111111 /
#24
0!
1"
0&
0$
b0 )
b1111111111111111111111111111111 *
b0 ,
b11111111111111111111111111111111 (
b0 -
b11111111111111111111111111111110 /
#25
b1111111111111111111111111111110 *
b1 ,
b11111111111111111111111111111101 +
b1 -
b11111111111111111111111111111110 (
b11111111111111111111111111111101 /
#26
b1111111111111111111111111111111 *
b0 ,
b11111111111111111111111111111101 (
b0 -
b11111111111111111111111111111100 /
#27
b10 )
b1111111111111111111111111111100 *
b11 ,
b11111111111111111111111111111011 +
b1 -
b11111111111111111111111111111100 (
b11111111111111111111111111111011 /
#28
b0 )
b1111111111111111111111111111111 *
b0 ,
b11111111111111111111111111111011 (
b0 -
b11111111111111111111111111111010 /
#29
b1111111111111111111111111111110 *
b1 ,
b11111111111111111111111111111001 +
b1 -
b11111111111111111111111111111010 (
b11111111111111111111111111111001 /
#30
b1111111111111111111111111111111 *
b0 ,
b11111111111111111111111111111001 (
b0 -
b11111111111111111111111111111000 /
#31
b110 )
b1111111111111111111111111111000 *
b111 ,
b11111111111111111111111111110111 +
b1 -
b11111111111111111111111111111000 (
b11111111111111111111111111110111 /
#32
b0 )
b1111111111111111111111111111111 *
b0 ,
b11111111111111111111111111110111 (
b0 -
b11111111111111111111111111110110 /
#33
b1111111111111111111111111111110 *
b1 ,
b11111111111111111111111111110101 +
b1 -
b11111111111111111111111111110110 (
b11111111111111111111111111110101 /
#34
b1111111111111111111111111111111 *
b0 ,
b11111111111111111111111111110101 (
b0 -
b11111111111111111111111111110100 /
#35
b10 )
b1111111111111111111111111111100 *
b11 ,
b11111111111111111111111111110011 +
b1 -
b11111111111111111111111111110100 (
b11111111111111111111111111110011 /
#36
b0 )
b1111111111111111111111111111111 *
b0 ,
b11111111111111111111111111110011 (
b0 -
b11111111111111111111111111110010 /
#37
b1111111111111111111111111111110 *
b1 ,
b11111111111111111111111111110001 +
b1 -
b11111111111111111111111111110010 (
b11111111111111111111111111110001 /
#38
0$
1'
0"
b0 )
b1111111111111111111111111111110 *
0#
b0 ,
0&
1%
b10 +
b0 -
b10 (
b0 /
b10 .
#39
1!
b11111111111111111111111111111100 )
b11111111111111111111111111111110 ,
0"
b1111111111111111111111111111111 *
1&
0%
b10 -
b11111111111111111111111111111111 +
b1 (
b11111111111111111111111111111111 /
#40
1$
b0 *
b0 (
b11111111111111111111111111111110 +
b11111111111111111111111111111110 /
#41
0!
1"
0&
0$
b0 )
b0 ,
b1111111111111111111111111111111 *
b0 -
b11111111111111111111111111111111 +
b11111111111111111111111111111111 (
b11111111111111111111111111111101 /
#42
b1111111111111111111111111111110 *
b11111111111111111111111111111110 (
b11111111111111111111111111111110 +
b11111111111111111111111111111100 /
#43
b10 ,
b1111111111111111111111111111111 *
b10 -
b11111111111111111111111111111011 +
b11111111111111111111111111111101 (
b11111111111111111111111111111011 /
#44
b1111111111111111111111111111100 *
b11111111111111111111111111111100 (
b11111111111111111111111111111010 +
b11111111111111111111111111111010 /
#45
b0 ,
b1111111111111111111111111111111 *
b0 -
b11111111111111111111111111111011 +
b11111111111111111111111111111011 (
b11111111111111111111111111111001 /
#46
b1111111111111111111111111111110 *
b11111111111111111111111111111010 (
b11111111111111111111111111111010 +
b11111111111111111111111111111000 /
#47
b100 )
b110 ,
b1111111111111111111111111111111 *
b10 -
b11111111111111111111111111110111 +
b11111111111111111111111111111001 (
b11111111111111111111111111110111 /
#48
b1111111111111111111111111111000 *
b11111111111111111111111111111000 (
b11111111111111111111111111110110 +
b11111111111111111111111111110110 /
#49
b0 )
b0 ,
b1111111111111111111111111111111 *
b0 -
b11111111111111111111111111110111 +
b11111111111111111111111111110111 (
b11111111111111111111111111110101 /
#50
b1111111111111111111111111111110 *
b11111111111111111111111111110110 (
b11111111111111111111111111110110 +
b11111111111111111111111111110100 /
#51
b10 ,
b1111111111111111111111111111111 *
b10 -
b11111111111111111111111111110011 +
b11111111111111111111111111110101 (
b11111111111111111111111111110011 /
#52
b1111111111111111111111111111100 *
b11111111111111111111111111110100 (
b11111111111111111111111111110010 +
b11111111111111111111111111110010 /
#53
b0 ,
b1111111111111111111111111111111 *
b0 -
b11111111111111111111111111110011 +
b11111111111111111111111111110011 (
b11111111111111111111111111110001 /
#54
1'
0"
0#
0&
1%
b11 +
b11 (
b0 /
b11 .
#55
1!
b11111111111111111111111111111110 )
b1111111111111111111111111111110 *
0"
b11111111111111111111111111111111 ,
1&
0%
b11111111111111111111111111111111 +
b11 -
b10 (
b11111111111111111111111111111111 /
#56
b11111111111111111111111111111100 )
b1111111111111111111111111111111 *
b11111111111111111111111111111110 ,
b1 (
b10 -
b11111111111111111111111111111110 /
#57
1!
1$
0"
1&
b11111111111111111111111111111110 )
b0 *
b11111111111111111111111111111111 ,
b1 -
b0 (
b11111111111111111111111111111101 /
#58
0!
1"
0&
0$
b0 )
b1111111111111111111111111111111 *
b0 ,
b11111111111111111111111111111111 (
b0 -
b11111111111111111111111111111100 /
#59
b10 )
b1111111111111111111111111111110 *
b11 ,
b11111111111111111111111111111011 +
b11 -
b11111111111111111111111111111110 (
b11111111111111111111111111111011 /
#60
b0 )
b1111111111111111111111111111111 *
b10 ,
b11111111111111111111111111111101 (
b10 -
b11111111111111111111111111111010 /
#61
b10 )
b1111111111111111111111111111100 *
b11 ,
b1 -
b11111111111111111111111111111100 (
b11111111111111111111111111111001 /
#62
b0 )
b1111111111111111111111111111111 *
b0 ,
b11111111111111111111111111111011 (
b0 -
b11111111111111111111111111111000 /
#63
b110 )
b1111111111111111111111111111110 *
b111 ,
b11111111111111111111111111110111 +
b11 -
b11111111111111111111111111111010 (
b11111111111111111111111111110111 /
#64
b100 )
b1111111111111111111111111111111 *
b110 ,
b11111111111111111111111111111001 (
b10 -
b11111111111111111111111111110110 /
#65
b110 )
b1111111111111111111111111111000 *
b111 ,
b1 -
b11111111111111111111111111111000 (
b11111111111111111111111111110101 /
#66
b0 )
b1111111111111111111111111111111 *
b0 ,
b11111111111111111111111111110111 (
b0 -
b11111111111111111111111111110100 /
#67
b10 )
b1111111111111111111111111111110 *
b11 ,
b11111111111111111111111111110011 +
b11 -
b11111111111111111111111111110110 (
b11111111111111111111111111110011 /
#68
b0 )
b1111111111111111111111111111111 *
b10 ,
b11111111111111111111111111110101 (
b10 -
b11111111111111111111111111110010 /
#69
b10 )
b1111111111111111111111111111100 *
b11 ,
b1 -
b11111111111111111111111111110100 (
b11111111111111111111111111110001 /
#70
0$
1'
0"
b0 )
b1111111111111111111111111111100 *
0#
b0 ,
0&
1%
b100 +
b0 -
b100 (
b0 /
b100 .
#71
1!
b11111111111111111111111111111000 )
b11111111111111111111111111111100 ,
0"
b1111111111111111111111111111111 *
1&
0%
b100 -
b11111111111111111111111111111111 +
b11 (
b11111111111111111111111111111111 /
#72
b1111111111111111111111111111110 *
b10 (
b11111111111111111111111111111110 +
b11111111111111111111111111111110 /
#73
0$
b1111111111111111111111111111111 *
b11111111111111111111111111111101 +
b1 (
b11111111111111111111111111111101 /
#74
1$
b0 *
b0 (
b11111111111111111111111111111100 +
b11111111111111111111111111111100 /
#75
0!
1"
0&
0$
b0 )
b0 ,
b1111111111111111111111111111111 *
b0 -
b11111111111111111111111111111111 +
b11111111111111111111111111111111 (
b11111111111111111111111111111011 /
#76
b1111111111111111111111111111110 *
b11111111111111111111111111111110 (
b11111111111111111111111111111110 +
b11111111111111111111111111111010 /
#77
b1111111111111111111111111111111 *
b11111111111111111111111111111101 +
b11111111111111111111111111111101 (
b11111111111111111111111111111001 /
#78
b1111111111111111111111111111100 *
b11111111111111111111111111111100 (
b11111111111111111111111111111100 +
b11111111111111111111111111111000 /
#79
b100 ,
b1111111111111111111111111111111 *
b100 -
b11111111111111111111111111110111 +
b11111111111111111111111111111011 (
b11111111111111111111111111110111 /
#80
b1111111111111111111111111111110 *
b11111111111111111111111111111010 (
b11111111111111111111111111110110 +
b11111111111111111111111111110110 /
#81
b1111111111111111111111111111111 *
b11111111111111111111111111110101 +
b11111111111111111111111111111001 (
b11111111111111111111111111110101 /
#82
b1111111111111111111111111111000 *
b11111111111111111111111111111000 (
b11111111111111111111111111110100 +
b11111111111111111111111111110100 /
#83
b0 ,
b1111111111111111111111111111111 *
b0 -
b11111111111111111111111111110111 +
b11111111111111111111111111110111 (
b11111111111111111111111111110011 /
#84
b1111111111111111111111111111110 *
b11111111111111111111111111110110 (
b11111111111111111111111111110110 +
b11111111111111111111111111110010 /
#85
b1111111111111111111111111111111 *
b11111111111111111111111111110101 +
b11111111111111111111111111110101 (
b11111111111111111111111111110001 /
#86
1'
0"
0#
0&
1%
b101 +
b101 (
b0 /
b101 .
#87
1!
b11111111111111111111111111111110 )
b1111111111111111111111111111100 *
0"
b11111111111111111111111111111111 ,
1&
0%
b11111111111111111111111111111111 +
b101 -
b100 (
b11111111111111111111111111111111 /
#88
b11111111111111111111111111111000 )
b1111111111111111111111111111111 *
b11111111111111111111111111111100 ,
b11 (
b100 -
b11111111111111111111111111111110 /
#89
b1111111111111111111111111111110 *
b11111111111111111111111111111101 ,
b11111111111111111111111111111101 +
b101 -
b10 (
b11111111111111111111111111111101 /
#90
b1111111111111111111111111111111 *
b11111111111111111111111111111100 ,
b1 (
b100 -
b11111111111111111111111111111100 /
#91
1$
1!
0"
1&
b11111111111111111111111111111110 )
b0 *
b11111111111111111111111111111111 ,
b11111111111111111111111111111111 +
b1 -
b0 (
b11111111111111111111111111111011 /
#92
0!
1"
0&
0$
b0 )
b1111111111111111111111111111111 *
b0 ,
b11111111111111111111111111111111 (
b0 -
b11111111111111111111111111111010 /
#93
b1111111111111111111111111111110 *
b1 ,
b11111111111111111111111111111101 +
b1 -
b11111111111111111111111111111110 (
b11111111111111111111111111111001 /
#94
b1111111111111111111111111111111 *
b0 ,
b11111111111111111111111111111101 (
b0 -
b11111111111111111111111111111000 /
#95
b110 )
b1111111111111111111111111111100 *
b111 ,
b11111111111111111111111111110111 +
b101 -
b11111111111111111111111111111100 (
b11111111111111111111111111110111 /
#96
b0 )
b1111111111111111111111111111111 *
b100 ,
b11111111111111111111111111111011 (
b100 -
b11111111111111111111111111110110 /
#97
b1111111111111111111111111111110 *
b101 ,
b11111111111111111111111111110101 +
b101 -
b11111111111111111111111111111010 (
b11111111111111111111111111110101 /
#98
b1111111111111111111111111111111 *
b100 ,
b11111111111111111111111111111001 (
b100 -
b11111111111111111111111111110100 /
#99
b110 )
b1111111111111111111111111111000 *
b111 ,
b11111111111111111111111111110111 +
b1 -
b11111111111111111111111111111000 (
b11111111111111111111111111110011 /
#100
b0 )
b1111111111111111111111111111111 *
b0 ,
b11111111111111111111111111110111 (
b0 -
b11111111111111111111111111110010 /
#101
b1111111111111111111111111111110 *
b1 ,
b11111111111111111111111111110101 +
b1 -
b11111111111111111111111111110110 (
b11111111111111111111111111110001 /
#102
1'
0"
b0 )
b1111111111111111111111111111110 *
0#
b0 ,
0&
1%
b110 +
b0 -
b110 (
b0 /
b110 .
#103
1!
b11111111111111111111111111111100 )
b11111111111111111111111111111110 ,
0"
b1111111111111111111111111111111 *
1&
0%
b110 -
b11111111111111111111111111111111 +
b101 (
b11111111111111111111111111111111 /
#104
b1111111111111111111111111111100 *
b100 (
b11111111111111111111111111111110 +
b11111111111111111111111111111110 /
#105
b11111111111111111111111111111000 )
b11111111111111111111111111111100 ,
b1111111111111111111111111111111 *
b100 -
b11111111111111111111111111111111 +
b11 (
b11111111111111111111111111111101 /
#106
b1111111111111111111111111111110 *
b10 (
b11111111111111111111111111111110 +
b11111111111111111111111111111100 /
#107
1!
0"
1&
b11111111111111111111111111111100 )
b11111111111111111111111111111110 ,
b1111111111111111111111111111111 *
b10 -
b11111111111111111111111111111111 +
b1 (
b11111111111111111111111111111011 /
#108
1$
b0 *
b0 (
b11111111111111111111111111111110 +
b11111111111111111111111111111010 /
#109
0!
1"
0&
0$
b0 )
b0 ,
b1111111111111111111111111111111 *
b0 -
b11111111111111111111111111111111 +
b11111111111111111111111111111111 (
b11111111111111111111111111111001 /
#110
b1111111111111111111111111111110 *
b11111111111111111111111111111110 (
b11111111111111111111111111111110 +
b11111111111111111111111111111000 /
#111
b100 )
b110 ,
b1111111111111111111111111111111 *
b110 -
b11111111111111111111111111110111 +
b11111111111111111111111111111101 (
b11111111111111111111111111110111 /
#112
b1111111111111111111111111111100 *
b11111111111111111111111111111100 (
b11111111111111111111111111110110 +
b11111111111111111111111111110110 /
#113
b0 )
b100 ,
b1111111111111111111111111111111 *
b100 -
b11111111111111111111111111110111 +
b11111111111111111111111111111011 (
b11111111111111111111111111110101 /
#114
b1111111111111111111111111111110 *
b11111111111111111111111111111010 (
b11111111111111111111111111110110 +
b11111111111111111111111111110100 /
#115
b100 )
b110 ,
b1111111111111111111111111111111 *
b10 -
b11111111111111111111111111110111 +
b11111111111111111111111111111001 (
b11111111111111111111111111110011 /
#116
b1111111111111111111111111111000 *
b11111111111111111111111111111000 (
b11111111111111111111111111110110 +
b11111111111111111111111111110010 /
#117
b0 )
b0 ,
b1111111111111111111111111111111 *
b0 -
b11111111111111111111111111110111 +
b11111111111111111111111111110111 (
b11111111111111111111111111110001 /
#118
1'
0"
0#
0&
1%
b111 +
b111 (
b0 /
b111 .
#119
1!
b11111111111111111111111111111110 )
b1111111111111111111111111111110 *
0"
b11111111111111111111111111111111 ,
1&
0%
b11111111111111111111111111111111 +
b111 -
b110 (
b11111111111111111111111111111111 /
#120
b11111111111111111111111111111100 )
b1111111111111111111111111111111 *
b11111111111111111111111111111110 ,
b101 (
b110 -
b11111111111111111111111111111110 /
#121
0$
b11111111111111111111111111111110 )
b1111111111111111111111111111100 *
b11111111111111111111111111111111 ,
b101 -
b100 (
b11111111111111111111111111111101 /
#122
b11111111111111111111111111111000 )
b1111111111111111111111111111111 *
b11111111111111111111111111111100 ,
b11 (
b100 -
b11111111111111111111111111111100 /
#123
1!
0"
1&
b11111111111111111111111111111110 )
b1111111111111111111111111111110 *
b11111111111111111111111111111111 ,
b11 -
b10 (
b11111111111111111111111111111011 /
#124
b11111111111111111111111111111100 )
b1111111111111111111111111111111 *
b11111111111111111111111111111110 ,
b1 (
b10 -
b11111111111111111111111111111010 /
#125
1!
1$
0"
1&
b11111111111111111111111111111110 )
b0 *
b11111111111111111111111111111111 ,
b1 -
b0 (
b11111111111111111111111111111001 /
#126
0!
1"
0&
0$
b0 )
b1111111111111111111111111111111 *
b0 ,
b11111111111111111111111111111111 (
b0 -
b11111111111111111111111111111000 /
#127
b110 )
b1111111111111111111111111111110 *
b111 ,
b11111111111111111111111111110111 +
b111 -
b11111111111111111111111111111110 (
b11111111111111111111111111110111 /
#128
b100 )
b1111111111111111111111111111111 *
b110 ,
b11111111111111111111111111111101 (
b110 -
b11111111111111111111111111110110 /
#129
b110 )
b1111111111111111111111111111100 *
b111 ,
b101 -
b11111111111111111111111111111100 (
b11111111111111111111111111110101 /
#130
b0 )
b1111111111111111111111111111111 *
b100 ,
b11111111111111111111111111111011 (
b100 -
b11111111111111111111111111110100 /
#131
b110 )
b1111111111111111111111111111110 *
b111 ,
b11 -
b11111111111111111111111111111010 (
b11111111111111111111111111110011 /
#132
b100 )
b1111111111111111111111111111111 *
b110 ,
b11111111111111111111111111111001 (
b10 -
b11111111111111111111111111110010 /
#133
b110 )
b1111111111111111111111111111000 *
b111 ,
b1 -
b11111111111111111111111111111000 (
b11111111111111111111111111110001 /
#134
0$
1'
0"
b0 )
b1111111111111111111111111111000 *
0#
b0 ,
0&
1%
b1000 +
b0 -
b1000 (
b0 /
b1000 .
#135
1!
b11111111111111111111111111110000 )
b11111111111111111111111111111000 ,
0"
b1111111111111111111111111111111 *
1&
0%
b1000 -
b11111111111111111111111111111111 +
b111 (
b11111111111111111111111111111111 /
#136
b1111111111111111111111111111110 *
b110 (
b11111111111111111111111111111110 +
b11111111111111111111111111111110 /
#137
b1111111111111111111111111111111 *
b11111111111111111111111111111101 +
b101 (
b11111111111111111111111111111101 /
#138
b1111111111111111111111111111100 *
b100 (
b11111111111111111111111111111100 +
b11111111111111111111111111111100 /
#139
0$
b1111111111111111111111111111111 *
b11111111111111111111111111111011 +
b11 (
b11111111111111111111111111111011 /
#140
b1111111111111111111111111111110 *
b10 (
b11111111111111111111111111111010 +
b11111111111111111111111111111010 /
#141
0$
b1111111111111111111111111111111 *
b11111111111111111111111111111001 +
b1 (
b11111111111111111111111111111001 /
#142
1$
b0 *
b0 (
b11111111111111111111111111111000 +
b11111111111111111111111111111000 /
#143
0!
1"
0&
0$
b0 )
b0 ,
b1111111111111111111111111111111 *
b0 -
b11111111111111111111111111111111 +
b11111111111111111111111111111111 (
b11111111111111111111111111110111 /
#144
b1111111111111111111111111111110 *
b11111111111111111111111111111110 (
b11111111111111111111111111111110 +
b11111111111111111111111111110110 /
#145
b1111111111111111111111111111111 *
b11111111111111111111111111111101 +
b11111111111111111111111111111101 (
b11111111111111111111111111110101 /
#146
b1111111111111111111111111111100 *
b11111111111111111111111111111100 (
b11111111111111111111111111111100 +
b11111111111111111111111111110100 /
#147
b1111111111111111111111111111111 *
b11111111111111111111111111111011 +
b11111111111111111111111111111011 (
b11111111111111111111111111110011 /
#148
b1111111111111111111111111111110 *
b11111111111111111111111111111010 (
b11111111111111111111111111111010 +
b11111111111111111111111111110010 /
#149
b1111111111111111111111111111111 *
b11111111111111111111111111111001 +
b11111111111111111111111111111001 (
b11111111111111111111111111110001 /
#150
1'
0"
0#
0&
1%
b1001 +
b1001 (
b0 /
b1001 .
#151
1!
b11111111111111111111111111111110 )
b1111111111111111111111111111000 *
0"
b11111111111111111111111111111111 ,
1&
0%
b11111111111111111111111111111111 +
b1001 -
b1000 (
b11111111111111111111111111111111 /
#152
b11111111111111111111111111110000 )
b1111111111111111111111111111111 *
b11111111111111111111111111111000 ,
b111 (
b1000 -
b11111111111111111111111111111110 /
#153
b1111111111111111111111111111110 *
b11111111111111111111111111111001 ,
b11111111111111111111111111111101 +
b1001 -
b110 (
b11111111111111111111111111111101 /
#154
b1111111111111111111111111111111 *
b11111111111111111111111111111000 ,
b101 (
b1000 -
b11111111111111111111111111111100 /
#155
0$
b11111111111111111111111111110010 )
b1111111111111111111111111111100 *
b11111111111111111111111111111011 ,
b11111111111111111111111111111011 +
b1001 -
b100 (
b11111111111111111111111111111011 /
#156
b11111111111111111111111111110000 )
b1111111111111111111111111111111 *
b11111111111111111111111111111000 ,
b11 (
b1000 -
b11111111111111111111111111111010 /
#157
b1111111111111111111111111111110 *
b11111111111111111111111111111001 ,
b11111111111111111111111111111001 +
b1001 -
b10 (
b11111111111111111111111111111001 /
#158
b1111111111111111111111111111111 *
b11111111111111111111111111111000 ,
b1 (
b1000 -
b11111111111111111111111111111000 /
#159
1$
1!
0"
1&
b11111111111111111111111111111110 )
b0 *
b11111111111111111111111111111111 ,
b11111111111111111111111111111111 +
b1 -
b0 (
b11111111111111111111111111110111 /
#160
0!
1"
0&
0$
b0 )
b1111111111111111111111111111111 *
b0 ,
b11111111111111111111111111111111 (
b0 -
b11111111111111111111111111110110 /
#161
b1111111111111111111111111111110 *
b1 ,
b11111111111111111111111111111101 +
b1 -
b11111111111111111111111111111110 (
b11111111111111111111111111110101 /
#162
b1111111111111111111111111111111 *
b0 ,
b11111111111111111111111111111101 (
b0 -
b11111111111111111111111111110100 /
#163
b10 )
b1111111111111111111111111111100 *
b11 ,
b11111111111111111111111111111011 +
b1 -
b11111111111111111111111111111100 (
b11111111111111111111111111110011 /
#164
b0 )
b1111111111111111111111111111111 *
b0 ,
b11111111111111111111111111111011 (
b0 -
b11111111111111111111111111110010 /
#165
b1111111111111111111111111111110 *
b1 ,
b11111111111111111111111111111001 +
b1 -
b11111111111111111111111111111010 (
b11111111111111111111111111110001 /
#166
1'
0"
b0 )
b1111111111111111111111111111110 *
0#
b0 ,
0&
1%
b1010 +
b0 -
b1010 (
b0 /
b1010 .
