Lab5/verilog/buffers/mem_wb_buffer.v
/*
Author: Adolfo Pineda
Title: Memory / Writeback Buffer Registers
Summary: Buffer stores data, addresses, control signals, and instrutions between
   the Memory and Writeback stages of a pipelined CPU
*/


module mem_wb_buffer( 
         clk,
         rst,
         wb_ctrl,
         alu_data,
         mem_data,
         instruction,
         wb_ctrl_out,
         alu_data_out,
         mem_data_out,
         instruction_out
);
	
   // INPUT
   // buffer control
	input wire clk, rst;
   // cpu control in
   input wire [2:0] wb_ctrl;
   // data in
	input wire [31:0] alu_data, mem_data;
	// instr in
   input wire [31:0] instruction;
	// OUTPUT
   // cpu control out
	output reg [2:0]  wb_ctrl_out;
   // data out
	output reg [31:0] alu_data_out, mem_data_out;
	// instr out
   output reg [31:0] instruction_out;
	
   
	initial begin
		wb_ctrl_out = 3'b0;  // no write
		alu_data_out = 7'b0;
		mem_data_out = 32'b0;
		instruction_out = 32'b0;
	end
	always @(posedge clk or negedge rst) begin
		if (!rst) begin;
         wb_ctrl_out <= 3'b0; 
			alu_data_out <= 7'b0;
			mem_data_out <= 32'b0;
			instruction_out <= 32'b0;
		end
      else begin
			wb_ctrl_out <= wb_ctrl;
			alu_data_out <= alu_data;
			mem_data_out <= mem_data;
			instruction_out <= instruction;
		end
	end
endmodule

Lab5/verilog/buffers/ex_mem_buffer.v
/*
Author: Adolfo Pineda
Title: Execution / Memory Buffer Registers
Summary: Buffer stores data, addresses, control signals, and instrutions between
   the Execution and Memory stages of a pipelined CPU
*/


module ex_mem_buffer( 
         clk,
         rst,
         mem_fwd,
         wb_ctrl,
         mem_ctrl,
         alu_data,
         data_to_mem,
         mem_data_forward,
         instruction,
         wb_ctrl_out,
         mem_ctrl_out,
         alu_data_out,
         data_to_mem_out,
         instruction_out
);
   // INPUT
   // buffer control
	input wire clk, rst, mem_fwd;
   // cpu control in
   input wire [2:0] wb_ctrl, mem_ctrl;
   // data in
	input wire [31:0] alu_data, data_to_mem, mem_data_forward;
	// instr in
   input wire [31:0] instruction;
	// OUTPUT
   // cpu control out
	output reg [2:0]  wb_ctrl_out, mem_ctrl_out;
   // data out
	output reg [31:0] alu_data_out, data_to_mem_out;
	// instr out
   output reg [31:0] instruction_out;
	// INTERNAL
   wire [31:0] data_to_mem_saved;
   
   
   // forward data mux
   assign data_to_mem_saved = mem_fwd ? mem_data_forward : data_to_mem;
   
   // storage logic
	initial begin
		wb_ctrl_out = 3'b0;  // no write
		mem_ctrl_out = 3'b100;  // cs high disable mem
		alu_data_out = 7'b0;
		data_to_mem_out = 32'b0;
		instruction_out = 32'b0;
	end
	always @(posedge clk or negedge rst) begin
		if (!rst) begin;
         wb_ctrl_out <= 3'b0; 
         mem_ctrl_out <= 3'b100;
			alu_data_out <= 7'b0;
			data_to_mem_out <= 32'b0;
			instruction_out <= 32'b0;
		end
      else begin
			wb_ctrl_out <= wb_ctrl; 
			mem_ctrl_out <= mem_ctrl;
			alu_data_out <= alu_data;
			data_to_mem_out <= data_to_mem_saved;
			instruction_out <= instruction;
		end
	end
endmodule

Lab5/verilog/buffers/id_ex_buffer.v
/*
Author: Adolfo Pineda
Title: Instruction Decode / Execution Buffer Registers
Summary: Buffer stores read_data, addresses, control signals, and instrutions 
   between the Instruction Decode and Execution stages of a pipelined CPU
*/


module id_ex_buffer( 
         clk,
         stall,
         rst,
         wb_ctrl,
         mem_ctrl,
         ex_ctrl,
         r_data_0,
         r_data_1,
         instruction,
         wb_ctrl_out, 
         mem_ctrl_out,
         ex_ctrl_out,
         wb_ctrl_saved, 
         mem_ctrl_saved,
         ex_ctrl_saved,
         r_data_0_out,
         r_data_1_out,
         instruction_out,
         instruction_saved
);
   // INPUT
   // buffer control
   input wire clk, stall, rst;
   // control in
	input wire [2:0] wb_ctrl, mem_ctrl;
	input wire [6:0] ex_ctrl;
   // data in
	input wire [31:0] r_data_0, r_data_1;
	// instruction in
   input wire [31:0] instruction;
	// OUTPUT
   // control out
   output wire [2:0] wb_ctrl_out, mem_ctrl_out;  // to id stage
   output wire [6:0] ex_ctrl_out;  // to id stage
	output reg [2:0] wb_ctrl_saved, mem_ctrl_saved;  // checked by data fwd
	output reg [6:0] ex_ctrl_saved;  // checked by data fwd
   // data out
	output reg [31:0] r_data_0_out, r_data_1_out;
	// instruction out
   output wire [31:0] instruction_out;
   output reg [31:0] instruction_saved;
	
   
   // output logic (incorporate stall)
   assign wb_ctrl_out = stall ? 3'b011 : wb_ctrl_saved;
   assign mem_ctrl_out = stall ? 3'b100 : mem_ctrl_saved;
   assign ex_ctrl_out = stall ? 7'b0 : ex_ctrl_saved;
   assign instruction_out = stall ? 32'b0 : instruction_saved;
   
   // storage logic
	initial begin
		wb_ctrl_saved = 3'b0;  // no write
		mem_ctrl_saved = 3'b100;  // cs high disable mem
		ex_ctrl_saved = 7'b0;  // NOP
		r_data_0_out = 32'b0;
		r_data_1_out = 32'b0;
		instruction_saved = 32'b0;
	end
	always @(posedge clk or negedge rst) begin
		if (!rst) begin;
         wb_ctrl_saved <= 3'b0; 
         mem_ctrl_saved <= 3'b100;
         ex_ctrl_saved <= 7'b0;
         r_data_0_out <= 32'b0;
         r_data_1_out <= 32'b0;
         instruction_saved <= 32'b0;
		end 
      else if (stall) begin
         wb_ctrl_saved <= wb_ctrl_saved; 
         mem_ctrl_saved <= mem_ctrl_saved;
         ex_ctrl_saved <= ex_ctrl_saved;
         r_data_0_out <= r_data_0_out;
         r_data_1_out <= r_data_1_out;
         instruction_saved <= instruction_saved;
      end
      else begin
			wb_ctrl_saved <= wb_ctrl; 
         mem_ctrl_saved <= mem_ctrl;
         ex_ctrl_saved <= ex_ctrl;
         r_data_0_out <= r_data_0;
         r_data_1_out <= r_data_1;
         instruction_saved <= instruction;
		end
	end
endmodule

Lab5/verilog/buffers/if_id_buffer.v
/*
Author: Ian Gilman
Title: Instruction Fetch / Instruction Decode Buffer Registers
Summary: Buffer stores instrution between the Instruction Fetch and Instruction
   Decode stages of a pipelined CPU
*/


module if_id_buffer(
         clk,
         rst,
         stall,
         instruction,
         instruction_out,
         instruction_saved
);
   // INPUT
   // buffer control
   input wire clk, rst, stall;  // clock, reset buf data, stall buf changes
   // instruction
   input wire [31:0] instruction;
   // OUTPUT
   output wire [31:0] instruction_out;  // instr to id stage
   output reg [31:0]  instruction_saved;  // instr checked by data fwd
   
   
   // instruction output logic (incorporate stall)
   assign instruction_out = stall ? 32'b0 : instruction_saved;
   
   // instruction storage logic
   initial begin
      instruction_saved = 32'b0;
   end
   always @(posedge clk or negedge rst) begin
      if(!rst)
         instruction_saved <= 32'b0;
      else if(stall)
         instruction_saved <= instruction_saved;
      else
         instruction_saved <= instruction;
   end
endmodule

Lab5/verilog/buffers/buffer_tester.v
/*
Author: Ian Gilman
Title: Pipelined CPU Buffer Tester
Summary: Provides stimulus signals to test the behavior of the buffers in a
   pipelined CPU
*/


module buffer_tester(
         clk,
         rst,
         if_id_stall,
         id_ex_stall,
         ex_mem_fwd,
         instruction,
         wb_ctrl,
         mem_ctrl,
         ex_ctrl,
         fr_d0,
         fr_d1,
         alu_data,
         data_to_mem,
         mem_data_fwd,
         data_from_mem
);
// OUTPUT
   output reg clk, rst, if_id_stall, id_ex_stall, ex_mem_fwd;  // buffer controls
   output reg [31:0] instruction, fr_d0, fr_d1, alu_data, data_to_mem, 
                     mem_data_fwd, data_from_mem;
   output reg [2:0] wb_ctrl, mem_ctrl;
   output reg [6:0] ex_ctrl;
// INTERNAL
   parameter delay = 10;
   
   
// Stimulus signal logic
   // clock
   always begin
      #delay; clk <= ~clk;
   end
   
   initial begin
      // initial conditions
      clk <= 1;
      rst <= 0;
      rst <= 1;
      if_id_stall <= 0;
      id_ex_stall <= 0;
      ex_mem_fwd <= 0;
      instruction <= 0;
      wb_ctrl <= 3'b0;
      ex_ctrl <= 6'b1;
      mem_ctrl <= 3'b100;
      alu_data <= 0;
      data_to_mem <= 0;
      mem_data_fwd <= 0;
      data_from_mem <= 0;
      
      // reset
      @(posedge clk);
      rst = 0;
      @(posedge clk);
      rst = 1;
      
      // 1ST
      @(posedge clk);
      // if
      instruction <= 32'h70000000;
      
      // 2ND
      @(posedge clk);
      // if
      instruction <= 32'h60000000;
      // id
      wb_ctrl <= 3'b100;
      ex_ctrl <= 6'b1;
      mem_ctrl <= 3'b010;
      fr_d0 <= 32'h30303030;
      fr_d1 <= 32'h06060606;
      
      // 3RD
      @(posedge clk);
      // if
      instruction <= 32'h80000000;
      // id
      wb_ctrl <= 3'b101;
      ex_ctrl <= 6'h2;
      mem_ctrl <= 3'b001;
      fr_d0 <= 32'h23;
      fr_d1 <= 32'h62;
      // ex
      alu_data <= 32'h30303030 + 32'h06060606;
      data_to_mem <= 32'b1;
      mem_data_fwd <= 32'h2;
      
      // 4TH
      @(posedge clk);
      // if
      instruction <= 32'h00000012;
      // id
      wb_ctrl <= 3'b100;
      ex_ctrl <= 6'h0;
      mem_ctrl <= 3'b000;
      fr_d0 <= 32'b1010;
      fr_d1 <= 32'h2;
      // ex
      alu_data <= 32'h23 > 32'h62;
      data_to_mem <= 32'h5;
      mem_data_fwd <= 32'h6;
      // mem
      data_from_mem <= 32'h3;
      
      // 5TH
      @(posedge clk);
      // control / hazard
      if_id_stall <= 1;
      // if
      instruction <= 32'h20000000;
      // id
      wb_ctrl <= 3'b101;
      ex_ctrl <= 6'h03;
      mem_ctrl <= 3'b111;
      fr_d0 <= 32'h13;
      fr_d1 <= 32'h3;
      // ex
      alu_data <= 32'b1010 << 32'h2;
      data_to_mem <= 32'h2;
      mem_data_fwd <= 32'h45;
      // mem
      data_from_mem <= 32'h4;
      
      // 6TH
      @(posedge clk);
      // control / hazard
      if_id_stall <= 0;
      ex_mem_fwd <= 1;
      // if
      instruction <= 32'h19000000;
      // id
      wb_ctrl <= 3'b111;
      ex_ctrl <= 6'h04;
      mem_ctrl <= 3'b100;
      fr_d0 <= 32'h71;
      fr_d1 <= 32'b0;
      // ex
      alu_data <= 32'h13 - 32'h3;
      data_to_mem <= 32'h0;
      mem_data_fwd <= 32'h14;
      // mem
      data_from_mem <= 32'h3;
      
      // 7TH
      @(posedge clk);
      // control / hazard
      ex_mem_fwd <= 0;
      id_ex_stall <= 1;
      // if
      instruction <= 32'h40000000;
      // id
      wb_ctrl <= 3'b010;
      ex_ctrl <= 6'h02;
      mem_ctrl <= 3'b001;
      fr_d0 <= 32'h22;
      fr_d1 <= 32'h378;
      // ex
      alu_data <= 32'h71 + 32'h0;
      data_to_mem <= 32'h1;
      mem_data_fwd <= 32'h8;
      // mem
      data_from_mem <= 32'h7;
      
      // 8TH
      @(posedge clk);
      // control / hazard
      if_id_stall <= 1;
      id_ex_stall <= 1;
      // if
      instruction <= 32'h13000000;
      // id
      wb_ctrl <= 3'b100;
      ex_ctrl <= 6'h0;
      mem_ctrl <= 3'b000;
      fr_d0 <= 32'b1010;
      fr_d1 <= 32'h2;
      // ex
      alu_data <= 32'h23 > 32'h62;
      data_to_mem <= 32'h5;
      mem_data_fwd <= 32'h6;
      // mem
      data_from_mem <= 32'h3;
      
      @(posedge clk);
      $finish;
   end
   
endmodule

Lab5/verilog/buffers/buffer_testbench.v
/*
Author:  Ian Gilman
Title:   Pipelined CPU Buffers Testbench
Summary: Links cpu buffers under test with test stimulus, record dut signals 
   response to stimulus
*/

// Module Dependencies
`include "if_id_buffer.v"
`include "id_ex_buffer.v"
`include "ex_mem_buffer.v"
`include "mem_wb_buffer.v"
`include "buffer_tester.v"


module buffer_testbench();
   // buffer control signals
   wire clk, rst, if_id_stall, id_ex_stall, ex_mem_fwd;
   // instructions between buffers
   wire [31:0] if_instruction, id_instruction, ex_instruction, mem_instruction,
               wb_instruction;
   // instructions saved for forwarding
   wire [31:0] if_id_instruction_saved, id_ex_instruction_saved;
   // writeback control signals between buffers
   wire [2:0] id_wb_ctrl, ex_wb_ctrl, mem_wb_ctrl, wb_wb_ctrl; 
   // writeback control signal saved for data forwarding
   wire [2:0] id_ex_wb_ctrl_saved;
   // memory control signals between buffers
   wire [2:0] id_mem_ctrl, ex_mem_ctrl, mem_mem_ctrl;
   // memory control signal saved for data forwarding
   wire [2:0] id_ex_mem_ctrl_saved;
   // execution control signals between buffers
   wire [6:0] id_ex_ctrl, ex_ex_ctrl;
   // execution control signal save for data forwarding
   wire [6:0] id_ex_ex_ctrl_saved;
   // file register data between buffers
   wire [31:0] id_fr_d0, id_fr_d1, ex_fr_d0, ex_fr_d1;
   // alu data between buffers
   wire [31:0] ex_alu_data, mem_alu_data, wb_alu_data;
   // memory bus data between buffers
   wire [31:0] ex_data_to_mem, mem_data_to_mem, mem_data_from_mem, 
               wb_data_from_mem;
   // memory data forwarded to buffer
   wire [31:0] ex_mem_data_fwd;
   
   
 // Buffer Tester
   buffer_tester tester(
      .clk(clk),
      .rst(rst),
      .if_id_stall(if_id_stall),
      .id_ex_stall(id_ex_stall),
      .ex_mem_fwd(ex_mem_fwd),
      .instruction(if_instruction),
      .wb_ctrl(id_wb_ctrl),
      .mem_ctrl(id_mem_ctrl),
      .ex_ctrl(id_ex_ctrl),
      .fr_d0(id_fr_d0),
      .fr_d1(id_fr_d1),
      .alu_data(ex_alu_data),
      .data_to_mem(ex_data_to_mem),
      .mem_data_fwd(ex_mem_data_fwd),
      .data_from_mem(mem_data_from_mem)
   );

 // Buffer Devies under Test
   // INSTRUCTION_FETCH/INSTRUCTION_DECODE Intermediary Buffer
   if_id_buffer if_id_dut(
      .clk(clk),
      .rst(rst),
      .stall(if_id_stall),
      .instruction(if_instruction),
      .instruction_out(id_instruction),
      .instruction_saved(if_id_instruction_saved)
   );
   // INSTRUCTION_DECODE/EXECUTION Intermediary Buffer
   id_ex_buffer id_ex_dut( 
      .clk(clk),
      .stall(id_ex_stall),
      .rst(rst),
      .wb_ctrl(id_wb_ctrl),
      .mem_ctrl(id_mem_ctrl),
      .ex_ctrl(id_ex_ctrl),
      .r_data_0(id_fr_d0),
      .r_data_1(id_fr_d1),
      .instruction(id_instruction),
      .wb_ctrl_out(ex_wb_ctrl), 
      .mem_ctrl_out(ex_mem_ctrl),
      .ex_ctrl_out(ex_ex_ctrl),
      .wb_ctrl_saved(id_ex_wb_ctrl_saved), 
      .mem_ctrl_saved(id_ex_mem_ctrl_saved),
      .ex_ctrl_saved(id_ex_ex_ctrl_saved),
      .r_data_0_out(ex_fr_d0),
      .r_data_1_out(ex_fr_d1),
      .instruction_out(ex_instruction),
      .instruction_saved(id_ex_instruction_saved)
   );
   // EXECUTION/MEMORY Intermediary Buffer
   ex_mem_buffer ex_mem_dut( 
      .clk(clk),
      .rst(rst),
      .mem_fwd(ex_mem_fwd),
      .wb_ctrl(ex_wb_ctrl),
      .mem_ctrl(ex_mem_ctrl),
      .alu_data(ex_alu_data),
      .data_to_mem(ex_data_to_mem),
      .mem_data_forward(ex_mem_data_fwd),
      .instruction(ex_instruction),
      .wb_ctrl_out(mem_wb_ctrl),
      .mem_ctrl_out(mem_mem_ctrl),
      .alu_data_out(mem_alu_data),
      .data_to_mem_out(mem_data_to_mem),
      .instruction_out(mem_instruction)
   );
   // MEMORY/WRITEBACK Intermediary Buffer
   mem_wb_buffer mem_wb_dut( 
      .clk(clk),
      .rst(rst),
      .wb_ctrl(mem_wb_ctrl),
      .alu_data(mem_alu_data),
      .mem_data(mem_data_from_mem),
      .instruction(mem_instruction),
      .wb_ctrl_out(wb_wb_ctrl),
      .alu_data_out(wb_alu_data),
      .mem_data_out(wb_data_from_mem),
      .instruction_out(wb_instruction)
   );
   
   
   // Collect DUT signal data
   initial begin
      $dumpfile("buffer_test.vcd");
      $dumpvars(0, if_id_dut, id_ex_dut, ex_mem_dut, mem_wb_dut);
   end
endmodule

Lab5/verilog/buffers/buffer_test.vcd
$date
	Fri Jun 03 15:58:27 2016
$end
$version
	Icarus Verilog
$end
$timescale
	1s
$end
$scope module buffer_testbench $end
$scope module if_id_dut $end
$var wire 1 ! stall $end
$var wire 1 " rst $end
$var wire 32 # instruction_out [31:0] $end
$var wire 32 $ instruction [31:0] $end
$var wire 1 % clk $end
$var reg 32 & instruction_saved [31:0] $end
$upscope $end
$upscope $end
$scope module buffer_testbench $end
$scope module id_ex_dut $end
$var wire 3 ' wb_ctrl_out [2:0] $end
$var wire 3 ( wb_ctrl [2:0] $end
$var wire 1 ) stall $end
$var wire 1 " rst $end
$var wire 32 * r_data_1 [31:0] $end
$var wire 32 + r_data_0 [31:0] $end
$var wire 3 , mem_ctrl_out [2:0] $end
$var wire 3 - mem_ctrl [2:0] $end
$var wire 32 . instruction_out [31:0] $end
$var wire 32 / instruction [31:0] $end
$var wire 7 0 ex_ctrl_out [6:0] $end
$var wire 7 1 ex_ctrl [6:0] $end
$var wire 1 % clk $end
$var reg 7 2 ex_ctrl_saved [6:0] $end
$var reg 32 3 instruction_saved [31:0] $end
$var reg 3 4 mem_ctrl_saved [2:0] $end
$var reg 32 5 r_data_0_out [31:0] $end
$var reg 32 6 r_data_1_out [31:0] $end
$var reg 3 7 wb_ctrl_saved [2:0] $end
$upscope $end
$upscope $end
$scope module buffer_testbench $end
$scope module ex_mem_dut $end
$var wire 3 8 wb_ctrl [2:0] $end
$var wire 1 " rst $end
$var wire 1 9 mem_fwd $end
$var wire 32 : mem_data_forward [31:0] $end
$var wire 3 ; mem_ctrl [2:0] $end
$var wire 32 < instruction [31:0] $end
$var wire 32 = data_to_mem_saved [31:0] $end
$var wire 32 > data_to_mem [31:0] $end
$var wire 1 % clk $end
$var wire 32 ? alu_data [31:0] $end
$var reg 32 @ alu_data_out [31:0] $end
$var reg 32 A data_to_mem_out [31:0] $end
$var reg 32 B instruction_out [31:0] $end
$var reg 3 C mem_ctrl_out [2:0] $end
$var reg 3 D wb_ctrl_out [2:0] $end
$upscope $end
$upscope $end
$scope module buffer_testbench $end
$scope module mem_wb_dut $end
$var wire 32 E alu_data [31:0] $end
$var wire 32 F instruction [31:0] $end
$var wire 3 G wb_ctrl [2:0] $end
$var wire 1 " rst $end
$var wire 32 H mem_data [31:0] $end
$var wire 1 % clk $end
$var reg 32 I alu_data_out [31:0] $end
$var reg 32 J instruction_out [31:0] $end
$var reg 32 K mem_data_out [31:0] $end
$var reg 3 L wb_ctrl_out [2:0] $end
$upscope $end
$upscope $end
$enddefinitions $end
#0
$dumpvars
b0 L
b0 K
b0 J
b0 I
b0 H
b0 G
b0 F
b0 E
b0 D
b100 C
b0 B
b0 A
b0 @
b0 ?
b0 >
b0 =
b0 <
b100 ;
b0 :
09
b0 8
b0 7
b0 6
b0 5
b100 4
b0 3
b0 2
b1 1
b0 0
b0 /
b0 .
b100 -
b100 ,
bx +
bx *
0)
b0 (
b0 '
b0 &
1%
b0 $
b0 #
0"
0!
$end
#10
0%
#20
b1 0
bx 6
bx 5
b1 2
1"
1%
#30
0%
#40
b1110000000000000000000000000000 $
1%
#50
0%
#60
b1110000000000000000000000000000 #
b1110000000000000000000000000000 /
b1110000000000000000000000000000 &
b110000001100000011000000110 *
b110000001100000011000000110000 +
b10 -
b100 (
b1100000000000000000000000000000 $
1%
#70
0%
#80
b1100000000000000000000000000000 #
b1100000000000000000000000000000 /
b1110000000000000000000000000000 .
b1110000000000000000000000000000 <
b10 ,
b10 ;
b100 '
b100 8
b1 =
b1100000000000000000000000000000 &
b1110000000000000000000000000000 3
b110000001100000011000000110 6
b110000001100000011000000110000 5
b10 4
b100 7
b10 :
b1 >
b110110001101100011011000110110 ?
b1100010 *
b100011 +
b1 -
b10 1
b101 (
b10000000000000000000000000000000 $
1%
#90
0%
#100
b1100000000000000000000000000000 .
b1100000000000000000000000000000 <
b10 0
b1 ,
b1 ;
b101 '
b101 8
b10000000000000000000000000000000 #
b10000000000000000000000000000000 /
b101 =
b1110000000000000000000000000000 B
b1110000000000000000000000000000 F
b1 A
b110110001101100011011000110110 @
b110110001101100011011000110110 E
b10 C
b100 D
b100 G
b1100000000000000000000000000000 3
b1100010 6
b100011 5
b10 2
b1 4
b101 7
b10000000000000000000000000000000 &
b11 H
b110 :
b101 >
b0 ?
b10 *
b1010 +
b0 -
b0 1
b100 (
b10010 $
1%
#110
0%
#120
b10000000000000000000000000000000 .
b10000000000000000000000000000000 <
b0 0
b0 ,
b0 ;
b100 '
b100 8
b10 =
b0 #
b0 /
b10010 &
b10000000000000000000000000000000 3
b10 6
b1010 5
b0 2
b0 4
b100 7
b1100000000000000000000000000000 B
b1100000000000000000000000000000 F
b101 A
b0 @
b0 E
b1 C
b101 D
b101 G
b1110000000000000000000000000000 J
b11 K
b110110001101100011011000110110 I
b100 L
b100 H
b1000101 :
b10 >
b101000 ?
b11 *
b10011 +
b111 -
b11 1
b101 (
b100000000000000000000000000000 $
1!
1%
#130
0%
#140
b0 .
b0 <
b11 0
b111 ,
b111 ;
b101 '
b101 8
b10100 =
b10010 #
b10010 /
b1100000000000000000000000000000 J
b100 K
b0 I
b101 L
b10000000000000000000000000000000 B
b10000000000000000000000000000000 F
b10 A
b101000 @
b101000 E
b0 C
b100 D
b100 G
b0 3
b11 6
b10011 5
b11 2
b111 4
b101 7
b11 H
b10100 :
b0 >
b10000 ?
b0 *
b1110001 +
b100 -
b100 1
b111 (
b11001000000000000000000000000 $
19
0!
1%
#150
0%
#160
b11001000000000000000000000000 #
b11001000000000000000000000000 /
b0 0
b100 ,
b100 ;
b11 '
b11 8
b1 =
b11001000000000000000000000000 &
b10010 3
b0 6
b1110001 5
b100 2
b100 4
b111 7
b0 B
b0 F
b10100 A
b10000 @
b10000 E
b111 C
b101 D
b101 G
b10000000000000000000000000000000 J
b11 K
b101000 I
b100 L
b111 H
b1000 :
b1 >
b1110001 ?
b1101111000 *
b100010 +
b1 -
b10 1
b10 (
b1000000000000000000000000000000 $
1)
09
1%
#170
0%
#180
b101 =
b0 #
b0 /
b0 J
b111 K
b10000 I
b101 L
b1 A
b1110001 @
b1110001 E
b100 C
b11 D
b11 G
b1000000000000000000000000000000 &
b11 H
b110 :
b101 >
b0 ?
b10 *
b1010 +
b0 -
b0 1
b100 (
b10011000000000000000000000000 $
1!
1%
#190
0%
#200
b101 A
b0 @
b0 E
b11 K
b1110001 I
b11 L
1%
