Lab2/verilog/shared_modules/decoder/decoder_5bit_tester.v
/*
Author: Ian Gilman
Title: 5-bit decoder test device
Summary: Provides stimulus signals for decoder testing, prints out test results
*/

module decoder_5bit_tester(selection, code);
   input wire [31:0] selection;
   output reg [4:0] code;
   
   parameter delay = 1;

   // display logic data
   initial begin
      $display("\t\tcod\tsel     \ttime");
      $monitor("\t\t%b\t%h\t%g", code, selection, $time);
   end
   
   // create stimulus signals
   initial begin
      code = 5'b0;
      
      while(code < 5'b11111) begin
         #delay;
         code = code + 5'b1;
      end
      
      $finish;   
   end
endmodule

Lab2/verilog/shared_modules/decoder/decoder_5bit.v
/*
Author: Ian Gilman
Title: Single-output 5:1 Decoder
Summary: Recieves a code on 5-bit inputs which raises a logic high on 1 of the
   32 outputs while the rest are held low
*/

module decoder_5bit(code, selection);
   input wire [4:0] code;  // code driving which selct is output
   output wire [31:0] selection;  // outputs including single selection
   
   // shift high value to proper selection based on code
   assign selection = {32'b1 << (code)};

endmodule

Lab2/verilog/shared_modules/decoder/decoder_5bit_testbench.v
/*
Author: Ian Gilman
Title: testbench for 5-bit decoder
Summary: Test module for 5-bit decoder 
*/

`include "decoder_5bit.v"
`include "decoder_5bit_tester.v"

module decoder_5bit_testbench();
   wire [4:0] code;
   wire [31:0] selection;
   
   // DUT & Tester
   decoder_5bit decoder(.code, .selection);
   decoder_5bit_tester tester(.selection, .code);

   // create wave data file
   initial begin
      $dumpfile("decoder_5bit.vcd");
      $dumpvars(1, decoder);
   end


endmodule

Lab2/verilog/shared_modules/decoder/decoder_5bit.vcd
$date
	Sat Apr 09 17:43:01 2016
$end
$version
	Icarus Verilog
$end
$timescale
	1s
$end
$scope module decoder_5bit_testbench $end
$scope module decoder $end
$var wire 32 ! selection [31:0] $end
$var wire 5 " code [4:0] $end
$upscope $end
$upscope $end
$enddefinitions $end
#0
$dumpvars
b0 "
b1 !
$end
#1
b10 !
b1 "
#2
b100 !
b10 "
#3
b1000 !
b11 "
#4
b10000 !
b100 "
#5
b100000 !
b101 "
#6
b1000000 !
b110 "
#7
b10000000 !
b111 "
#8
b100000000 !
b1000 "
#9
b1000000000 !
b1001 "
#10
b10000000000 !
b1010 "
#11
b100000000000 !
b1011 "
#12
b1000000000000 !
b1100 "
#13
b10000000000000 !
b1101 "
#14
b100000000000000 !
b1110 "
#15
b1000000000000000 !
b1111 "
#16
b10000000000000000 !
b10000 "
#17
b100000000000000000 !
b10001 "
#18
b1000000000000000000 !
b10010 "
#19
b10000000000000000000 !
b10011 "
#20
b100000000000000000000 !
b10100 "
#21
b1000000000000000000000 !
b10101 "
#22
b10000000000000000000000 !
b10110 "
#23
b100000000000000000000000 !
b10111 "
#24
b1000000000000000000000000 !
b11000 "
#25
b10000000000000000000000000 !
b11001 "
#26
b100000000000000000000000000 !
b11010 "
#27
b1000000000000000000000000000 !
b11011 "
#28
b10000000000000000000000000000 !
b11100 "
#29
b100000000000000000000000000000 !
b11101 "
#30
b1000000000000000000000000000000 !
b11110 "
#31
b10000000000000000000000000000000 !
b11111 "
