Lab4/Verilog/Control_Signals/control_signals_tester.v
module control_signals_tester (
						.op_code(op_code),
						.alu_function(alu_function),
						.reg_dst(reg_dst),
						.jump(jump),
						.jump_reg(jump_reg),
						.branch(branch), 
						.cs(cs),
						.oe(oe),
						.rw(rw),
						.mem_to_reg(mem_to_reg),
						.alu_src(alu_src),
						.reg_write(reg_write),
						.alu_op(alu_op)
					   );
					   
	output reg [5:0] op_code, alu_function;
	input wire [5:0] alu_op;
	input wire reg_dst, jump, jump_reg,
			   branch, cs, oe, rw,
			   mem_to_reg, alu_src, reg_write;
			   
	 // print out test results
	initial begin
        $display("\top_code alu_op \talu_function \treg_dst jump \tjump_reg \tbranch \t\tcs \toe \trw \tmem_to_reg \alu_src \treg_write \ttime");
        $monitor("\t%h \t%h \t%h \t\t%b \t%b \t%b  \t\t%b \t\t%b \t%b \t%b \t%b \t\t%b \t%b \t%g",
                  op_code, alu_op, alu_function, reg_dst, jump, jump_reg, branch, cs, oe, rw, 
                  mem_to_reg, alu_src, reg_write, $time);
	end
	
	parameter REG = 6'b0;
	parameter JUMP = 6'b000010;
	parameter IBGT = 6'b000111;
	parameter IADD = 6'b001000;
	parameter ISLT = 6'b001010;
	parameter IAND = 6'b001100;
	parameter IOR = 6'b001101;
	parameter IXOR = 6'b001110;
	parameter ISLL = 6'b001111;
	parameter ILW = 6'b100011;
	parameter ISW = 6'b101011;
	
	parameter NOP = 6'b0;
	parameter SLLV = 6'b000100;
	parameter JR = 6'b001000;
	parameter ADD = 6'b100000;
	parameter SUB = 6'b100010;
	parameter AND = 6'b100100;
	parameter OR = 6'b100101;
	parameter XOR = 6'b100110;
	parameter SLT = 6'b101010;
   
	// create stimulus signals
	parameter delay = 10;
	integer i;
	integer j;
	initial begin
		#delay;
		op_code = REG; alu_function = JR; #delay;
		#delay;
		#delay;
		#delay;
		#delay;
		alu_function = SLLV; #delay;
		#delay;
		op_code = JUMP; #delay;
		#delay;
		op_code = IBGT; #delay;
		#delay;
		op_code = IADD; #delay;
		#delay;
		op_code = ISLT; #delay;
		#delay;
		op_code = IAND; #delay;
		#delay;
		op_code = IOR; #delay;
		#delay;
		op_code = IXOR; #delay;
		#delay;
		op_code = ISLL; #delay;
		#delay;
		op_code = ILW; #delay;
		#delay;
		op_code = ISW; #delay;
		#delay;
		
		

	end

endmodule

Lab4/Verilog/Control_Signals/control_signals.v
module control_signals(
						op_code,
						alu_function,
						reg_dst,
						jump,
						jump_reg,
						branch, 
						cs, oe, rw, // goes into data memory
						mem_to_reg,
						alu_src,
						reg_write,
						alu_op
					   );
					   
	input wire [5:0] op_code, alu_function;
	output reg reg_dst, jump, jump_reg,
			   branch, cs, oe, rw,
			   mem_to_reg, alu_src, reg_write;
	output reg [5:0] alu_op;
	
	parameter REG = 6'b0;
	parameter JUMP = 6'b000010;
	parameter IBGT = 6'b000111;
	parameter IADD = 6'b001000;
	parameter ISLT = 6'b001010;
	parameter IAND = 6'b001100;
	parameter IOR = 6'b001101;
	parameter IXOR = 6'b001110;
	parameter ISLL = 6'b001111;
	parameter ILW = 6'b100011;
	parameter ISW = 6'b101011;
	
	parameter NOP = 6'b0;
	parameter SLLV = 6'b000100;
	parameter JR = 6'b001000;
	parameter ADD = 6'b100000;
	parameter SUB = 6'b100010;
	parameter AND = 6'b100100;
	parameter OR = 6'b100101;
	parameter XOR = 6'b100110;
	parameter SLT = 6'b101010;
	
	initial begin;
		reg_dst = 0;
		jump = 0;
		jump_reg = 0;
		branch = 0;
		cs = 0;
		oe = 0;
		rw = 0;
		mem_to_reg = 0;
		alu_op = 6'b0;
		alu_src = 0;
		reg_write = 0;
	end
	
	always @(*) begin
		case(op_code)
		
			REG: begin
				reg_dst = 1;
				
				if (alu_function == JR ) begin
					jump = 1;
					jump_reg = 1;
					alu_op = NOP;
				end else begin
					jump = 0;
					jump_reg = 0;
					alu_op = alu_function;	
				end
				
				branch = 0;
				cs = 1;
				oe = oe;
				rw = rw;
				mem_to_reg = 0;		
				alu_src = 0;
				if(alu_function == NOP || alu_function == JR)
					reg_write = 0;
				else
					reg_write = 1;
			end
			
			JUMP: begin
				reg_dst = reg_dst;
				jump = 1;
				jump_reg = 0;
				branch = 0;
				cs = 1;
				oe = oe;
				rw = rw;
				mem_to_reg = mem_to_reg;
				alu_op = alu_op;
				alu_src = alu_src;
				reg_write = 0;			
			end
			
			IBGT: begin
				reg_dst = reg_dst;
				jump = 1;
				jump_reg = jump_reg;
				branch = 1;
				cs = 1;
				oe = oe;
				rw = rw;
				mem_to_reg = mem_to_reg;
				alu_op = SUB;
				alu_src = 0;
				reg_write = 0;				

			end
			
			IADD: begin
			
				reg_dst = 0;
				jump = 0;
				jump_reg = 0;
				branch = 0;
				cs = 1;
				oe = oe;
				rw = rw;
				mem_to_reg = 0;
				alu_op = ADD;
				alu_src = 1;
				reg_write = 1;	
			
			end
			
			ISLT: begin
				reg_dst = 0;
				jump = 0;
				jump_reg = 0;
				branch = 0;
				cs = 1;
				oe = oe;
				rw = rw;
				mem_to_reg = 0;
				alu_op = SLT;
				alu_src = 1;
				reg_write = 1;	
				
			end
			
			IAND: begin
				reg_dst = 0;
				jump = 0;
				jump_reg = 0;
				branch = 0;
				cs = 1;
				oe = oe;
				rw = rw;
				mem_to_reg = 0;
				alu_op = AND;
				alu_src = 1;
				reg_write = 1;	
				
			end
			
			IOR: begin
				reg_dst = 0;
				jump = 0;
				jump_reg = 0;
				branch = 0;
				cs = 1;
				oe = oe;
				rw = rw;
				mem_to_reg = 0;
				alu_op = OR;
				alu_src = 1;
				reg_write = 1;	
				
			end
			
			IXOR: begin
				reg_dst = 0;
				jump = 0;
				jump_reg = 0;
				branch = 0;
				cs = 1;
				oe = oe;
				rw = rw;
				mem_to_reg = 0;
				alu_op = XOR;
				alu_src = 1;
				reg_write = 1;	
				
			end
			
			ISLL: begin
				reg_dst = 0;
				jump = 0;
				jump_reg = 0;
				branch = 0;
				cs = 1;
				oe = oe;
				rw = rw;
				mem_to_reg = 0;
				alu_op = SLLV;
				alu_src = 1;
				reg_write = 1;	
				
			end
			
			ILW: begin
			
				reg_dst = 0;
				jump = 0;
				jump_reg = 0;
				branch = 0;
				cs = 0;
				oe = 1;
				rw = 0;
				mem_to_reg = 1;
				alu_op = ADD;
				alu_src = 1;
				reg_write = 1;
				
			end
			
			ISW: begin
			
				reg_dst = reg_dst;
				jump = 0;
				jump_reg = 0;
				branch = 0;
				cs = 0;
				oe = 0;
				rw = 1;
				mem_to_reg = 0;
				alu_op = ADD;
				alu_src = 1;
				reg_write = 0;	
				
			end
		
		endcase
	end

endmodule

Lab4/Verilog/Control_Signals/control_signals_tb.v
`include "control_signals.v"
`include "control_signals_tester.v"

module control_signals_tb();
	wire [5:0] op_code, alu_function, alu_op;
	wire reg_dst, jump, jump_reg,
		 branch, cs, oe, rw,
		 mem_to_reg, alu_src, reg_write;
	
	control_signals signals (
						.op_code(op_code),
						.alu_function(alu_function),
						.reg_dst(reg_dst),
						.jump(jump),
						.jump_reg(jump_reg),
						.branch(branch), 
						.cs(cs),
						.oe(oe),
						.rw(rw),
						.mem_to_reg(mem_to_reg),
						.alu_src(alu_src),
						.reg_write(reg_write),
						.alu_op(alu_op)
					   );
					   
	control_signals_tester tester (
						.op_code(op_code),
						.alu_function(alu_function),
						.reg_dst(reg_dst),
						.jump(jump),
						.jump_reg(jump_reg),
						.branch(branch), 
						.cs(cs),
						.oe(oe),
						.rw(rw),
						.mem_to_reg(mem_to_reg),
						.alu_src(alu_src),
						.reg_write(reg_write),
						.alu_op(alu_op)
					   );
					   
	initial begin
		$dumpfile("control_signals.vcd");
		$dumpvars(1, signals);
	end
	
endmodule

Lab4/Verilog/Control_Signals/control_signals.vcd
$date
	Sat May 14 17:47:29 2016
$end
$version
	Icarus Verilog
$end
$timescale
	1s
$end
$scope module control_signals_tb $end
$scope module signals $end
$var wire 6 ! op_code [5:0] $end
$var wire 6 " alu_function [5:0] $end
$var reg 6 # alu_op [5:0] $end
$var reg 1 $ alu_src $end
$var reg 1 % branch $end
$var reg 1 & cs $end
$var reg 1 ' jump $end
$var reg 1 ( jump_reg $end
$var reg 1 ) mem_to_reg $end
$var reg 1 * oe $end
$var reg 1 + reg_dst $end
$var reg 1 , reg_write $end
$var reg 1 - rw $end
$upscope $end
$upscope $end
$enddefinitions $end
#0
$dumpvars
0-
0,
0+
0*
0)
0(
0'
0&
0%
0$
b0 #
bx "
bx !
$end
#10
1&
1(
1'
1+
b1000 "
b0 !
#60
1,
b100 #
0(
0'
b100 "
#80
0,
1'
b10 !
#100
b100010 #
1%
b111 !
#120
1,
1$
b100000 #
0%
0'
0+
b1000 !
#140
b101010 #
b1010 !
#160
b100100 #
b1100 !
#180
b100101 #
b1101 !
#200
b100110 #
b1110 !
#220
b100 #
b1111 !
#240
b100000 #
1)
1*
0&
b100011 !
#260
0,
0)
1-
0*
b101011 !
