Lab4/Verilog/alu/alu.v
/*
Author: Adolfo Pineda & Ian Gilman
Title: Behavioral Arithmetic Logic Unit
Summary: two-operand / one-result implementation with Add/Sub/And/Or/Xor/Slt/Sll
functions selected by control code and produces status flags for 
zero result (Z), overflow (V), carry out (C), and negative result (N).
*/

module alu(fr_read0, fr_read1, immediate, control, alu_source, result, Z, V, C, N);

	// I/O
	input wire [31:0] fr_read0, fr_read1,  // file register read data
                     immediate;  // immediate value
	input wire [6:0] control;  // determines operation performed
   input wire alu_source;  // ALU operand1 Data alu_source
	output reg [31:0] result;  // result of operation
	output reg Z, V, C, N;  // status flags after operation
	
	// Internal
	wire [31:0] add_result, sub_result, and_result,     //  wires connected to 
			   or_result, xor_result, slt_result,       	//  operation sub-module
			   sll_result, operand0, operand1;          //  results
			   
	wire add_Z, sub_Z, // zero flags
		 add_V, sub_V, // overflow flags
		 add_C, sub_C, // carry flags
		 add_N, sub_N; // negative value flags   
       
	reg op0_msb, op1_msb, result_msb;
	reg [31:0] twos_comp_op1, result_manip;

   // Determine operands
   assign operand0 = fr_read0;
   assign operand1 = alu_source ? immediate : fr_read1;
	
	// ALU operation control codes
	parameter NOP = 6'h0;
	parameter ADD = 6'h32;
	parameter SUB = 6'h34;
	parameter AND = 6'h36;
	parameter OR  = 6'h37;
	parameter XOR = 6'h38;
	parameter SLT = 6'42;
	parameter SLL = 6'h4;
	
	always @ (*) begin
		case (control)
		
			NOP: begin
				Z = 0;
				V = 0;
				C = 0;
				N = 0;
				result = 0;
			end
			
			ADD: begin
				op0_msb = operand0[31];
				op1_msb = operand1[31];
				result = operand0 + operand1;
				result_msb = result[31];
				
				Z = (result == 0);
				V = (~(op0_msb ^ op1_msb)) & (op0_msb ^ result_msb);
				C = (op0_msb & op1_msb) | (op0_msb & ~result_msb) | (op1_msb & ~result_msb);
				N = (result_msb == 1);
				
			end
			
			SUB: begin
				twos_comp_op1 = ~operand1 + 32'b1;
				result_manip = operand0 + twos_comp_op1;
				op0_msb = operand0[31];
				op1_msb = twos_comp_op1[31];
				result_msb = result_manip[31];
				result = operand0 - operand1;
				
				Z = (result == 0);
				V = (op0_msb & op1_msb & ~result_msb) | (~op0_msb & ~op1_msb & result_msb);
				//V = ((op0_msb ~^ op1_msb)) & (op0_msb ^ result_msb);
				C = (op0_msb & op1_msb) | (op0_msb & ~result_msb) | (op1_msb & ~result_msb) | ((operand0 == 0) & (operand1 == 0) & (result == 0));
				N = (result_msb == 1);
				
			end
			
			AND: begin
				result = operand0 & operand1;
				Z = (result == 0);
				V = 0; 
				C = 0;
				N = (result[31] == 1);
					
			end
			
			OR: begin
				result = operand0 | operand1;
				Z = (result == 0);
				V = 0; 
				C = 0;
				N = (result[31] == 1);
				
			end
			
			XOR: begin
				result = operand0 ^ operand1;
				Z = (result == 0);
				V = 0; 
				C = 0;
				N = (result[31] == 1);
				
			end
			
			SLT: begin
				result = (operand0 < operand1) ? 1 : 0;
				Z = (result == 0);
				V = 0; 
				C = 0;
				N = (result[31] == 1);
				
			end
			
			SLL: begin
				result = operand0 << operand1;
				Z = (result == 0);
				V = 0; 
				C = 0;
				N = (result[31] == 1);
				
			end
		
		endcase
	end
	
endmodule

Lab4/Verilog/alu/alu_tb.v
// All files used
`include "alu.v"

// Title: 	ALU behavioral Test bench
// Author: 	Adolfo Pineda & Ian Gilman
// Summary:	A test bench module
module alu_tb;
   wire [31:0] fr_read0, fr_read1,  // file register read data
                     immediate;  // immediate value
	wire [6:0] control;  // determines operation performed
   wire alu_source;  // ALU operand1 Data alu_source
	wire [31:0] result;  // result of operation
	wire Z, V, C, N;  // status flags after operation
	
	// dut
	alu dut(fr_read0, fr_read1, immediate, control, alu_source, result, Z, V, C, N);
	
	// tester
	aluTester tester(fr_read0, fr_read1, immediate, control, alu_source, result, Z, V, C, N);

	// File for gtkwave
	initial begin
		$dumpfile("alu_test.vcd");
		$dumpvars(1, dut);
	end
endmodule



// Title: ALU behavioral tester
// Author: Adolfo Pineda
// A testing module

module aluTester(fr_read0, fr_read1, immediate, control, alu_source, result, Z, V, C, N);
	output reg [31:0] fr_read0, fr_read1,  // file register read data
                     immediate;  // immediate value
	output reg [6:0] control;  // determines operation performed
   output reg alu_source;  // ALU operand1 Data alu_source
	input wire [31:0] result;  // result of operation
	input wire Z, V, C, N;  // status flags after operation
	
	parameter delay = 10;

	// ALU operation control codes
	parameter NOP = 6'd0;
	parameter ADD = 6'd32;
	parameter SUB = 6'd34;
	parameter AND = 6'd36;
	parameter OR  = 6'd37;
	parameter XOR = 6'd38;
	parameter SLT = 6'd42;
	parameter SLL = 6'd4;
	
	// Display variables 
	initial begin
		$display("\t\tfr0\t\tfr1\t\timm\t control\tsor\t     result\t Z V C N\t time");
		$monitor("\t %d\t %d\t %d\t %b\t %b\t %d\t %b %b %b %b\t %g", 
												fr_read0, 
												fr_read1,
                                    immediate,
												control,
                                    alu_source,
												result, 
												Z, 
												V, 
												C, 
												N, 
												$time);
	end
	
	initial begin
		#delay; #delay; #delay;
		
      alu_source <= 0;
		control <= SUB;
		immediate <= 32'h14;
      
		 #delay;
		fr_read0 <= 32'd0;
		fr_read1 <= 32'd0;
		 #delay;
		fr_read0 <= 32'd500;
		fr_read1 <= 32'd500;
		 #delay;
		fr_read0 <= 32'd500000000;
		fr_read1 <= 32'd500000000;
		 #delay; #delay;
		fr_read0 <= 32'hFFFFFFE6;
		fr_read1 <= 32'd10;

      control <= ADD;
		#delay;
		fr_read0 <= 32'hFFFFFFFF;
		fr_read1 <= 32'h00000001;
		 #delay;
		fr_read0 <= 32'd10;
		fr_read1 <= 32'hFFFFFFFA;
		 #delay;
		fr_read0 <= 32'd5;
		fr_read1 <= 32'hFFFFFFF6;

		#delay;
		fr_read0 <= 32'd2147483647;
		fr_read1 <= 32'd2147483647;
		 #delay;#delay;
		fr_read0 <= 32'd3147483647;
		fr_read1 <= 32'd3147483647;
		 #delay;#delay;
		fr_read0 <= 32'hFFFFF000;
		fr_read1 <= 32'h80000000;
		 #delay;#delay;
		fr_read0 <= 32'd2147483647;
		fr_read1 <= 32'd2147483647;
		 #delay;#delay;
		fr_read0 <= 32'h80000000;
		fr_read1 <= 32'h00000001;
		 #delay;#delay;
		fr_read0 <= 32'hC0000000;
		fr_read1 <= 32'hC0000000;
		 #delay;#delay;
		fr_read0 <= 32'h80000000;
		fr_read1 <= 32'h80000000;
      alu_source <= 1'b1;
      control <=ADD;
		#delay;#delay;
		fr_read1 <= 32'hFFFFFFF6;
		fr_read0 <= 32'hFFFFFFF6;
		 #delay; #delay; #delay;
	end

endmodule
	
	/*initial // Response
	begin

	// Displays the labels and data
	$display("\tcontrol \ta \t  b \tresult \tTime");
	$monitor("\t%b \t%h \t%h \t%h \t%g",
		control, fr_read0, fr_read1, result, $time);
	end

	
	
	initial // Stimulus
	begin
		#stimdelay; 
		#stimdelay; control <= 3'b000;
		#stimdelay;
		#stimdelay; 
		#stimdelay; control <= 3'b001; // add
		#stimdelay;
		#stimdelay;
		#stimdelay;
		#stimdelay;
		#stimdelay;
		#stimdelay; fr_read0 <= {29'b0, 3'b111}; fr_read1 <= {29'b0, 3'b011}; 
		#stimdelay;
		#stimdelay;
		#stimdelay;
		#stimdelay; control <= 3'b010; // subtract
		#stimdelay;
		#stimdelay;
		#stimdelay; control <= 3'b011; // and
		#stimdelay;
		#stimdelay; control <= 3'b100; // or
		#stimdelay;
		#stimdelay; control <= 3'b101; // xor
		#stimdelay;
							//slt 
		#stimdelay; control <= 3'b110; fr_read0 <= 5; fr_read1 <= 7;
		#stimdelay;
							//sll
		#stimdelay; control <= 3'b111; fr_read0 <= 1; fr_read1 <= 7;
		#stimdelay;
		#stimdelay; control <= 3'b010; fr_read0 <= 100; fr_read1 <= 32; // subtract
		#stimdelay;
		#stimdelay;
		#stimdelay;

		$finish; // finish simulation
	end

endmodule*/

Lab4/Verilog/alu/alu_test.vcd
$date
	Fri May 13 18:02:08 2016
$end
$version
	Icarus Verilog
$end
$timescale
	1s
$end
$scope module alu_tb $end
$scope module dut $end
$var wire 32 ! operand0 [31:0] $end
$var wire 32 " operand1 [31:0] $end
$var wire 32 # immediate [31:0] $end
$var wire 32 $ fr_read1 [31:0] $end
$var wire 32 % fr_read0 [31:0] $end
$var wire 7 & control [6:0] $end
$var wire 1 ' alu_source $end
$var reg 1 ( C $end
$var reg 1 ) N $end
$var reg 1 * V $end
$var reg 1 + Z $end
$var reg 1 , op0_msb $end
$var reg 1 - op1_msb $end
$var reg 32 . result [31:0] $end
$var reg 32 / result_manip [31:0] $end
$var reg 1 0 result_msb $end
$var reg 32 1 twos_comp_op1 [31:0] $end
$upscope $end
$upscope $end
$enddefinitions $end
#0
$dumpvars
bx 1
x0
bx /
bx .
x-
x,
x+
x*
x)
x(
x'
bx &
bx %
bx $
bx #
bx "
bx !
$end
#30
b10100 #
b10 &
0'
#40
0)
1(
0*
1+
b0 .
00
0-
b0 /
b0 1
b0 "
0,
b0 $
b0 !
b0 %
#50
1-
b11111111111111111111111000001100 1
b111110100 "
1(
1+
b0 .
b0 /
b111110100 $
b111110100 !
b111110100 %
#60
b11100010001100101001101100000000 1
b11101110011010110010100000000 "
1+
b0 .
b0 /
b11101110011010110010100000000 $
b11101110011010110010100000000 !
b11101110011010110010100000000 %
#80
1)
0(
10
b1010 "
0+
b11111111111111111111111111110000 .
0-
1,
b1 &
b1010 $
b11111111111111111111111111100110 !
b11111111111111111111111111100110 %
#90
1+
b1 "
0)
1(
00
b0 .
b1 $
b11111111111111111111111111111111 !
b11111111111111111111111111111111 %
#100
1-
b11111111111111111111111111111010 "
1(
0+
b100 .
0,
b11111111111111111111111111111010 $
b1010 !
b1010 %
#110
b11111111111111111111111111110110 "
1)
0(
10
b11111111111111111111111111111011 .
b11111111111111111111111111110110 $
b101 !
b101 %
#120
1*
0-
b1111111111111111111111111111111 "
1)
0(
10
b11111111111111111111111111111110 .
b1111111111111111111111111111111 $
b1111111111111111111111111111111 !
b1111111111111111111111111111111 %
#140
1-
b10111011100110101100100111111111 "
0)
1(
1*
00
b1110111001101011001001111111110 .
1,
b10111011100110101100100111111111 $
b10111011100110101100100111111111 !
b10111011100110101100100111111111 %
#160
b10000000000000000000000000000000 "
0)
1*
00
b1111111111111111111000000000000 .
b10000000000000000000000000000000 $
b11111111111111111111000000000000 !
b11111111111111111111000000000000 %
#180
0-
b1111111111111111111111111111111 "
1)
0(
1*
10
b11111111111111111111111111111110 .
0,
b1111111111111111111111111111111 $
b1111111111111111111111111111111 !
b1111111111111111111111111111111 %
#200
b1 "
0*
b10000000000000000000000000000001 .
1,
b1 $
b10000000000000000000000000000000 !
b10000000000000000000000000000000 %
#220
1(
1-
b11000000000000000000000000000000 "
b10000000000000000000000000000000 .
b11000000000000000000000000000000 $
b11000000000000000000000000000000 !
b11000000000000000000000000000000 %
#240
0(
0-
b10100 "
1)
0*
10
b10000000000000000000000000010100 .
1'
b10000000000000000000000000000000 $
b10000000000000000000000000000000 !
b10000000000000000000000000000000 %
#260
0)
1(
00
b1010 .
b11111111111111111111111111110110 !
b11111111111111111111111111110110 %
b11111111111111111111111111110110 $
