Lab2/verilog/file_register/register_32bit/register_32bit_tester.v
/*
Author: Ian Gilman
Title: 32-bit Parallel In/Out Register test device
Summary: Provides stimulus signals for register testing, prints out test results
*/

module register_32bit_tester(Q, clk, we, rst, D);
   input wire [31:0] Q;  // parallel data from register
   output reg clk, we, rst;  // clock, write enabled, active-low reset register
   output reg [31:0] D;  // parallel data to write
   
   // print data out
   initial begin
      $display("\tQ       \tD       \twe \trst\tclk\ttime");
      $monitor("\t%h\t%h\t%b  \t%b  \t%b  \t%g", Q, D, we, rst, clk, $time);
   end

   // control register stimulus signals
   integer i;
   parameter delay = 1;
   initial begin
   
      // initial state and reset register
      D = 32'h0;
      we = 1'b0;
      clk = 1'b1;
      rst = 1'b1;    #delay;
      rst = 1'b0;    #delay;
      rst = 1'b1;    #delay;
      
      // write data
      D = 32'hACE5F8ED; #delay;
      for(i=0; i<2; i=i+1) begin
         clk = ~clk;    #delay;
      end
      we = 1'b1;
      for(i=0; i<4; i=i+1) begin
         clk = ~clk;    #delay;
      end
      we = 1'b0;
      for(i=0; i<2; i=i+1) begin
         clk = ~clk;    #delay;
      end
      
      // write data again
      D = 32'h1EE7BA17; #delay;
      for(i=0; i<2; i=i+1) begin
         clk = ~clk;    #delay;
      end
      we = 1'b1;
      for(i=0; i<4; i=i+1) begin
         clk = ~clk;    #delay;
      end
      we = 1'b0;
      for(i=0; i<2; i=i+1) begin
         clk = ~clk;    #delay;
      end
      
      $finish;
   end
   
endmodule

Lab2/verilog/shared_modules/dff/dff.v
/*
Author: Lab-provided code
Title: D flip-flop
Summary: Behavioral model of a d flip-flop
*/


module dff(q, qBar, D, clk, rst);
   input D, clk, rst; // DFF input, clock, reset
   output q, qBar; // DFF output, DFF negated output
   reg q;

   not n1 (qBar, q); // negate q

   // flip-flop storage logic
   always@ (negedge rst or posedge clk)
   begin
      if(!rst)
         q = 0;
      else
         q = D;
   end
endmodule

Lab2/verilog/file_register/register_32bit/register_32bit.v
/*
Author: Ian Gilman
Title: 32-bit Parallel In/Out Register
Summary: 32 synchronous d flip-flops configured to operate as a parallel in/out,
   register with write enable and reset.
*/

`include "../../shared_modules/dff/dff.v"

module register_32bit(clk, we, rst, D, Q);
   input wire clk, we, rst;  // clock, write enabled, active-low reset register
   input wire [31:0] D;  // parallel data to write
   output wire [31:0] Q;  // parallel data from register
   wire [31:0] parallel_write_data;  // parallel data to register
   
   // write new data to register if write is enabled, else keep same data
   assign parallel_write_data = we ? D : Q;
   
   // register of 32 d flip-flops
   genvar i;
   generate for(i = 0; i < 32; i = i + 1) begin: REGISTER
      dff U(.q(Q[i]), .qBar(), .D(parallel_write_data[i]), .clk, .rst);
   end
   endgenerate

endmodule

Lab2/verilog/file_register/register_32bit/register_32bit_testbench.v
/*
Author: Ian Gilman
Title: 32-bit Parallel In/Out Register test bench
Summary: Test module for 32-bit register
*/

`include "register_32bit.v"
`include "register_32bit_tester.v"

module register_32bit_testbench();
   wire [31:0] D, Q;  // data to write to register, data read from register
   wire clk, we, rst;  // clock, register write enable, reset register
   
   // DUT and test device
   register_32bit register(.clk, .we, .rst, .D, .Q);
   register_32bit_tester tester(.Q, .clk, .we, .rst, .D);
   
   // Store waveform data from test
   initial begin
      $dumpfile("register_32bit.vcd");
      $dumpvars(1, register);
   end

endmodule

Lab2/verilog/file_register/register_32bit/register_32bit.vcd
$date
	Sat Apr 09 22:41:06 2016
$end
$version
	Icarus Verilog
$end
$timescale
	1s
$end
$scope module register_32bit_testbench $end
$scope module register $end
$var wire 1 ! we $end
$var wire 1 " rst $end
$var wire 32 # parallel_write_data [31:0] $end
$var wire 1 $ clk $end
$var wire 32 % Q [31:0] $end
$var wire 32 & D [31:0] $end
$upscope $end
$upscope $end
$enddefinitions $end
#0
$dumpvars
b0 &
bx %
1$
bx #
1"
0!
$end
#1
b0 #
b0 %
0"
#2
1"
#3
b10101100111001011111100011101101 &
#4
0$
#5
1$
#6
b10101100111001011111100011101101 #
0$
1!
#7
b10101100111001011111100011101101 %
1$
#8
0$
#9
1$
#10
0$
0!
#11
1$
#12
b11110111001111011101000010111 &
#13
0$
#14
1$
#15
b11110111001111011101000010111 #
0$
1!
#16
b11110111001111011101000010111 %
1$
#17
0$
#18
1$
#19
0$
0!
