Lab3/verilog/alu_behvaioral/2sComplimenter_behavioral/Twos_Tester.v
// Title:  32-bit adder Tester
// Author: David Dolengewicz
// A test bench module for the 32-bit adder
// that makes sure it works to spec


module Twos_Tester(in, out);

output reg [31:0] in;
input wire [31:0] out;

integer i;

parameter stimDelay = 1;

initial // Response
	begin
	// Displays the labels and data
	$display("\t\t in \t\t out ");
	$monitor("\t\t %d \t\t %d \t %g",in, out, $time );
	end

	initial // Stimulus
	begin
	#stimDelay;
	in = 32'h7FFFFFF;
	#stimDelay;
	in = 32'h8FFFFFF;
	#stimDelay;
	in = 32'h9FFFFFF;
	#stimDelay;
	in = 32'hAFFFFFF;
	#stimDelay;
	in = 32'hBFFFFFF;
	#stimDelay;
	in = 32'hCFFFFFF;
	#stimDelay;
	in = 32'hDFFFFFF;
	#stimDelay;

	#stimDelay;
	in = -2;
	#stimDelay;
	in = -2000;
	#stimDelay;
	in = -320000;	
	#stimDelay;
	in = -10;
	

	#(2*stimDelay); // needed to see END of simulation
	$finish; // finish simulation
	end



endmodule

Lab3/verilog/alu_behvaioral/2sComplimenter_behavioral/Twos_Complimenter.v
module Twos_Complimenter(in, out);

input wire [31:0] in;
output reg [31:0] out;

reg [31:0] var;

always @(*) begin


		out = ~in + 32'b1;
	


end

endmodule

Lab3/verilog/alu_behvaioral/2sComplimenter_behavioral/Twos_tb.v
// Title:  32-bit adder testbench
// Author: David Dolengewicz
// A test bench module for the 32-bit adder
// that makes sure it works to spec

//All files Used
`include "Twos_Complimenter.v"
`include "Twos_Tester.v"

module Twos_tb();

wire [31:0] in, out;

Twos_Complimenter dut (.in(in), .out(out));

Twos_Tester tester (.in(in), .out(out));
								
									// File for gtkwave
	initial begin
		$dumpfile("TwosTest.vcd");
		$dumpvars(1, dut);
		
	end
						


endmodule

Lab3/verilog/alu_behvaioral/2sComplimenter_behavioral/TwosTest.vcd
$date
	Wed Apr 27 16:30:51 2016
$end
$version
	Icarus Verilog
$end
$timescale
	1s
$end
$scope module Twos_tb $end
$scope module dut $end
$var wire 32 ! in [31:0] $end
$var reg 32 " out [31:0] $end
$upscope $end
$upscope $end
$enddefinitions $end
#0
$dumpvars
bx "
bx !
$end
#1
b11111000000000000000000000000001 "
b111111111111111111111111111 !
#2
b11110111000000000000000000000001 "
b1000111111111111111111111111 !
#3
b11110110000000000000000000000001 "
b1001111111111111111111111111 !
#4
b11110101000000000000000000000001 "
b1010111111111111111111111111 !
#5
b11110100000000000000000000000001 "
b1011111111111111111111111111 !
#6
b11110011000000000000000000000001 "
b1100111111111111111111111111 !
#7
b11110010000000000000000000000001 "
b1101111111111111111111111111 !
#9
b10 "
b11111111111111111111111111111110 !
#10
b11111010000 "
b11111111111111111111100000110000 !
#11
b1001110001000000000 "
b11111111111110110001111000000000 !
#12
b1010 "
b11111111111111111111111111110110 !
