Lab5/verilog/dataForwarding/dataForwarding.v
/*
Author David Dolengewicz, Ian Gilman
	dataForwarding is handles the logic, datapath and control for the dataforwarding/hazard control
*/

/*/// DEFINITION OF TERMS  /////
-------------------------------------------------------------------------------------
||  TERM           ||  Reference
-------------------------------------------------------------------------------------
||  IFID           ||  Refers to the data buffer between the Instruction Fetch and the 
||                 ||  Instruction Decode pipelining stages
-------------------------------------------------------------------------------------
||  IDEX           ||  Refers to the data buffer between the Instruction Decode and the 
||                 ||  Execution pipelining stages
-------------------------------------------------------------------------------------
||  EXMEM          ||  Refers to the data buffer between the Execution and the 
||                 ||  Memory pipelinging stages
--------------------------------------------------------------------------------------
||  MEMWB          ||  Refers to the data bffer between the Memory and the
||                 ||  Write Back pipelining stages
--------------------------------------------------------------------------------------
||  op             ||  The op-code part of an instruction: instr[31:26] (6-bits)
---------------------------------------------------------------------------------------
||  rs             ||  The 1st FR register address in an instruction: instr[25:21] (5-bits)
||                 ||  this indicates a register that is being read
--------------------------------------------------------------------------------------
||  rt             ||  The 2nd FR register address in an instruction: instr[20:16] (5-bits)
||                 ||  this indicates the register that is written to for immediate instructions
||                 ||  or a register that is read for register instructions
---------------------------------------------------------------------------------------
||  rd             ||  The 2nd FR register address in an instruction (register only): instr[15:11] (5-bits)
||                 ||  this indicates the register that is written to for register instructions
||                 ||  it is invalid for immediate instructions
---------------------------------------------------------------------------------------
||  funct          ||  The part of the instruction that indicates the ALU function to perform:
||                 ||      instr[5:0] (6-bit)
---------------------------------------------------------------------------------------              
||  alui_wr        ||  Op-codes for instructions that write data to FR from the ALU:
||                 ||      ADDI, SLTI, ANDI, ORI, XORI, SLLI
-------------------------------------------------------------------------------------
||  alui_rd         ||  Op-codes for instructions that read data to ALU from the FR:
||                 ||      ADDI, SLTI, ANDI, ORI, XORI, SLLI, SW, LW
-------------------------------------------------------------------------------------
||  alur           ||  ALU funct code for register instructions (Op-code = 0) that read
||                 ||  from the FR to the ALU and also write from the ALU to the FR:
||	               ||      ADD, SUB, SLT, AND, OR, XOR, SLLV
-------------------------------------------------------------------------------------
*/

module dataForwarding(		instrIFID,	//inputs
							instrIDEX,
							instrEXMEM,
							instrMEMWB,
							aluEXMEM_Data,
							aluMEMWB_Data,
							EXMEM_Data2Mem,
							MEMWB_MemData,
							jmp0D,		//Data outputs
							jmp1D,
							aluD0,
							aluD1,
							exmemD,
							memMemD,
							jmp0,			//Control outputs
							jmp1,
							stall,
							calc_branch,
							alu0,
							alu1,
							exmem,
							mem_mem		);
								
input wire [31:0] 			instrIFID,	
							instrIDEX,
							instrEXMEM,
							instrMEMWB,
							aluEXMEM_Data,
							aluMEMWB_Data,
							EXMEM_Data2Mem,
							MEMWB_MemData;
							
output reg [31:0]			jmp0D,		//Data outputs
							jmp1D,
							aluD0,
							aluD1,
							exmemD,
							memMemD;	
							
output reg					jmp0,			//Control outputs
							jmp1,
							stall,
							calc_branch,
							alu0,
							alu1,
							exmem,
							mem_mem;	

//parameters
// Instruction OP Codes
parameter REG = 6'd0;
parameter JUMP = 6'd2;
parameter BGTI = 6'd7;
parameter ADDI = 6'd8;
parameter SLTI = 6'd10;
parameter ANDI = 6'd12;
parameter ORI = 6'd13;
parameter XORI = 6'd14;
parameter SLLI = 6'd15;
parameter LW = 6'd35;
parameter SW = 6'd43;

// ALU Functions
parameter NOP = 6'd0;
parameter SLLV = 6'd4;
parameter JR = 6'd8;
parameter ADD = 6'd32;
parameter SUB = 6'd34;
parameter AND = 6'd36;
parameter OR = 6'd37;
parameter XOR = 6'd38;
parameter SLT = 6'd42;

wire op_IFID_is_alui_rd;
wire op_IDEX_is_alui_rd;
wire op_EXMEM_is_alui_rd;
wire op_MEMWB_is_alui_rd;

wire op_IFID_is_alui_wr;
wire op_IDEX_is_alui_wr;
wire op_EXMEM_is_alui_wr;
wire op_MEMWB_is_alui_wr;

wire op_IFID_is_alur;
wire op_IDEX_is_alur;
wire op_EXMEM_is_alur;
wire op_MEMWB_is_alur;

wire funct_IFID_is_alur;
wire funct_IDEX_is_alur;
wire funct_EXMEM_is_alur;
wire funct_MEMWB_is_alur;

wire	[4:0]	op_IFID,
				op_IDEX,
				op_EXMEM,
				op_MEMWB,	
                rs_IFID,
				rs_IDEX,
				rs_EXMEM,
				rs_MEMWB,
                rt_IFID, 
				rt_IDEX,
				rt_EXMEM,
				rt_MEMWB,
                rd_IFID,
				rd_IDEX,
				rd_EXMEM,
				rd_MEMWB;
				
wire [5:0]      funct_IFID, 	 			 		
                funct_IDEX,	
                funct_EXMEM, 	
                funct_MEMWB; 	

//assignation 
assign op_IFID = 		instrIFID[31:26];
assign rs_IFID = 		instrIFID[25:21];
assign rt_IFID = 		instrIFID[20:16];						
assign rd_IFID = 		instrIFID[15:11];
assign funct_IFID = 	instrIFID[5:0];								
									
assign op_IDEX = 		instrIDEX[31:26];
assign rs_IDEX = 		instrIDEX[25:21];
assign rt_IDEX = 		instrIDEX[20:16];						
assign rd_IDEX = 		instrIDEX[15:11];
assign funct_IDEX = 	instrIDEX[5:0];	
								
assign op_EXMEM = 		instrEXMEM[31:26];
assign rs_EXMEM = 		instrEXMEM[25:21];
assign rt_EXMEM = 		instrEXMEM[20:16];						
assign rd_EXMEM = 		instrEXMEM[15:11];
assign funct_EXMEM = 	instrEXMEM[5:0];									
								
assign op_MEMWB = 		instrMEMWB[31:26];
assign rs_MEMWB = 		instrMEMWB[25:21];
assign rt_MEMWB = 		instrMEMWB[20:16];						
assign rd_MEMWB = 		instrMEMWB[15:11];
assign funct_MEMWB = 	instrMEMWB[5:0];	

//is_alui_rd assigns
assign op_IFID_is_alui_rd = (		(op_IFID == ADDI) || 
									(op_IFID == SLTI) ||
									(op_IFID == ORI)  ||
									(op_IFID == ANDI) ||
									(op_IFID == XORI) ||
									(op_IFID == SLLI) ||
									(op_IFID == SW)   ||
									(op_IFID == LW)	);
									
assign op_IDEX_is_alui_rd = (		(op_IDEX == ADDI) || 
									(op_IDEX == SLTI) ||
									(op_IDEX == ORI)  ||
									(op_IDEX == ANDI) ||
									(op_IDEX == XORI) ||
									(op_IDEX == SLLI) ||
									(op_IDEX == SW)   ||
									(op_IDEX == LW)	);
									
assign op_EXMEM_is_alui_rd = (		(op_EXMEM == ADDI) || 
									(op_EXMEM == SLTI) ||
									(op_EXMEM == ANDI) ||
									(op_EXMEM == XORI) ||
									(op_EXMEM == SLLI) ||
									(op_EXMEM == SW)   ||
									(op_EXMEM == ORI)  ||
									(op_EXMEM == LW)	);
									
assign op_MEMWB_is_alui_rd = (		(op_MEMWB == ADDI) || 
									(op_MEMWB == SLTI) ||
									(op_MEMWB == ORI)  ||
									(op_MEMWB == ANDI) ||
									(op_MEMWB == XORI) ||
									(op_MEMWB == SLLI) ||
									(op_MEMWB == SW)   ||
									(op_MEMWB == LW)	);


//is_alui_wr									
assign op_IFID_is_alui_wr = ( 		(op_IFID == ADDI) || 
									(op_IFID == SLTI) ||
									(op_IFID == ORI)  ||
									(op_IFID == ANDI) ||
									(op_IFID == XORI) ||
									(op_IFID == SLLI) );
									
assign op_IDEX_is_alui_wr = ( 		(op_IFID == ADDI) || 
									(op_IDEX == SLTI) ||
									(op_IDEX == ORI)  ||
									(op_IDEX == ANDI) ||
									(op_IDEX == XORI) ||
									(op_IDEX == SLLI) );
									
assign op_EXMEM_is_alui_wr = ( 		(op_EXMEM == ADDI)  || 
									(op_EXMEM == SLTI) ||
									(op_EXMEM == ORI)  ||
									(op_EXMEM == ANDI) ||
									(op_EXMEM == XORI) ||
									(op_EXMEM == SLLI) );
									
assign op_MEMWB_is_alui_wr = ( 		(op_EXMEM == ADDI)  || 
									(op_MEMWB == SLTI) ||
									(op_MEMWB == ORI)  ||
									(op_MEMWB == ANDI) ||
									(op_MEMWB == XORI) ||
									(op_MEMWB == SLLI) );
									

//is_alur
assign op_IFID_is_alur = (			(op_IFID == ADD)	||
									(op_IFID == SUB)	||
									(op_IFID == SLT)	||
									(op_IFID == AND)	||
									(op_IFID == OR)		||
									(op_IFID == XOR)	||
									(op_IFID == SLLV)	);
									
assign op_IDEX_is_alur = (			(op_IDEX == ADD)	||
									(op_IDEX == SUB)	||
									(op_IDEX == SLT)	||
									(op_IDEX == AND)	||
									(op_IDEX == OR)		||
									(op_IDEX == XOR)	||
									(op_IDEX == SLLV)	);
									
assign op_EXMEM_is_alur = (			(op_EXMEM == ADD)	||
									(op_EXMEM == SUB)	||
									(op_EXMEM == SLT)	||
									(op_EXMEM == AND)	||
									(op_EXMEM == OR)	||
									(op_EXMEM == XOR)	||
									(op_EXMEM == SLLV)	);
									
assign op_MEMWB_is_alur = (			(op_MEMWB == ADD)	||
									(op_MEMWB == SUB)	||
									(op_MEMWB == SLT)	||
									(op_MEMWB == AND)	||
									(op_MEMWB == OR)	||
									(op_MEMWB == XOR)	||
									(op_MEMWB == SLLV)	);
									
assign funct_IFID_is_alur = (		(funct_IFID == ADD)	||
									(funct_IFID == SUB)	||
									(funct_IFID == SLT)	||
									(funct_IFID == AND)	||
									(funct_IFID == OR)	||
									(funct_IFID == XOR)	||
									(funct_IFID == SLLV)	);
									
assign funct_IDEX_is_alur = (		(funct_IDEX == ADD)	||
									(funct_IDEX == SUB)	||
									(funct_IDEX == SLT)	||
									(funct_IDEX == AND)	||
									(funct_IDEX == OR)	||
									(funct_IDEX == XOR)	||
									(funct_IDEX == SLLV)	);
									
assign funct_EXMEM_is_alur = (		(funct_EXMEM == ADD)	||
									(funct_EXMEM == SUB)	||
									(funct_EXMEM == SLT)	||
									(funct_EXMEM == AND)	||
									(funct_EXMEM == OR)		||
									(funct_EXMEM == XOR)	||
									(funct_EXMEM == SLLV)	);
									
assign funct_MEMWB_is_alur = (		(funct_MEMWB == ADD)	||
									(funct_MEMWB == SUB)	||
									(funct_MEMWB == SLT)	||
									(funct_MEMWB == AND)	||
									(funct_MEMWB == OR)		||
									(funct_MEMWB == XOR)	||
									(funct_MEMWB == SLLV)	);
										
										
										
always @(*) begin
	// BLOCK 1 forwarding to the ALU
	if(op_IDEX_is_alui_rd) begin 
		
		alu1 = 0;

		if(op_EXMEM_is_alui_wr)
			alu0 = (rt_EXMEM == rs_IDEX);
		else if(op_EXMEM == 0 && funct_EXMEM_is_alur)
			alu0 = (rd_EXMEM == rs_IDEX);
		else if(op_MEMWB_is_alui_wr || op_MEMWB == LW)
			alu0 = (rd_MEMWB == rs_IDEX);
		else
			alu0 = (rd_MEMWB == rs_IDEX);
			
			
		if(op_EXMEM_is_alui_wr || (op_EXMEM == 0 && funct_EXMEM_is_alur))
			aluD0 = aluEXMEM_Data;
		else 
			aluD0 = aluD0;
			
		aluD1 = aluD1; 

	end
	
	//BLOCK 2
	else if(op_IDEX == 0 && funct_IDEX_is_alur) begin //
		if(op_EXMEM_is_alui_wr) begin				//SUB-BLOCK A
			if(op_MEMWB_is_alui_wr || (op_MEMWB == LW)) begin
				alu0 = (rt_EXMEM == rs_IDEX) || (rt_MEMWB == rs_IDEX);
				alu1 = (rt_EXMEM == rt_IDEX) || (rt_MEMWB == rt_IDEX);
			end
			else if(op_MEMWB == 0 || funct_MEMWB_is_alur) begin
				alu0 = (rt_EXMEM == rs_IDEX) || (rd_MEMWB == rs_IDEX);
				alu1 = (rt_EXMEM == rt_IDEX) || (rd_MEMWB == rt_IDEX);
			end
			else begin
				alu0 = (rt_EXMEM == rs_IDEX);
				alu1 = (rt_EXMEM == rt_IDEX);
			end
			
			if(rt_EXMEM == rs_IDEX)
				aluD0 = aluEXMEM_Data;
			else
				aluD0 = aluMEMWB_Data;
				
			if(rt_EXMEM == rt_IDEX)
				aluD1 = aluEXMEM_Data;
			else
				aluD1 = aluMEMWB_Data;
		end
		else if(op_EXMEM == 0 && funct_EXMEM_is_alur) begin	//SUB-BLOCK B
			if(op_MEMWB_is_alui_wr || op_MEMWB == LW) begin
				alu0 = (rd_EXMEM == rs_IDEX) || (rt_MEMWB == rs_IDEX);
				alu1 = (rd_EXMEM == rt_IDEX) || (rt_MEMWB == rt_IDEX);			
			end
			else if(op_MEMWB == 0 && funct_MEMWB_is_alur) begin
				alu0 = (rd_EXMEM == rs_IDEX) || (rd_MEMWB == rs_IDEX);
				alu1 = (rd_EXMEM == rt_IDEX) || (rd_MEMWB == rt_IDEX);	
			end 
			else begin
				alu0 = (rd_EXMEM == rs_IDEX);
				alu1 = (rd_EXMEM == rt_IDEX);
			end
			
			// data logic
			// mux 0 data
			if(rd_EXMEM == rs_IDEX)
				aluD0 = aluEXMEM_Data;
			else
				aluD0 = aluMEMWB_Data;
			
			// mux 1 data
			if(rd_EXMEM == rt_IDEX)
				aluD1 = aluEXMEM_Data;
			else
				aluD1 = aluMEMWB_Data;
		end
	end	
	
	
// FORWARDING TO DATA MEMORY
/*
mem mux logic and data (memD_mux == true  means memD is forwarded):
signals:
   ex_memD_mux, mem_memD_mux
   ex_memD,     mem_memD
*/
// ex mem mux

	//BLOCK 3
	if(op_IDEX == SW) begin	//144
		if((op_EXMEM_is_alui_wr) && (rt_EXMEM == rt_IDEX))
			exmem = 1;
		else if(op_EXMEM == 0 && funct_EXMEM_is_alur && rd_EXMEM == rt_IDEX)
			exmem = 1;
		else if((op_MEMWB_is_alui_wr || op_MEMWB == LW) && rt_MEMWB == rt_IDEX)
			exmem = 1;
		else
			exmem = rd_MEMWB == rt_IDEX;
	end	
	
	
		//BLOCK 4
	// ex mem mux data
	if(op_IDEX == SW) begin //155
		if((op_EXMEM_is_alui_wr) && (rt_EXMEM == rt_IDEX))
			exmemD = aluEXMEM_Data;
		else if(op_EXMEM == 0 && funct_EXMEM_is_alur && rd_EXMEM == rt_IDEX)
			exmemD = aluEXMEM_Data;
		else if(op_MEMWB_is_alui_wr && rt_MEMWB == rt_IDEX)
			exmemD = aluMEMWB_Data;
		else if(op_MEMWB == 0 && funct_MEMWB_is_alur && rd_MEMWB == rt_IDEX)
			exmemD = aluMEMWB_Data;
		else
			exmemD = MEMWB_MemData;
	end
	
	// mem mem mux and data
	//BLOCK 5
	if(op_EXMEM == SW) begin
		memMemD = MEMWB_MemData;
		if(op_MEMWB == LW)
			mem_mem = (rt_MEMWB == rt_EXMEM);
	end

// FORWARDING TO JUMPS
/*
jmp mux logic and data (jmp_mux == true  means jmpD is forwarded)
signals:
   jmp0_mux,   jmpD0
   jmp1_mux,   jmpD1
*/
// jmp mux	

		//BLOCK 6
	if((op_IFID == 0 && funct_IFID == JUMP) || op_IFID == BGTI) begin //183
		if(op_EXMEM_is_alui_wr) begin
			jmp0 = rt_EXMEM == rs_IFID;
			jmp1 = rt_EXMEM == rt_IFID;
		end
		else if(op_EXMEM == 0 && funct_EXMEM_is_alur) begin
			jmp0 = rd_EXMEM == rs_IFID;
			jmp1 = rd_EXMEM == rt_IFID;
		end
	end
// jmp mux data	
	if((op_IFID == 0 && funct_IFID == JUMP) || op_IFID == BGTI) begin
		if(op_EXMEM_is_alui_wr || (op_EXMEM == 0 && funct_EXMEM_is_alur)) begin
			jmp0 = aluEXMEM_Data;
			jmp1 = aluEXMEM_Data;
		end
	end
	
	
///// HAZARD CONTROL /////
/*
signals:
   stall
   calc_branch
   guess_brnch (currently not implemented)
*/
// stall

	//BLOCK 7
	if(op_EXMEM == LW) begin //// stall for forwarding from memory to alu
		if(op_IDEX_is_alui_rd)
			stall = rt_EXMEM == rs_IDEX;
		if(op_IDEX == 0 && funct_IDEX_is_alur)
			stall = (rt_EXMEM == rs_IDEX) || (rt_EXMEM == rt_IDEX);
	end
	else if(op_IFID == 0 && funct_IFID == JR) begin  // stall for data from alu / memory to jr
		if(op_IDEX_is_alui_wr || op_IDEX == LW)
			stall = rt_IDEX == rs_IFID;
		else if(op_IDEX == 0 && funct_IDEX_is_alur)
			stall = rd_IDEX == rs_IFID;
		else if(op_EXMEM == LW)
			stall = rt_EXMEM == rs_IFID;
	end
	else if(op_IFID == BGTI) begin // stall for data from alu / memory to bgt
		if(op_IDEX_is_alui_wr || op_IDEX == LW)
			stall = (rt_IDEX == rs_IFID) || (rt_IDEX == rt_IFID);
		else if(op_IDEX == 0 && funct_IDEX_is_alur)
			stall = rt_IDEX == (	rt_IDEX == rs_IFID || rt_IDEX == rt_IFID ||
									rs_IDEX == rs_IFID || rs_IDEX == rt_IFID  	);
		else if(op_EXMEM == LW)
			stall = rt_EXMEM == rs_IFID || rt_EXMEM == rt_IFID;
	end	
		
end

//calc_branch = (!stall) && (op_IFID == 0 && funct_IFID == JR) || op_IFID == BGT || op_IFID == JUMP;

endmodule

Lab5/verilog/dataForwarding/df_tbCOPY.v
/*
Author: David Dolengewicz
Summary: Test the operation of the Program_Control module
*/

`include "dataForwarding.v"

//test bench
module df_tb();

wire [31:0] 	instrIFID,	//Data inputs
				instrIDEX,
				instrEXMEM,
				instrMEMWB,
				aluEXMEM_Data,
				aluMEMWB_Data,
				EXMEM_Data2Mem,
				MEMWB_MemData;
					
wire [31:0]		jmp0D,		//Data outputs
				jmp1D,
				aluD0,
				aluD1,
				exmemD,
				memMemD;	
					
wire			jmp0,			//Control outputs
				jmp1,
				stall,
				calc_branch,
				alu0,
				alu1,
				exmem,
				mem_mem;		

df_tester tester(	.instrIFID(instrIFID),	//inputs
					.instrIDEX(instrIDEX),
					.instrEXMEM(instrEXMEM),
					.instrMEMWB(instrMEMWB),
					.aluEXMEM_Data(aluEXMEM_Data),
					.aluMEMWB_Data(aluMEMWB_Data),
					.EXMEM_Data2Mem(EXMEM_Data2Mem),
					.MEMWB_MemData(MEMWB_MemData),
					.jmp0D(jmp0D),		//Data outputs
					.jmp1D(jmp1D),
					.aluD0(aluD0),
					.aluD1(aluD1),
					.exmemD(exmemD),
					.memMemD(memMemD),
					.jmp0(jmp0),			//Control outputs
					.jmp1(jmp1),
					.stall(stall),
					.calc_branch(calc_branch),
					.alu0(alu0),
					.alu1(alu1),
					.exmem(exmem),
					.mem_mem(mem_mem)		);							

dataForwarding dut(	.instrIFID(instrIFID),	//inputs
					.instrIDEX(instrIDEX),
					.instrEXMEM(instrEXMEM),
					.instrMEMWB(instrMEMWB),
					.aluEXMEM_Data(aluEXMEM_Data),
					.aluMEMWB_Data(aluMEMWB_Data),
					.EXMEM_Data2Mem(EXMEM_Data2Mem),
					.MEMWB_MemData(MEMWB_MemData),
					.jmp0D(jmp0D),		//Data outputs
					.jmp1D(jmp1D),
					.aluD0(aluD0),
					.aluD1(aluD1),
					.exmemD(exmemD),
					.memMemD(memMemD),
					.jmp0(jmp0),			//Control outputs
					.jmp1(jmp1),
					.stall(stall),
					.calc_branch(calc_branch),
					.alu0(alu0),
					.alu1(alu1),
					.exmem(exmem),
					.mem_mem(mem_mem)		);								
								
   // Store waveform data
   initial begin
      $dumpfile("DFTest.vcd");
      $dumpvars(4, dut);
   end
																
endmodule





//tester							
								
module df_tester(	instrIFID,	//inputs (tester outputs)
					instrIDEX,
					instrEXMEM,
					instrMEMWB,
					aluEXMEM_Data,
					aluMEMWB_Data,
					EXMEM_Data2Mem,
					MEMWB_MemData,
					jmp0D,		//Data outputs (tester inputs)
					jmp1D,
					aluD0,
					aluD1,
					exmemD,
					memMemD,
					jmp0,			//Control outputs (tester inputs)
					jmp1,
					stall,
					calc_branch,
					alu0,
					alu1,
					exmem,
					mem_mem		);
								
output wire [31:0] 	instrIFID,	//outputs
					instrIDEX,
					instrEXMEM,
					instrMEMWB;
					
output reg [31:0]	aluEXMEM_Data,
					aluMEMWB_Data,
					EXMEM_Data2Mem,
					MEMWB_MemData;
					
input wire [31:0]	jmp0D,		//inputs
					jmp1D,
					aluD0,
					aluD1,
					exmemD,
					memMemD;	
					
input wire			jmp0,		//inputs
					jmp1,
					stall,
					calc_branch,
					alu0,
					alu1,
					exmem,
					mem_mem;

reg	[4:0]		op_IFID,
				op_IDEX,
				op_EXMEM,
				op_MEMWB,	
                rs_IFID,
				rs_IDEX,
				rs_EXMEM,
				rs_MEMWB,
                rt_IFID, 
				rt_IDEX,
				rt_EXMEM,
				rt_MEMWB,
                rd_IFID,
				rd_IDEX,
				rd_EXMEM,
				rd_MEMWB;
				
reg [5:0]       funct_IFID, 	 			 		
                funct_IDEX,	
                funct_EXMEM, 	
                funct_MEMWB; 	

assign	instrIFID	=	{op_IFID, rs_IFID, rt_IFID, rd_IFID, 5'b11111, funct_IFID};
assign  instrIDEX	=	{op_IDEX, rs_IDEX, rt_IDEX, rd_IDEX, 5'b11111, funct_IDEX};
assign  instrEXMEM	=	{op_EXMEM, rs_EXMEM, rt_EXMEM, rd_EXMEM, 5'b11111, funct_EXMEM};
assign  instrMEMWB	=	{op_MEMWB, rs_MEMWB, rt_MEMWB, rd_MEMWB, 5'b11111, funct_MEMWB};
				
//parameters
// Instruction OP Codes
parameter REG = 6'd0;
parameter JUMP = 6'd2;
parameter BGTI = 6'd7;
parameter ADDI = 6'd8;
parameter SLTI = 6'd10;
parameter ANDI = 6'd12;
parameter ORI = 6'd13;
parameter XORI = 6'd14;
parameter SLLI = 6'd15;
parameter LW = 6'd35;
parameter SW = 6'd43;

// ALU Functions
parameter NOP = 6'd0;
parameter SLLV = 6'd4;
parameter JR = 6'd8;
parameter ADD = 6'd32;
parameter SUB = 6'd34;
parameter AND = 6'd36;
parameter OR = 6'd37;
parameter XOR = 6'd38;
parameter SLT = 6'd42;					
					
					
/*					
initial begin
	$display("\tIFID \tIDEX \tEXMEM \tMEMWB \talu0	\talu1	\ttime");
    $monitor("\t%b  \t%b  \t%b \t%b  \t%b	\t%b  \t%g",
              instrIFID,
					insrtIDEX,
						  instrEXMEM,
								instrMEMWB,
									  alu0,
											alu1,
												$time   );
   end					
*/					
   parameter delay = 1;					
					
					
	initial begin
	
	
	//reset parameters
	{op_IFID, rs_IFID, rt_IFID, rd_IFID, funct_IFID} = 27'b0;
	{op_IDEX, rs_IDEX, rt_IDEX, rd_IDEX, funct_IDEX} = 27'b0;
	{op_IFID, rs_EXMEM, rt_EXMEM, rd_EXMEM, funct_EXMEM} = 27'b0;
	{op_MEMWB, rs_MEMWB, rt_MEMWB, rd_MEMWB, funct_MEMWB} = 27'b0;
	
	aluEXMEM_Data = 32'd0;
	aluMEMWB_Data = 32'd1;
	EXMEM_Data2Mem = 32'd3;
	MEMWB_MemData = 32'd7;
	
	//BLOCK 1, op_IDEX_is_alui_rd = true
	#delay; 
	op_IDEX = ADDI;

	
		//Case 1, 			op_EXMEM_is_alui_wr
		//result 1: 		alu0 = (rt_EXMEM == rs_IDEX);
		#delay; #delay;	
		op_EXMEM = ADDI;		
		rt_EXMEM = 5'b10101; //true case
		rs_IDEX =  5'b10101;
		#delay; #delay;
		rs_IDEX = 5'b0; 	//false case
		#delay; #delay; 
		#delay; #delay; #delay; #delay; 
		
		
		//Case 2, 			op_EXMEM == 0 && funct_EXMEM_is_alur
		//result 2: 		alu0 = (rd_EXMEM == rs_IDEX);
		#delay; #delay;	
		op_EXMEM = 6'b0;
		funct_EXMEM = ADD;
		rd_EXMEM = 5'b10101; //true case
		rs_IDEX =  5'b10101;
		#delay; #delay;
		rs_IDEX = 5'b0; 	//false case
		#delay; #delay;
		#delay; #delay; #delay; #delay; 
		
		op_EXMEM = 6'b0;
		funct_EXMEM = 6'b111111;

		//Case 3:   		op_MEMWB_is_alui_wr || op_MEMWB == LW
		//result 3: 		alu0 = (rd_MEMWB == rs_IDEX);
		#delay; #delay;	
		op_MEMWB = ADDI;
		rd_MEMWB = 5'b10101; //true case
		rs_IDEX =  5'b10101;
		#delay; #delay;
		rs_IDEX = 5'b0; 	//false case
		#delay; #delay;

		op_MEMWB = LW;
		rd_MEMWB = 5'b10101; //true case
		rs_IDEX =  5'b10101;
		#delay; #delay;
		rs_IDEX = 5'b0; 	//false case
		#delay; #delay;


		//Case 4: 			else for above
		//result  			alu0 = (rd_MEMWB == rs_IDEX);
		#delay; #delay;	
		op_MEMWB = 6'b0;
		rd_MEMWB = 5'b10101; //true case
		rs_IDEX =  5'b10101;
		#delay; #delay;
		rs_IDEX = 5'b0; 	//false case
		#delay; #delay;


		//Case 5: 			op_EXMEM_is_alui_wr || (op_EXMEM == 0 && funct_EXMEM_is_alur)
		//result: 			aluD0 = aluEXMEM_Data;
		#delay; #delay;	
		op_EXMEM = ADDI;
		
	op_IDEX = 6'b1;	
		

	
	{op_IFID, rs_IFID, rt_IFID, rd_IFID, funct_IFID} = 27'b0;
	{op_IDEX, rs_IDEX, rt_IDEX, rd_IDEX, funct_IDEX} = 27'b0;
	{op_IFID, rs_EXMEM, rt_EXMEM, rd_EXMEM, funct_EXMEM} = 27'b0;
	{op_MEMWB, rs_MEMWB, rt_MEMWB, rd_MEMWB, funct_MEMWB} = 27'b0;

	//BLOCK 2, !(op_IDEX_is_alui_rd) && op_IDEX == 0 && funct_IDEX_is_alur
	
	
		//SUB-BLOCK A, op_EXMEM_is_alui_wr

		
		

			

			
			
			
			
			
			
			
	$finish;
	end
					
					
endmodule

Lab5/verilog/dataForwarding/DFTest.vcd
$date
	Thu Jun 02 18:34:53 2016
$end
$version
	Icarus Verilog
$end
$timescale
	1s
$end
$scope module df_tb $end
$scope module dut $end
$var wire 1 ! funct_EXMEM_is_alur $end
$var wire 1 " funct_IDEX_is_alur $end
$var wire 1 # funct_IFID_is_alur $end
$var wire 1 $ funct_MEMWB_is_alur $end
$var wire 1 % op_EXMEM_is_alui_rd $end
$var wire 1 & op_EXMEM_is_alui_wr $end
$var wire 1 ' op_EXMEM_is_alur $end
$var wire 1 ( op_IDEX_is_alui_rd $end
$var wire 1 ) op_IDEX_is_alui_wr $end
$var wire 1 * op_IDEX_is_alur $end
$var wire 1 + op_IFID_is_alui_rd $end
$var wire 1 , op_IFID_is_alui_wr $end
$var wire 1 - op_IFID_is_alur $end
$var wire 1 . op_MEMWB_is_alui_rd $end
$var wire 1 / op_MEMWB_is_alui_wr $end
$var wire 1 0 op_MEMWB_is_alur $end
$var wire 5 1 rt_MEMWB [4:0] $end
$var wire 5 2 rt_IFID [4:0] $end
$var wire 5 3 rt_IDEX [4:0] $end
$var wire 5 4 rt_EXMEM [4:0] $end
$var wire 5 5 rs_MEMWB [4:0] $end
$var wire 5 6 rs_IFID [4:0] $end
$var wire 5 7 rs_IDEX [4:0] $end
$var wire 5 8 rs_EXMEM [4:0] $end
$var wire 5 9 rd_MEMWB [4:0] $end
$var wire 5 : rd_IFID [4:0] $end
$var wire 5 ; rd_IDEX [4:0] $end
$var wire 5 < rd_EXMEM [4:0] $end
$var wire 5 = op_MEMWB [4:0] $end
$var wire 5 > op_IFID [4:0] $end
$var wire 5 ? op_IDEX [4:0] $end
$var wire 5 @ op_EXMEM [4:0] $end
$var wire 32 A instrMEMWB [31:0] $end
$var wire 32 B instrIFID [31:0] $end
$var wire 32 C instrIDEX [31:0] $end
$var wire 32 D instrEXMEM [31:0] $end
$var wire 6 E funct_MEMWB [5:0] $end
$var wire 6 F funct_IFID [5:0] $end
$var wire 6 G funct_IDEX [5:0] $end
$var wire 6 H funct_EXMEM [5:0] $end
$var wire 32 I aluMEMWB_Data [31:0] $end
$var wire 32 J aluEXMEM_Data [31:0] $end
$var wire 32 K MEMWB_MemData [31:0] $end
$var wire 32 L EXMEM_Data2Mem [31:0] $end
$var reg 1 M alu0 $end
$var reg 1 N alu1 $end
$var reg 32 O aluD0 [31:0] $end
$var reg 32 P aluD1 [31:0] $end
$var reg 1 Q calc_branch $end
$var reg 1 R exmem $end
$var reg 32 S exmemD [31:0] $end
$var reg 1 T jmp0 $end
$var reg 32 U jmp0D [31:0] $end
$var reg 1 V jmp1 $end
$var reg 32 W jmp1D [31:0] $end
$var reg 32 X memMemD [31:0] $end
$var reg 1 Y mem_mem $end
$var reg 1 Z stall $end
$upscope $end
$upscope $end
$enddefinitions $end
#0
$dumpvars
xZ
xY
bx X
bx W
xV
bx U
xT
bx S
xR
xQ
bx P
bx O
xN
xM
b11 L
b111 K
b0 J
b1 I
b0 H
b0 G
b0 F
b0 E
b0xxxxx00000000000000011111000000 D
b11111000000 C
b11111000000 B
b11111000000 A
bx @
b0 ?
b0 >
b0 =
b0 <
b0 ;
b0 :
b0 9
b0 8
b0 7
b0 6
b0 5
b0 4
b0 3
b0 2
b0 1
00
x/
0.
0-
0,
0+
0*
0)
0(
x'
x&
x%
0$
0#
0"
0!
$end
#1
1M
0N
1(
b1000 ?
b100000000000000000011111000000 C
#3
1%
b0 O
1&
1/
0'
1M
b1000 @
b10101 7
b10101 4
b100010101000000000011111000000 C
b100000000101010000011111000000 D
#5
0M
b0 7
b100000000000000000011111000000 C
#13
0%
1!
0&
0/
1M
b0 @
b10101 7
b10101 <
b100000 H
b100010101000000000011111000000 C
b101011010111111100000 D
#15
0M
b0 7
b100000000000000000011111000000 C
#21
0(
0!
1M
b0 ?
b0 4
b0 <
b0 H
b11111000000 D
b11111000000 C
#23
1.
b1000 =
b10101 7
b10101 9
b10101000000000011111000000 C
b100000000000001010111111000000 A
#25
b0 7
b11111000000 C
#27
0.
b11 =
b10101 7
b10101000000000011111000000 C
b1100000000001010111111000000 A
#29
b0 7
b11111000000 C
#33
b0 =
b10101 7
b10101000000000011111000000 C
b1010111111000000 A
#35
b0 7
b11111000000 C
#39
1%
1&
1/
b1000 @
b0 9
b11111000000 A
b11111000000 C
b100000000000000000011111000000 D
