Lab_1/verilog/1_SupCounter/DFlipFlop.v
/*
Author: Lab-provided code
Title: D flip-flop
Summary: Behavioral model of a d flip-flop
*/


module DFlipFlop(q, qBar, D, clk, rst);
   input D, clk, rst; // DFF input, clock, reset
   output q, qBar; // DFF output, DFF negated output
   reg q;

   not n1 (qBar, q); // negate q

   // flip-flop storage logic
   always@ (negedge rst or posedge clk)
   begin
      if(!rst)
         q = 0;
      else
         q = D;
   end
endmodule

Lab_1/verilog/3_Johnson/JohnsonTester.v
// Title:  4-bit Synchronous Johnson Counter Test Bench
// Author: Adolfo Pineda
// A testing module for the 4-bit synchronous johnson counter
// that gets the counter to start counting

module JohnsonTester (clk, rst, q0, q1, q2, q3);

	integer i;
	input q0, q1, q2, q3;
	output reg clk, rst;
	parameter stimDelay = 1;
	
	wire [3:0] count;
	
	assign count = {q3, q2, q1, q0};
	initial // Response
	begin
	// Displays the labels and data
	$display("\t\t clk \t rst \t q3 \t q2 \t q1 \t q0 \t Count \t Time ");
	$monitor("\t\t %b \t %b \t %b \t %b \t %b \t %b \t %d \t %g", clk, rst, q3, q2, q1, q0, count, $time );
	end

	initial // Stimulus
	begin
	clk = 0; 
	rst = 1;
	#stimDelay;
	rst = 0;
	#stimDelay;
	// Counting starts at this point
	rst = 1;
	#stimDelay;
	for (i = 0; i < 32; i = i + 1) begin
		#stimDelay;
		clk = ~clk;
	end
	
	rst = 0;
	#stimDelay;
	rst = 1;
	#stimDelay;
	for (i = 0; i < 8; i = i + 1) begin
		#stimDelay;
		clk = ~clk;
	end

	#(2*stimDelay); // needed to see END of simulation
	$finish; // finish simulation
	end
	endmodule

Lab1/verilog/3_Johnson/Johnson.v
// Title:  4-bit Synchronous Johnson Counter
// Author: Adolfo Pineda
// This module is the 4-bit synchronous johnson counter
// with active low reset

module Johnson(q0, q1, q2, q3, clk, rst);
input clk, rst;
output reg q0, q1, q2, q3;

	// A johnson counter using behavioral level model logic 
	always @(negedge rst or posedge clk) begin
		if (!rst) begin
			q0 <= 0;
			q1 <= 0;
			q2 <= 0;
			q3 <= 0;
		end else begin
			q0 <= ~q3;
			q1 <= q0;
			q2 <= q1;
			q3 <= q2;
		end
	end

endmodule

Lab1/verilog/3_Johnson/Johnson_tb.v
// Title:  4-bit Synchronous Johnson Counter Test Bench
// Author: Adolfo Pineda
// A test bench module for the 4-bit Synchronous Johnson Counter
// that makes sure it is working perfectly

// All files used
`include "Johnson.v"
`include "JohnsonTester.v"
//`include "DFlipFlop.v"

module Johnson_tb;
	wire q0, q1, q2, q3, clk, rst;

	// Declare an instance of the Johnson module
	Johnson john (q0, q1, q2, q3, clk, rst);
	
	// Declare an instance of the JohnsonTester module
	JohnsonTester aTester (clk, rst, q0, q1, q2, q3);

	// File for gtkwave
	initial begin
		$dumpfile("Johnson.vcd");
		$dumpvars(1, john);
		
	end
endmodule

Lab1/verilog/3_Johnson/Johnson.vcd
$date
	Thu Apr 07 16:14:22 2016
$end
$version
	Icarus Verilog
$end
$timescale
	1s
$end
$scope module Johnson_tb $end
$scope module john $end
$var wire 1 ! clk $end
$var wire 1 " rst $end
$var reg 1 # q0 $end
$var reg 1 $ q1 $end
$var reg 1 % q2 $end
$var reg 1 & q3 $end
$upscope $end
$upscope $end
$enddefinitions $end
#0
$dumpvars
x&
x%
x$
x#
1"
0!
$end
#1
0&
0%
0$
0#
0"
#2
1"
#4
1#
1!
#5
0!
#6
1$
1!
#7
0!
#8
1%
1!
#9
0!
#10
1&
1!
#11
0!
#12
0#
1!
#13
0!
#14
0$
1!
#15
0!
#16
0%
1!
#17
0!
#18
0&
1!
#19
0!
#20
1#
1!
#21
0!
#22
1$
1!
#23
0!
#24
1%
1!
#25
0!
#26
1&
1!
#27
0!
#28
0#
1!
#29
0!
#30
0$
1!
#31
0!
#32
0%
1!
#33
0!
#34
0&
1!
#35
0"
0!
#36
1"
#38
1#
1!
#39
0!
#40
1$
1!
#41
0!
#42
1%
1!
#43
0!
#44
1&
1!
