Lab5/verilog/alu/alu.v
/*
Author: Adolfo Pineda & Ian Gilman
Title: Behavioral Arithmetic Logic Unit
Summary: two-operand / one-result implementation with Add/Sub/And/Or/Xor/Slt/Sll
functions selected by control code and produces status flags for 
zero result (Z), overflow (V), carry out (C), and negative result (N).
*/

module alu(
         fr_read0, 
         fr_read1, 
         immediate, 
         forward0, 
         forward1, 
         control, 
         alu1_src,
         alu0_fwd,
         alu1_fwd, 
         result, 
         Z, 
         V, 
         C, 
         N
      );

	// I/O
	input wire [31:0] fr_read0, fr_read1,  // file register read data
                     immediate,  // immediate value
                     forward0, forward1;  // data forwarded to alu mux 0 & 1
	input wire [5:0] control;  // determines operation performed
   input wire alu1_src, alu0_fwd, alu1_fwd;  // alu op1 source, alu op0 forwarded, alu op1 forwarded
	output reg [31:0] result;  // result of operation
	output reg Z, V, C, N;  // status flags after operation
	
	// Internal
	wire [31:0] add_result, sub_result, and_result,     //  wires connected to 
			   or_result, xor_result, slt_result,       	//  operation sub-module
			   sll_result, operand0, operand1;          //  results
			   
	wire add_Z, sub_Z, // zero flags
		 add_V, sub_V, // overflow flags
		 add_C, sub_C, // carry flags
		 add_N, sub_N; // negative value flags   
       
	reg op0_msb, op1_msb, result_msb;
	reg [31:0] twos_comp_op1, result_manip;

   // Determine operands
   assign operand0 = alu0_fwd ? forward0 : fr_read0;
   assign operand1 = alu1_src ? immediate : (alu1_fwd ? forward1 : fr_read1);
	
	// ALU operation control codes
	parameter NOP = 6'd0;
	parameter ADD = 6'd32;
	parameter SUB = 6'd34;
	parameter AND = 6'd36;
	parameter OR  = 6'd37;
	parameter XOR = 6'd38;
	parameter SLT = 6'd42;
	parameter SLL = 6'd4;
	
	always @ (*) begin
		case (control)
		
			NOP: begin
				Z = 0;
				V = 0;
				C = 0;
				N = 0;
				result = 0;
			end
			
			ADD: begin
				op0_msb = operand0[31];
				op1_msb = operand1[31];
				result = operand0 + operand1;
				result_msb = result[31];
				
				Z = (result == 0);
				V = (~(op0_msb ^ op1_msb)) & (op0_msb ^ result_msb);
				C = (op0_msb & op1_msb) | (op0_msb & ~result_msb) | (op1_msb & ~result_msb);
				N = (result_msb == 1);
				
			end
			
			SUB: begin
				twos_comp_op1 = ~operand1 + 32'b1;
				result_manip = operand0 + twos_comp_op1;
				op0_msb = operand0[31];
				op1_msb = twos_comp_op1[31];
				result_msb = result_manip[31];
				result = operand0 - operand1;
				
				Z = (result == 0);
				V = (op0_msb & op1_msb & ~result_msb) | (~op0_msb & ~op1_msb & result_msb);
				C = (op0_msb & op1_msb) | (op0_msb & ~result_msb) | (op1_msb & ~result_msb) | ((operand0 == 0) & (operand1 == 0) & (result == 0));
				N = (result_msb == 1);
				
			end
			
			AND: begin
				result = operand0 & operand1;
				Z = (result == 0);
				V = 0; 
				C = 0;
				N = (result[31] == 1);
					
			end
			
			OR: begin
				result = operand0 | operand1;
				Z = (result == 0);
				V = 0; 
				C = 0;
				N = (result[31] == 1);
				
			end
			
			XOR: begin
				result = operand0 ^ operand1;
				Z = (result == 0);
				V = 0; 
				C = 0;
				N = (result[31] == 1);
				
			end
			
			SLT: begin
				result = (operand0 < operand1) ? 1 : 0;
				Z = (result == 0);
				V = 0; 
				C = 0;
				N = (result[31] == 1);
				
			end
			
			SLL: begin
				result = operand0 << operand1;
				Z = (result == 0);
				V = 0; 
				C = 0;
				N = (result[31] == 1);
				
			end
		
		endcase
	end
	
endmodule

Lab5/verilog/alu/alu_tb.v
// All files used
`include "alu.v"

// Title: 	ALU behavioral Test bench
// Author: 	Adolfo Pineda & Ian Gilman
// Summary:	A test bench module
module alu_tb;
   wire [31:0] fr_read0, fr_read1,  // file register read data
                     immediate,  // immediate value
                     forward0, forward1;  // data forwarded to alu mux 0 & 1
	wire [5:0] control;  // determines operation performed
   wire alu1_src, alu0_fwd;  // alu op1 source, alu op0 forwarded, alu op1 forwarded
	wire [31:0] result;  // result of operation
	wire Z, V, C, N;  // status flags after operation
	
	// dut
	alu dut(fr_read0, 
         fr_read1, 
         immediate, 
         forward0, 
         forward1, 
         control, 
         alu1_src,
         alu0_fwd,
         alu1_fwd, 
         result, 
         Z, 
         V, 
         C, 
         N
   );
	
	// tester
	aluTester tester(
         fr_read0, 
         fr_read1, 
         immediate, 
         forward0, 
         forward1, 
         control, 
         alu1_src,
         alu0_fwd,
         alu1_fwd, 
         result, 
         Z, 
         V, 
         C, 
         N
   );

	// File for gtkwave
	initial begin
		$dumpfile("alu_test.vcd");
		$dumpvars(1, dut);
	end
endmodule



// Title: ALU behavioral tester
// Author: Adolfo Pineda
// A testing module

module aluTester(
         fr_read0, 
         fr_read1, 
         immediate, 
         forward0, 
         forward1, 
         control, 
         alu1_src,
         alu0_fwd,
         alu1_fwd, 
         result, 
         Z, 
         V, 
         C, 
         N
   );
	// I/O
	output reg [31:0] fr_read0, fr_read1,  // file register read data
                     immediate,  // immediate value
                     forward0, forward1;  // data forwarded to alu mux 0 & 1
	output reg [5:0] control;  // determines operation performed
   output reg alu1_src, alu0_fwd, alu1_fwd;  // alu op1 source, alu op0 forwarded, alu op1 forwar
	input wire [31:0] result;  // result of operation
	input wire Z, V, C, N;  // status flags after operation
	
	parameter delay = 10;

	// ALU operation control codes
	parameter NOP = 6'd0;
	parameter ADD = 6'd32;
	parameter SUB = 6'd34;
	parameter AND = 6'd36;
	parameter OR  = 6'd37;
	parameter XOR = 6'd38;
	parameter SLT = 6'd42;
	parameter SLL = 6'd4;
	
	// Display variables 
	initial begin
		$display("\tfr0\t\tfr1\t   imm\t      FD0\t FD1\tcontrol  sor F0 F1\t res\t Z V C N\t time");
		$monitor(" %d\t %d %d %d %d\t %b  %b   %b  %b %d\t %b %b %b %b\t %g", 
												fr_read0, 
												fr_read1,
                                    immediate,
                                    forward0,
                                    forward1,
												control,
                                    alu1_src,
                                    alu0_fwd,
                                    alu1_fwd,
												result, 
												Z, 
												V, 
												C, 
												N, 
												$time);
	end
	
	initial begin
		#delay; #delay; #delay;
		
      alu1_src <= 0;
      alu0_fwd <= 0;
      alu1_fwd <= 0;
		control <= SUB;
		immediate <= 32'h14;
      
      // Subtraction
		 #delay;
		fr_read0 <= 32'd0;
		fr_read1 <= 32'd0;
		#delay;
      alu1_src <= 1;
		fr_read0 <= 32'd500;
		immediate <= 32'd500;
      forward0 <= 32'd500000000;
      forward1 <= 32'd300000000;
		#delay;
      alu1_src <=0;
      alu0_fwd <=1;
		fr_read0 <= 32'd30000000;
		fr_read1 <= 32'd30000000;
		#delay; #delay;
      alu1_fwd <= 1;
		fr_read0 <= 32'hFFFFFFE6;
		fr_read1 <= 32'd10;

      // Addition
      control <= ADD;
		#delay;
		fr_read0 <= 32'hFFFFFFFF;
		fr_read1 <= 32'h00000001;
		#delay;
      alu0_fwd <= 0;
		fr_read0 <= 32'd10;
		fr_read1 <= 32'hFFFFFFFA;
		#delay;
      alu1_fwd <= 0;
      alu1_src <= 1;
		fr_read0 <= 32'd5;
		fr_read1 <= 32'hFFFFFFF6;

		#delay;
      alu1_src = 0;
		fr_read0 <= 32'd2147483647;
		fr_read1 <= 32'd2147483647;
		#delay;#delay;
		fr_read0 <= 32'd3147483647;
		fr_read1 <= 32'd3147483647;
		#delay;#delay;
		fr_read0 <= 32'hFFFFF000;
		fr_read1 <= 32'h80000000;
		#delay;#delay;
		fr_read0 <= 32'd2147483647;
		fr_read1 <= 32'd2147483647;
		#delay;#delay;
		fr_read0 <= 32'h80000000;
		fr_read1 <= 32'h00000001;
		#delay;#delay;
		fr_read0 <= 32'hC0000000;
		fr_read1 <= 32'hC0000000;
		#delay;#delay;
		fr_read0 <= 32'h80000000;
		fr_read1 <= 32'h80000000;
      alu1_src <= 1'b1;
      control <=ADD;
		#delay;#delay;
		fr_read1 <= 32'hFFFFFFF6;
		fr_read0 <= 32'hFFFFFFF6;
		#delay; #delay; #delay;
	end
endmodule

Lab5/verilog/alu/alu_test.vcd
$date
	Wed Jun 01 19:30:34 2016
$end
$version
	Icarus Verilog
$end
$timescale
	1s
$end
$scope module alu_tb $end
$scope module dut $end
$var wire 32 ! operand1 [31:0] $end
$var wire 32 " operand0 [31:0] $end
$var wire 32 # immediate [31:0] $end
$var wire 32 $ fr_read1 [31:0] $end
$var wire 32 % fr_read0 [31:0] $end
$var wire 32 & forward1 [31:0] $end
$var wire 32 ' forward0 [31:0] $end
$var wire 6 ( control [5:0] $end
$var wire 1 ) alu1_src $end
$var wire 1 * alu1_fwd $end
$var wire 1 + alu0_fwd $end
$var reg 1 , C $end
$var reg 1 - N $end
$var reg 1 . V $end
$var reg 1 / Z $end
$var reg 1 0 op0_msb $end
$var reg 1 1 op1_msb $end
$var reg 32 2 result [31:0] $end
$var reg 32 3 result_manip [31:0] $end
$var reg 1 4 result_msb $end
$var reg 32 5 twos_comp_op1 [31:0] $end
$upscope $end
$upscope $end
$enddefinitions $end
#0
$dumpvars
bx 5
x4
bx 3
bx 2
x1
x0
x/
x.
x-
x,
x+
x*
x)
bx (
bx '
bx &
bx %
bx $
bx #
bx "
bx !
$end
#30
b10100 #
b100010 (
0*
0+
0)
#40
0-
1,
0.
1/
b0 2
04
01
b0 3
b0 5
b0 !
00
b0 "
b0 $
b0 %
#50
11
b11111111111111111111111000001100 5
b111110100 "
b111110100 !
b10001111000011010001100000000 &
b11101110011010110010100000000 '
b111110100 #
b111110100 %
1)
#60
1,
0/
b11100000000111010000110000000 2
11
b11100000000111010000110000000 3
b11111110001101100011110010000000 5
b11101110011010110010100000000 "
b1110010011100001110000000 !
b1110010011100001110000000 $
b1110010011100001110000000 %
1+
0)
#80
b10001111000011010001100000000 !
0,
b101111101011110000100000000000 2
01
b100000 (
b1010 $
b11111111111111111111111111100110 %
1*
#90
b1 $
b11111111111111111111111111111111 %
#100
b10001111000011010001100001010 2
b1010 "
b11111111111111111111111111111010 $
b1010 %
0+
#110
b111111001 2
b101 "
b111110100 !
b11111111111111111111111111110110 $
b101 %
1)
0*
#120
1.
0,
b1111111111111111111111111111111 "
b1111111111111111111111111111111 $
b1111111111111111111111111111111 %
1-
14
b11111111111111111111111111111110 2
01
b1111111111111111111111111111111 !
0)
#140
11
b10111011100110101100100111111111 !
0-
1,
1.
04
b1110111001101011001001111111110 2
10
b10111011100110101100100111111111 "
b10111011100110101100100111111111 $
b10111011100110101100100111111111 %
#160
b10000000000000000000000000000000 !
0-
1.
04
b1111111111111111111000000000000 2
b11111111111111111111000000000000 "
b10000000000000000000000000000000 $
b11111111111111111111000000000000 %
#180
01
b1111111111111111111111111111111 !
1-
0,
1.
14
b11111111111111111111111111111110 2
00
b1111111111111111111111111111111 "
b1111111111111111111111111111111 $
b1111111111111111111111111111111 %
#200
b1 !
0.
b10000000000000000000000000000001 2
10
b10000000000000000000000000000000 "
b1 $
b10000000000000000000000000000000 %
#220
1,
11
b11000000000000000000000000000000 !
b10000000000000000000000000000000 2
b11000000000000000000000000000000 "
b11000000000000000000000000000000 $
b11000000000000000000000000000000 %
#240
0,
b10000000000000000000000111110100 2
01
b111110100 !
b10000000000000000000000000000000 "
1)
b10000000000000000000000000000000 $
b10000000000000000000000000000000 %
#260
0-
1,
04
b111101010 2
b11111111111111111111111111110110 "
b11111111111111111111111111110110 %
b11111111111111111111111111110110 $
