Lab2/verilog/file_register/file_register_tester.v
/*
Author: Ian Gilman
Title: 32x32 File Register HW Tester
Summary: Create test stimulus for 32x32 file register, prints out logic results
*/

module file_register_tester(
         clk, 
         we, 
         rst, 
         read0_addr, 
         read1_addr, 
         write_addr, 
         data_bus
       );
   input wire [31:0] read0_data,  // data to be read from read0 address
                     read1_data;  // data to be read from read1 address
   output reg clk, we, rst;  // clock, write enable, low reset
   output reg [4:0] read0_addr,  // read0 register address selection
                    read1_addr,  // read1 register address selection
                    write_addr;  // write register address selection
   inout wire [31:0] data_bus;  // data to be read/written from/to file reg
   reg [31:0] write_data; // data to write to bus
   
   // print out test results
   initial begin
         $display("   RA1\tRD1     \tdat     \tWrA\tWrD     \twe \trst\tclk\ttime");
         $monitor("   %h\t%h\t%h \t%h\t%h\t%b  \t%b  \t%b  \t%g",
                  read1_addr, read1_data, data_bus, write_addr,
                  write_data, we, rst, clk, $time);
   end
   
   // write data to file reg
   assign data_bus = we ? write_data : 32'bz;
   //read data from file reg
   assign read1_data = !we ? data_bus : 32'bz;
   
   // create stimulus signals
   parameter delay = 1;
   integer i;
   initial begin
   
      // initial file register state
      clk = 1'b1;
      we = 1'b0;
      read1_addr = 5'b0;
      write_addr = 5'b0;
      write_data = 32'h0;
      rst = 1'b1;   #delay;
      rst = 1'b0;   #delay;
      rst = 1'b1;   #delay;
      for(i=0; i<2; i=i+1) begin
         clk = ~clk;    #delay;
      end
      
      // write data to register
      write_addr = 5'b1;
      write_data = 32'h5ADFACED;
      for(i=0; i<4; i=i+1) begin
         clk = ~clk;    #delay;
      end
      we = 1'b1;
      for(i=0; i<4; i=i+1) begin
         clk = ~clk;    #delay;
      end
      we = 1'b0;
      
      // second write
      write_addr = 5'b10101;
      write_data = 32'hEA770A57;
      for(i=0; i<4; i=i+1) begin
         clk = ~clk;    #delay;
      end
      we = 1'b1;
      for(i=0; i<4; i=i+1) begin
         clk = ~clk;    #delay;
      end
      we = 1'b0;
      
      // read both in read0
      read1_addr = 5'b1;
      for(i=0; i<4; i=i+1) begin
         clk = ~clk;    #delay;
      end
      read1_addr = 5'b10101;
      for(i=0; i<4; i=i+1) begin
         clk = ~clk;    #delay;
      end
      
      $finish;
   end
endmodule

Lab2/verilog/shared_modules/d_flipflop/d_flipflop.v
/*
Author: Lab-provided code
Title: D flip-flop
Summary: Behavioral model of a d flip-flop
*/

module d_flipflop(q, qBar, D, clk, rst);
   input D, clk, rst; // DFF input, clock, reset
   output q, qBar; // DFF output, DFF negated output
   reg q;

   not n1 (qBar, q); // negate q

   // flip-flop storage logic
   always@ (negedge rst or posedge clk)
   begin
      if(!rst)
         q = 0;
      else
         q = D;
   end
endmodule

Lab2/verilog/file_register/register_32bit/register_32bit.v
/*
Author: Ian Gilman
Title: 32-bit Parallel In/Out Register
Summary: 32 synchronous d flip-flops configured to operate as a parallel in/out,
   register with write enable and reset.
*/

// Module Dependencies:
//`include "register_32bit/d_flipflop/d_flipflop.v"

module register_32bit(clk, we, rst, D, Q);
   input wire clk, we, rst;  // clock, write enabled, active-low reset register
   input wire [31:0] D;  // parallel data to write
   output wire [31:0] Q;  // parallel data from register
   wire [31:0] parallel_write_data;  // parallel data to register
   
   // write new data to register if write is enabled, else keep same data
   assign parallel_write_data = we ? D : Q;
   
   // register of 32 d flip-flops
   genvar i;
   generate for(i=0; i<32; i=i+1) begin: REGISTER
      d_flipflop FF(.q(Q[i]), .qBar(), .D(parallel_write_data[i]), .clk(clk), .rst(rst));
   end
   endgenerate
endmodule

Lab2/Verilog/file_register/decoder_5bit/mux_2to1/mux_2to1.v
/*
Author: Ian Gilman
Title: 2:1 Output Multiplexer
Summary: choose one of 2 inputs to output based on select
*/

module mux_2to1(in0, in1, select, out);
   input wire in0, in1, select;
   output wire out;
   wire sel0, sel1;
   
   and and_sel0(sel0, in0, !select);
   and and_sel1(sel1, in1, select);
   or or_sel(out, sel0, sel1);
endmodule

Lab2/verilog/file_register/decoder_5bit/decoder_5bit.v
// Module Dependencies
//`include mux_2to1/mux_2to1

/*
Author: Ian Gilman
Title: Single-output 5:1 Decoder
Summary: Recieves a code on 5-bit inputs which raises a logic high on 1 of the
   32 outputs while the rest are held low
*/

module decoder_5bit(code, selection);
   input wire [4:0] code;  // code driving which selct is output
   output wire [31:0] selection;  // outputs including single selection
   wire [31:0] mux1, mux2, mux3, mux4;
   
   // shift high value to proper selection based on code (barrel shifter)
   genvar i;
   generate
      for(i=0; i<32; i=i+1) begin: BARREL
         // 1st shift
         if(i == 0)
            mux_2to1 BARREL0(.in0(1'b1), .in1(1'b0), .select(code[0]), .out(mux1[i]));
         else if(i == 1)
            mux_2to1 BARREL0(.in0(1'b0), .in1(1'b1), .select(code[0]), .out(mux1[i]));
         else
            mux_2to1 BARREL0(.in0(1'b0), .in1(1'b0), .select(code[0]), .out(mux1[i]));
         // 2nd shift
         if(i < 2)
            mux_2to1 BARREL1(.in0(mux1[i]), .in1(1'b0), .select(code[1]), .out(mux2[i]));
         else
            mux_2to1 BARREL1(.in0(mux1[i]), .in1(mux1[i-2]), .select(code[1]), .out(mux2[i]));
         // 3rd shift
         if(i < 4)
            mux_2to1 BARREL2(.in0(mux2[i]), .in1(1'b0), .select(code[2]), .out(mux3[i]));
         else
            mux_2to1 BARREL2(.in0(mux2[i]), .in1(mux2[i-4]), .select(code[2]), .out(mux3[i]));
         // 4th shift
         if(i < 8)
            mux_2to1 BARREL3(.in0(mux3[i]), .in1(1'b0), .select(code[3]), .out(mux4[i]));
         else
            mux_2to1 BARREL3(.in0(mux3[i]), .in1(mux3[i-8]), .select(code[3]), .out(mux4[i]));
         // 5th shift
         if(i < 16)
            mux_2to1 BARREL4(.in0(mux4[i]), .in1(1'b0), .select(code[4]), .out(selection[i]));
         else
            mux_2to1 BARREL4(.in0(mux4[i]), .in1(mux4[i-16]), .select(code[4]), .out(selection[i]));
      end
   endgenerate
endmodule

Lab2/verilog/file_register/file_register.v

// Module Dependencies:
//`include "register_32bit/d_flipflop/d_flipflop.v"
//`include "register_32bit/register_32bit.v"
//`include "decoder_5bit/decoder_5bit.v"


/*
Author: Ian Gilman
Title: 32x32 File Register
Summary: MIPS-based 32 by 32 file register with data-bus-based dual-read/write
*/

module file_register(
         clk, 
         we, 
         rst,
         read0_addr, 
         read1_addr,
         write_addr,
         data_bus
       );
   input wire clk, we, rst;  // clock, write enable, low reset file registers
   input wire [4:0] read0_addr,  // read0 register address selection
                     read1_addr,  // read1 register address selection
                     write_addr;  // write register address selection
   inout [31:0] data_bus;  // bus for data read/write
   wire [31:0] read0_data,  // data from read0_addr 
               read1_data,  // data from read1_addr 
               write_data;  // data to write to write_addr
   
   // read from file register buffer
   assign data_bus = we ? 32'bz : read1_data;
   // write to file register buffer
   assign write_data = we ? data_bus : 32'bz;

   // file register hardware
   file_register_low FILE_REG_HW(
                       .clk(clk), 
                       .we(we), 
                       .rst_all(rst), 
                       .read0_addr(read0_addr), 
                       .read1_addr(read1_addr), 
                       .write_addr(write_addr), 
                       .write_data(write_data),
                       .read0_data(read0_data), 
                       .read1_data(read1_data)
                     );
endmodule



/*
Author: Ian Gilman
Title: 32x32 File Register Lower-Level HW
Summary: MIPS-based 32 by 32-bit file register hardware module with dual-read
   and single enabled-write
*/

module file_register_low(
         clk, 
         we, 
         rst_all, 
         read0_addr, 
         read1_addr, 
         write_addr, 
         write_data,
         read0_data, 
         read1_data
       );
   input wire clk, we, rst_all;  // clock, write enable, low reset all registers
   input wire [4:0] read0_addr,  // read0 register address selection
                    read1_addr,  // read1 register address selection
                    write_addr;  // write register address selection
   input wire [31:0] write_data;  // data to be written to write address
   output wire [31:0] read0_data,  // data to be read from read0 address
                      read1_data;  // data to be read from read1 address
   wire [31:0] Q[31:0];  // data read from all registers
   wire [31:0] wreg_sel,  // write register selection
               we_sel;  // write enable to selected register
  
   // write enable register selection
   assign we_sel = we ? wreg_sel : 32'b0;
   decoder_5bit write_decoder(.code(write_addr), .selection(wreg_sel));
   // read data selection
   assign read0_data = Q[read0_addr];
   assign read1_data = Q[read1_addr];
   
   // 32, 32-bit registers
   genvar i;
   generate for(i=0; i<32; i=i+1) begin: FILE_REGISTER
      register_32bit F_REG(
                        .clk(clk), 
                        .we(we_sel[i]), 
                        .rst(rst_all), 
                        .D(write_data), 
                        .Q(Q[i])
                     );
   end
   endgenerate
endmodule

Lab2/verilog/file_register/file_register_testbench.v
/*
Author: Ian Gilman
Title: 32x32 File Register HW Test Bench
Summary: Link 32x32 file register DUT to test stimulus device and record 
   waveform data
*/

// Module Dependencies:
`include "register_32bit/d_flipflop/d_flipflop.v"
`include "register_32bit/register_32bit.v"
`include "decoder_5bit/mux_2to1/mux_2to1.v"
`include "decoder_5bit/decoder_5bit.v"
`include "file_register.v"
`include "file_register_tester.v"

module file_register_testbench();
   wire clk, we, rst;  // clock, write enable, low reset
   wire [4:0] read0_addr,  // read0 register address selection 
              read1_addr,  // read1 register address selection
              write_addr;  // write register address selection
   wire [31:0] data_bus;  // data bus to/from file register

   // DUT and test stimulus
   file_register FILE_REG(
         .clk(clk), 
         .we(we), 
         .rst(rst), 
         .read0_addr(read0_addr), 
         .read1_addr(read1_addr), 
         .write_addr(write_addr), 
         .data_bus(data_bus)
       );
   file_register_tester TESTER(
         .clk(clk), 
         .we(we), 
         .rst(rst), 
         .read0_addr(read0_addr), 
         .read1_addr(read1_addr), 
         .write_addr(write_addr), 
         .data_bus(data_bus)
       );
   
   // Store waveform data
   initial begin
      $dumpfile("file_register.vcd");
      $dumpvars(1, FILE_REG);
   end
endmodule

Lab2/verilog/file_register/file_register.vcd
$date
	Thu Apr 14 16:48:16 2016
$end
$version
	Icarus Verilog
$end
$timescale
	1s
$end
$scope module file_register_testbench $end
$scope module FILE_REG $end
$var wire 32 ! data_bus [31:0] $end
$var wire 32 " write_data [31:0] $end
$var wire 5 # write_addr [4:0] $end
$var wire 1 $ we $end
$var wire 1 % rst $end
$var wire 32 & read1_data [31:0] $end
$var wire 5 ' read1_addr [4:0] $end
$var wire 32 ( read0_data [31:0] $end
$var wire 5 ) read0_addr [4:0] $end
$var wire 1 * clk $end
$upscope $end
$upscope $end
$enddefinitions $end
#0
$dumpvars
1*
bx )
bx (
b0 '
bx &
1%
0$
b0 #
bz "
bx !
$end
#1
b0 !
b0 &
0%
#2
1%
#3
0*
#4
1*
#5
0*
b1 #
#6
1*
#7
0*
#8
1*
#9
b1011010110111111010110011101101 "
b1011010110111111010110011101101 !
0*
1$
#10
1*
#11
0*
#12
1*
#13
bz "
b0 !
0*
b10101 #
0$
#14
1*
#15
0*
#16
1*
#17
b11101010011101110000101001010111 "
b11101010011101110000101001010111 !
0*
1$
#18
1*
#19
0*
#20
1*
#21
bz "
b1011010110111111010110011101101 !
0*
b1011010110111111010110011101101 &
b1 '
0$
#22
1*
#23
0*
#24
1*
#25
b11101010011101110000101001010111 !
0*
b11101010011101110000101001010111 &
b10101 '
