Lab2/Verilog/sram/sram.v

/*
Author: Adolfo Pineda
Title: 2kx16 SRAM 
Summary: 2k memory registers of 16 bits memory with data-in & data-out with
   chip select, output enable, write enable
*/

module sram(clk, cs, oe, rw, addr_bus, data_bus);
	input wire clk, cs, oe, rw;  // clock, !chip select, !out enable, read/!write
	inout wire [31:0] addr_bus;  // address bus to mar
	inout wire [31:0] data_bus;  // data bus to mdr
	reg [15:0] memory [0:2047];  // sram array of 16-bit registers
   reg [10:0] mar;  // memory address reg
   reg [15:0] mdr;  // memory data reg
   wire [10:0] sram_mar_bus;  // address bus from mar to sram
   wire [15:0] sram_data_bus;  // data bus from mdr to sram
	
   //// Tristate Buffers for data buses //
	// drive data to data_bus from mdr if reading sram else hi-z
   assign data_bus = (!cs && rw && !oe) ? {16'b0, mdr} : 32'bz;
	// drive data to sram from mdr if writing, drive data to mdr from sram if reading
	// else hi-z
   assign sram_data_bus = (!cs && rw && !oe) ? memory[sram_mar_bus] : ((!cs && !rw && oe) ? mdr : 16'bz);
   
	//// Tristate Buffers for address buses //
	// addr_bus not driven by sram
	assign addr_bus = 32'bz;
	// drive address from mar to sram if reading or writing else hi-z
	assign sram_mar_bus = (!cs && ((rw && !oe) || (!rw && oe))) ? mar : 11'bz;
   
   // Memory Address Register write:
   always @(negedge clk) begin
      if(!cs && ((rw && !oe) || (!rw && oe)))
         mar = addr_bus[10:0];
   end
   
   // Memory Data Register write:
   // write from sram to mdr on posedge clk, 
   // write from data bus to mdr on negedge clk
   always @(clk) begin
      if(!cs) begin
         if(!clk && (!rw && oe))
            mdr = data_bus[15:0];
         else if(clk &&((rw && !oe)))
            mdr = sram_data_bus;
      end
   end   
   
   // SRAM write:
	always @(posedge clk) begin
      if (!cs && (!rw && oe))
         memory[sram_mar_bus] = sram_data_bus;
	end
endmodule

Lab2/Verilog/sram/sram_tb.v
// Title:
// Author: Adolfo Pineda
// A test bench module

// All files used
`include "sram.v"

module sram_tb;

	wire clk, rst, oe, we;
	wire [10:0] address;
	wire [15:0] data;
	wire [15:0] read_out;
	//reg [15:0] other_out;
	
	// Declare an instance of the Johnson module
	sram ram (clk, rst, oe, we, address, data, read_out);
	
	// Declare an instance of the JohnsonTester module
	sramTester aTester (read_out, clk, rst, oe, we, address, data);

	// File for gtkwave
	initial begin
		$dumpfile("sram.vcd");
		$dumpvars(1, ram);
		
	end
endmodule

// Title:
// Author: Adolfo Pineda
// A testing module

module sramTester (read_out, clk, rst, oe, we, address, data);

	integer i;
	input [15:0] read_out;
	output reg clk, rst, oe, we;
	output reg [10:0] address;
	output reg [15:0] data;
	parameter stimDelay = 1;
	
	initial // Response
	begin
	
	// Displays the labels and data
	$display("\t\t clk \t rst \t we \t oe \t addr \t data \t r_out \t Time");
	$monitor("\t\t %b \t %b \t %b \t %b \t %d \t %h \t %h \t %g",
			clk, rst, we, oe, address, data, read_out, $time);
	end

	initial // Stimulus
	begin
	clk = 0; 
	rst = 1;
	we = 0;
	oe = 0;
	data = 16'b0;
	address = 0;
	
	#stimDelay;
	rst = 0;
	#stimDelay;
	rst = 1;
	#stimDelay;
	clk = 1;
	oe = 1;
	//sram[0] = data;
	for (i = 0; i < 32; i = i + 1) begin
		#stimDelay;
		clk = ~clk;
		if (clk) begin
			address = address + 1;
			data = data + 1;
		end
	end
	clk = ~clk;
	#stimDelay;
	
	clk = ~clk;
	#stimDelay;
	
	clk = ~clk;
	#stimDelay;
	
	clk = 0;
	we = 0;
	oe = 0;
	#stimDelay;
	
	clk = 1;
	we = 1;
	oe = 0;
	#stimDelay;
	
	address = 5;
	#stimDelay;
	
	clk = 0;
	#stimDelay;
	
	clk = 1;
	#stimDelay;
	
	address = 10;
	clk = 0;
	#stimDelay;
	
	clk = 1;
	#stimDelay;
	
	clk = 0;
	#stimDelay;
	
	we = 0;
	oe = 1;
	clk = 1;
	#stimDelay;
	
	clk = 0;
	#stimDelay;
	
	clk = 1;
	#stimDelay;
	
	clk = 0;
	#stimDelay;
	
	address = 2000; 
	data = 16'hAAAA;
	clk = 1;
	#stimDelay;
	
	we = 1;
	oe = 0;
	clk = ~clk;
	#stimDelay;
	
	clk = ~clk;
	#stimDelay;
	
	clk = ~clk;
	#stimDelay;
	
	#(2*stimDelay); // needed to see END of simulation
	$finish; // finish simulation
	end
	
endmodule

Lab2/Verilog/sram/sram.vcd
$date
	Sat Apr 16 16:02:07 2016
$end
$version
	Icarus Verilog
$end
$timescale
	1s
$end
$scope module sram_tb $end
$scope module ram $end
$var wire 32 ! addr_bus [31:0] $end
$var wire 1 " clk $end
$var wire 1 # cs $end
$var wire 32 $ data_bus [31:0] $end
$var wire 1 % oe $end
$var wire 1 & rw $end
$var wire 11 ' sram_mar_bus [10:0] $end
$var wire 16 ( sram_data_bus [15:0] $end
$var reg 11 ) mar [10:0] $end
$var reg 16 * mdr [15:0] $end
$upscope $end
$upscope $end
$enddefinitions $end
#0
$dumpvars
bx *
bx )
bz (
bz '
0&
0%
b0 $
1#
1"
bz !
$end
#1
b0 !
0"
0#
#2
bx '
bx (
1"
1%
#3
b1 (
b1 '
b1 *
b1 )
b1 !
b1 $
0"
#4
1"
#5
b10 (
b10 '
b10 *
b10 )
b10 !
b10 $
0"
#6
1"
#7
b11 (
b11 '
b11 *
b11 )
b11 !
b11 $
0"
#8
1"
#9
b100 (
b100 '
b100 *
b100 )
b100 !
b100 $
0"
#10
1"
#11
b101 (
b101 '
b101 *
b101 )
b101 !
b101 $
0"
#12
1"
#13
b110 (
b110 '
b110 *
b110 )
b110 !
b110 $
0"
#14
1"
#15
b111 (
b111 '
b111 *
b111 )
b111 !
b111 $
0"
#16
1"
#17
b1000 (
b1000 '
b1000 *
b1000 )
b1000 !
b1000 $
0"
#18
1"
#19
b1001 (
b1001 '
b1001 *
b1001 )
b1001 !
b1001 $
0"
#20
1"
#21
b1010 (
b1010 '
b1010 *
b1010 )
b1010 !
b1010 $
0"
#22
1"
#23
b1011 (
b1011 '
b1011 *
b1011 )
b1011 !
b1011 $
0"
#24
1"
#25
b1100 (
b1100 '
b1100 *
b1100 )
b1100 !
b1100 $
0"
#26
1"
#27
b1101 (
b1101 '
b1101 *
b1101 )
b1101 !
b1101 $
0"
#28
1"
#29
b1110 (
b1110 '
b1110 *
b1110 )
b1110 !
b1110 $
0"
#30
1"
#31
b1111 (
b1111 '
b1111 *
b1111 )
b1111 !
b1111 $
0"
#32
1"
#33
b10000 (
b10000 '
b10000 *
b10000 )
b10000 !
b10000 $
0"
#34
1"
#35
0"
#36
b101 !
1"
0%
1&
#37
b101 (
b101 '
b101 )
0"
#38
b101 $
b101 *
b1010 !
1"
#39
b1010 (
b1010 '
b1010 )
0"
#40
b1010 $
b1010 *
1"
#41
0"
#42
b10000 $
b1010 (
1"
1%
0&
#43
b1010101010101010 (
b1000000000 '
b1010101010101010 *
b1000000000 )
b1010101010101010 $
b1000000000 !
0"
#44
1"
#45
0"
0%
1&
