Lab2/Verilog/sram/sram.v

/*
Author: Adolfo Pineda
Title: 2kx16 SRAM 
Summary: 2k memory registers of 16 bits memory with data-in & data-out with
   chip select, output enable, write enable
*/

module sram(clk, cs, oe, rw, addr_bus, data_bus);
	input wire clk, cs, oe, rw;  // clock, !chip select, !out enable, read/!write
	inout wire [31:0] addr_bus;  // address bus to mar
	inout wire [31:0] data_bus;  // data bus to mdr
	reg [15:0] memory [0:2047];  // sram array of 16-bit registers
   reg [10:0] mar;  // memory address reg
   reg [15:0] mdr;  // memory data reg
   wire [10:0] sram_mar_bus;  // address bus from mar to sram
   wire [15:0] sram_data_bus;  // data bus from mdr to sram
	
   //// Tristate Buffers for data buses //
	// drive data to data_bus from mdr if reading sram else hi-z
   assign data_bus = (!cs && rw && !oe) ? {16'b0, mdr} : 32'bz;
	// drive data to sram from mdr if writing, drive data to mdr from sram if reading
	// else hi-z
   assign sram_data_bus = (!cs && rw && !oe) ? memory[sram_mar_bus] : ((!cs && !rw && oe) ? mdr : 16'bz);
   
	//// Tristate Buffers for address buses //
	// addr_bus not driven by sram
	assign addr_bus = 32'bz;
	// drive address from mar to sram if reading or writing else hi-z
	assign sram_mar_bus = (!cs && ((rw && !oe) || (!rw && oe))) ? mar : 11'bz;
   
   // Memory Address Register write:
   always @(negedge clk) begin
      if(!cs && ((rw && !oe) || (!rw && oe)))
         mar = addr_bus[10:0];
   end
   
   // Memory Data Register write:
   // write from sram to mdr on posedge clk, 
   // write from data bus to mdr on negedge clk
   always @(clk) begin
      if(!cs) begin
         if(!clk && (!rw && oe))
            mdr = data_bus[15:0];
         else if(clk &&((rw && !oe)))
            mdr = sram_data_bus;
      end
   end   
   
   // SRAM write:
	always @(posedge clk) begin
      if (!cs && (!rw && oe))
         memory[sram_mar_bus] = sram_data_bus;
	end
endmodule

Lab2/Verilog/sram/sram_tb.v

// All files used
`include "sram.v"

// Title: SRAM Testbench
// Author: Adolfo Pineda
// A test bench module

module sram_tb;

	wire clk, cs, oe, rw;
	wire [31:0] addr_bus;
	wire [31:0] data_bus;
	
	// dut
	sram ram(clk, cs, oe, rw, addr_bus, data_bus);
	
	// tester
	sramTester aTester(clk, cs, oe, rw, addr_bus, data_bus);

	// File for gtkwave
	initial begin
		$dumpfile("sram.vcd");
		$dumpvars(1, ram);
	end
endmodule



// Title: SRAM Tester
// Author: Adolfo Pineda
// A testing module

module sramTester (clk, cs, oe, rw, addr_bus, data_bus);

	integer i;
	input [15:0] read_out;
	output reg clk, cs, oe, rw;
   inout [31:0] addr_bus;
   inout [31:0] data_bus;
	reg [10:0] address;
	reg [15:0] data;
   wire [10:0] addr_bus_mon;
   wire [15:0] data_bus_mon;
	parameter stimDelay = 1;
	
   assign data_bus = (!cs && rw && !oe) ? 32'bz : {16'b0, data};
   assign addr_bus = !cs ? {21'b0, address} : 32'bz;
   
   assign addr_bus_mon = addr_bus[10:0];
   assign data_bus_mon = data_bus[15:0];
	initial // Response
	begin
	
	// Displays the labels and data
	$display("\t\t cs rw oe   ad_b da_b  clk  Time");
	$monitor("\t\t %b  %b  %b    %h  %h  %b    %g",
			cs, rw, oe, addr_bus_mon, data_bus_mon, clk, $time);
	end

	initial // Stimulus
	begin
   
   // initial
	clk = 1; 
	cs = 1;
	rw = 0;
	oe = 0;
	data = 16'b0;
	address = 0;
   clk = 1;
	
   // write values to first 16 addresses
   for(i=0; i<2; i=i+1) begin
      #stimDelay; clk = ~clk;
   end
   cs = 1'b0;
   oe = 1'b1;
	for (i = 0; i < 32; i = i + 1) begin
			data = data + (i+1)%2;
         address = address + (i+1)%2;
         #stimDelay; clk = ~clk;
   end
	
	
   // read
   for(i=0; i<2; i=i+1) begin
      #stimDelay; clk = ~clk;
   end
   address = 0;
	rw = 1;
	oe = 0;
   for (i = 0; i < 32; i = i + 1) begin
      address = address + (i+1)%2;
      #stimDelay; clk = ~clk;
	end
   for(i=0; i<2; i=i+1) begin
      #stimDelay; clk = ~clk;
   end
	
   // write
   rw = 0;
   oe = 1;
   address = 11'h200;
   data = 16'hAAAA;
   for(i=0; i<4; i=i+1) begin
      #stimDelay; clk = ~clk;
   end
	
   // read again
	rw = 1;
	oe = 0;
	for(i=0; i<4; i=i+1) begin
      #stimDelay; clk = ~clk;
   end
   
	$finish; // finish simulation
	end
	
endmodule

Lab2/Verilog/sram/sram.vcd
$date
	Sat Apr 16 20:12:49 2016
$end
$version
	Icarus Verilog
$end
$timescale
	1s
$end
$scope module sram_tb $end
$scope module ram $end
$var wire 32 ! addr_bus [31:0] $end
$var wire 1 " clk $end
$var wire 1 # cs $end
$var wire 32 $ data_bus [31:0] $end
$var wire 1 % oe $end
$var wire 1 & rw $end
$var wire 11 ' sram_mar_bus [10:0] $end
$var wire 16 ( sram_data_bus [15:0] $end
$var reg 11 ) mar [10:0] $end
$var reg 16 * mdr [15:0] $end
$upscope $end
$upscope $end
$enddefinitions $end
#0
$dumpvars
bx *
bx )
bz (
bz '
0&
0%
b0 $
1#
1"
bz !
$end
#1
0"
#2
bx '
bx (
b1 $
b1 !
1%
0#
1"
#3
b1 (
b1 '
b1 *
b1 )
0"
#4
b10 !
b10 $
1"
#5
b10 (
b10 '
b10 *
b10 )
0"
#6
b11 !
b11 $
1"
#7
b11 (
b11 '
b11 *
b11 )
0"
#8
b100 !
b100 $
1"
#9
b100 (
b100 '
b100 *
b100 )
0"
#10
b101 !
b101 $
1"
#11
b101 (
b101 '
b101 *
b101 )
0"
#12
b110 !
b110 $
1"
#13
b110 (
b110 '
b110 *
b110 )
0"
#14
b111 !
b111 $
1"
#15
b111 (
b111 '
b111 *
b111 )
0"
#16
b1000 !
b1000 $
1"
#17
b1000 (
b1000 '
b1000 *
b1000 )
0"
#18
b1001 !
b1001 $
1"
#19
b1001 (
b1001 '
b1001 *
b1001 )
0"
#20
b1010 !
b1010 $
1"
#21
b1010 (
b1010 '
b1010 *
b1010 )
0"
#22
b1011 !
b1011 $
1"
#23
b1011 (
b1011 '
b1011 *
b1011 )
0"
#24
b1100 !
b1100 $
1"
#25
b1100 (
b1100 '
b1100 *
b1100 )
0"
#26
b1101 !
b1101 $
1"
#27
b1101 (
b1101 '
b1101 *
b1101 )
0"
#28
b1110 !
b1110 $
1"
#29
b1110 (
b1110 '
b1110 *
b1110 )
0"
#30
b1111 !
b1111 $
1"
#31
b1111 (
b1111 '
b1111 *
b1111 )
0"
#32
b10000 !
b10000 $
1"
#33
b10000 (
b10000 '
b10000 *
b10000 )
0"
#34
1"
#35
0"
#36
b1 !
0%
1&
1"
#37
b1 (
b1 '
b1 )
0"
#38
b1 $
b10 !
b1 *
1"
#39
b10 (
b10 '
b10 )
0"
#40
b10 $
b11 !
b10 *
1"
#41
b11 (
b11 '
b11 )
0"
#42
b11 $
b100 !
b11 *
1"
#43
b100 (
b100 '
b100 )
0"
#44
b100 $
b101 !
b100 *
1"
#45
b101 (
b101 '
b101 )
0"
#46
b101 $
b110 !
b101 *
1"
#47
b110 (
b110 '
b110 )
0"
#48
b110 $
b111 !
b110 *
1"
#49
b111 (
b111 '
b111 )
0"
#50
b111 $
b1000 !
b111 *
1"
#51
b1000 (
b1000 '
b1000 )
0"
#52
b1000 $
b1001 !
b1000 *
1"
#53
b1001 (
b1001 '
b1001 )
0"
#54
b1001 $
b1010 !
b1001 *
1"
#55
b1010 (
b1010 '
b1010 )
0"
#56
b1010 $
b1011 !
b1010 *
1"
#57
b1011 (
b1011 '
b1011 )
0"
#58
b1011 $
b1100 !
b1011 *
1"
#59
b1100 (
b1100 '
b1100 )
0"
#60
b1100 $
b1101 !
b1100 *
1"
#61
b1101 (
b1101 '
b1101 )
0"
#62
b1101 $
b1110 !
b1101 *
1"
#63
b1110 (
b1110 '
b1110 )
0"
#64
b1110 $
b1111 !
b1110 *
1"
#65
b1111 (
b1111 '
b1111 )
0"
#66
b1111 $
b10000 !
b1111 *
1"
#67
b10000 (
b10000 '
b10000 )
0"
#68
b10000 $
b10000 *
1"
#69
0"
#70
b1010101010101010 $
b10000 (
b1000000000 !
1%
0&
1"
#71
b1010101010101010 (
b1000000000 '
b1010101010101010 *
b1000000000 )
0"
#72
1"
#73
0"
#74
0%
1&
1"
