Lab3/verilog/alu_gate/subtract_gate/subtract_gate.v
/*
Author: Ian Gilman
Title: 32-bit Subtraction Module
Summary: Subtract two 32-bit signed operands into difference. Controls flags:
 zero value (Z), underflow (V), carry (C), and negative value (N)
*/

// Module Dependencies
//`include "../adder_gate/adder_gate.v"
//`include "../adder_gate/full_adder_gate.v"
//`include "one_complement.v"

module subtract_gate(minuend, subtrahend, difference, Z, V, C, N);
// I/O
   input wire [31:0] minuend, subtrahend;
   output wire [31:0] difference;
   output wire Z, V, C, N;
// Internal
   wire [31:0] comp_subtrahend;
   
   // turn subtrahend into one_complements complement
   one_complement negate_value(subtrahend, comp_subtrahend);
   // add negative subtrahend to minuend (Cin = 1 makes subtrahend two's comp)
   adder_gate adding_negative(
               .addend0(minuend),
               .addend1(comp_subtrahend),
               .Cin(1'b1),
               .sum(difference),
               .Z(Z),
               .V(V),
               .C(C),
               .N(N)
             );
endmodule

Lab3/verilog/gate_level/adder_gate/adder_gate.v
/*
Author: Ian Gilman
Title: 32-bit Full Adder
Summary: adds signed addends together into sum. Controls flags: zero value (Z),
   overflow (V), carry (C), and negative value (N)
*/

// Module Dependencies
//`include "half_adder_gate.v"

module adder_gate(addend0, addend1, Cin, sum, Z, V, C, N);
// I/O
   input wire [31:0] addend0, addend1;  // signed values to add
   input wire Cin;  // Carry in value (used for negative)
   output wire [31:0] sum;  // sum of addends
   output wire Z, V, C, N;  // zero, overflow, carry_out, negative value
// Internal
   // adder flag wires
   wire [30:0] pre_zero;
   wire msb_addend_same, msb_sum_diff, not_overflow;
   // look-ahead carry wires
   wire [31:0] and_addend_pairs,
               carry,
               prop_carry,
               carry_propogate;
   
    
   //// ADDER FLAG LOGIC ////
   // zero flag
   // Z = sum[n] + sum[n-1] + ... + sum[1] + sum[0]
   not define_zero(Z, pre_zero[30]);
   buf init_prezero(pre_zero[0], sum[0]);
   genvar k;
   generate for(k=1; k<31; k=k+1) begin: ZERO_FLAG
      or prezero_or(pre_zero[k], pre_zero[k-1], sum[k]);
   end
   endgenerate
   
   // overflow flag
   // addend0 = A, addend1 = B
   // V = (A[31] x^ B[31]) * (A[31] x sum[31])
   xnor same_addend_msb(msb_addend_same, addend0[31], addend1[31]);
   xor diff_sum_msb(msb_sum_diff, sum[31], addend0[31]);
   and overflow_check(V, msb_addend_same, msb_sum_diff);
   
   // carry out flag
   // Cout = carry[31] * ^V
   not negate_overflow(not_overflow, V);
   and carry_out_and(C, not_overflow, carry[31]);
   
   // negative value flag
   // V = sum[31] * ~V
   and negative_val_and(N, not_overflow, sum[31]);
   
   
   // FULL_ADDERS
   // Produce sums using half-adders
   full_adder bit0_summation(  // first sum is an exception (no carry)
                           .addend0(addend0[0]),
                           .addend1(addend1[0]),
                           .carry_in(Cin),
                           .sum(sum[0]),
                           .carry_out(carry[0]) // 1st carry calc'd here
                        );
   genvar j;
   generate for(j=1; j<32; j=j+1) begin: HALF_ADDERS
      full_adder summation(
                           .addend0(addend0[j]),
                           .addend1(addend1[j]),
                           .carry_in(carry[j-1]),
                           .sum(sum[j]),
                           .carry_out()
                          );
   end
   endgenerate
   
   
   // Determine carry using several stages of combinational logic
   // LOOK AHEAD CARRY
   /* carry = C, addend0 = A, addend1 = B 
      for n=(1-31) bits: C[n] = A[n]*B[n] + (A[n] + B[n])*C([n]-1)
      special case: C[0] = A[0]*B[0],
   */
   buf(prop_carry[0], 1'b0);
   genvar i;
   generate for(i=0; i<32; i=i+1) begin: CARRY_CALC
      // determine definite carry from anding addend pairs
      and and_pairs(and_addend_pairs[i], addend0[i], addend1[i]);
      // determine if carry propogates (oring or xoring addends)
      or or_pairs(carry_propogate[i], addend0[i], addend1[i]);
      if(i>0) begin
         // determine final carry value
         or carry_or(carry[i], prop_carry[i], and_addend_pairs[i]);
         // determine propogation carry (prop_carry)
         and pre_carry_and(prop_carry[i], carry[i-1], carry_propogate[i]);
      end
   end
   endgenerate
endmodule

Lab3/verilog/alu_gate/adder_gate/full_adder_gate.v
/*
Author: Ian Gilman
Title: 1-bit Full-Adder
Summary: Logic for adding addend0, addend1, and carry_in to produce sum and carry
*/

module full_adder(addend0, addend1, carry_in, sum, carry_out);
   // I/O
   input wire addend0, addend1, carry_in;
   output wire sum, carry_out;
   // Internal
   wire carry0, carry1, carry2;
   
   // find sum
   // S = A0 x A1 x Cin
   xor xor0(sum, addend0, addend1, carry_in);
   
   // find carry_out
   // Cout = A0*A1 + A0*Cin + A1*Cin
   and and0(carry0, addend0, addend1);
   and and1(carry1, addend0, carry_in);
   and and2(carry2, addend1, carry_in);
   or or0(carry_out, carry0, carry1, carry2);
endmodule

Lab3/verilog/gate_level/slt_gate/slt_tester.v
/*
Author: Ian Gilman
Title: SLT Tester
Summary: Provides the stimulus for set less than test, prints logic output data
*/

module slt_tester(result, operand0, operand1);
// I/O
   input wire [31:0] result;
   output reg [31:0] operand0, operand1;
// Internal
   parameter delay = 5;
   
   //print logical data
   initial begin
      $display("\t       op0\t       op1\tres\ttime");
      $monitor("\t%d\t%d\t%b  \t%g", operand0, operand1, result[0], $time);   
   end

   // stimuls values
   initial begin
      // initial values
      #delay;
      operand0 <= 32'b0;
      operand1 <= 32'b0;
      
      // less than
      #delay;
      operand0 <= 32'hFFFFFFF1;
      operand1 <= 32'h2;
      #delay;
      operand0 <= 32'hFFFFFFF1;
      operand1 <= 32'hFFFFFFF3;
      #delay;
      operand0 <= 32'h50;
      operand1 <= 32'h40000040;
      #delay;
      operand0 <= 32'h45804674;
      operand1 <= 32'h56309375;
      #delay;
      
      // greater than
      operand0 <= 32'h75;
      operand1 <= 32'h49;
      #delay;
      operand0 <= 32'h80000004;
      operand1 <= 32'h80000002;
      #delay
      operand0 <= 32'h34;
      operand1 <= 32'h80000005;
      #delay
      operand0 <= 32'h40000001;
      operand1 <= 32'h2;
      #delay
      
      // equal
      operand0 <= 32'hF;
      operand1 <= 32'hFFFFFFF1;
      #delay;
   end
endmodule

Lab3/verilog/gate_level/slt_gate/slt_gate.v
/*
Author: Ian Gilman
Title: Set Less Than
Summary: Sets result equal to 1 if operand0 less than operand1, else set to 0
*/

module slt_gate(operand0, operand1, result);
// I/O
   input wire [31:0] operand0, operand1;  // operands to compare values
   output wire [31:0] result;  // result of less than comparison
// Internal
   // general calc wires
   wire [31:0] neg_op0, neg_op1;  // negate operand bits
   // primary calculation wires
   wire fast_calc,  // fast part of the calculation
        slow_calc;  // slower part of the calc
  // slow calculation wires
   wire msb_same;   // determines if msb is the same
   wire [30:0] digit_lesser,  // check if op0 digit < op1 digit
               digit_less_eq;  // check if op0 digit <= op1 digit
   wire [29:0] sum_less_eq,  // cumulative check if all digits op0 <= op1
               valid_less_than,  // individual digit valid less than check
               sum_valid_less_than;  // cumulative valid less than check
   // other wires
   wire [30:0] equal_val,  // checks if digits of operands are equal
               sum_equal_val;  // sums equal values checked
   
   
   // negate complementary values
   genvar i;
   generate for(i=0; i<32; i=i+1) begin: NEGATE
      not neg_op0_not(neg_op0[i], operand0[i]);
      not neg_op1_not(neg_op1[i], operand1[i]);
   end
   endgenerate
   
   // calc fast part
   and fast_calc_and(fast_calc, operand0[31], neg_op1[31]);
 

   // SLOW CALCULATION SERIES
   // find if msbs are the same
   xnor msb_same_xnor(msb_same, operand0[31], operand1[31]);
   
   // digit compares
   genvar j;
   generate for(j=30; j>=0; j=j-1) begin: DIGIT_COMPARE
      and digit_lesser_and(digit_lesser[j], neg_op0[j], operand1[j]);
      or digit_less_eq_or(digit_less_eq[j], neg_op0[j], operand1[j]);
   end
   endgenerate
   
   // accumulate less than or equal values
   and sum_less_eq_and(sum_less_eq[29], digit_less_eq[30], digit_less_eq[29]);
   genvar k;
   generate for(k=28; k>=0; k=k-1) begin: TOTAL_LESS_EQ
      and sum_less_eq_and(sum_less_eq[k], sum_less_eq[k+1], digit_less_eq[k]);
   end
   endgenerate
   
   /*
      ///// Slow Logic, accumulative values /////
      VARS:
      op0[30:0] = A, op1[30:0] = B
      inidivdual less thans = L, individual less than or equal to = F,
      cumulative less than or equal = G,
      individual valid less than detected = D, final less than found check = C
      LOGIC:
      Ln = ^A*B     Fn = ^An + Bn     G30 = L30 else Gn = G30*...*G(n-1) * Ln      
      D30 = L30 else Dn = Gn + D30 + ... + D(n+1)    C = D0
   */
   // determine whether valid <= is found and propogate < if present
   and valid_less_than_and(valid_less_than[29], digit_less_eq[30], digit_lesser[29]);
   or sum_valid_less_than_or(sum_valid_less_than[29], valid_less_than[29], digit_lesser[30]);
   genvar m;
   generate for(m=28; m>=0; m=m-1) begin: VALID_LESS_THAN
      and valid_less_than_and(valid_less_than[m], sum_less_eq[m+1], digit_lesser[m]);
      or sum_valid_less_than_or(sum_valid_less_than[m], valid_less_than[m], sum_valid_less_than[m+1]);
   end
   endgenerate
   
   // final slow calc
   and slow_and(slow, msb_same, sum_valid_less_than[0]);
   
   
   // RESULT CALCULATIONS
   // final result
   or result_or(result[0], fast_calc, slow);
   
   // buffer unused part of result with zeros
   genvar o;
   generate for(o=1; o<32; o=o+1) begin: BUFF_ZERO
      buf result_buf(result[o], 1'b0);
   end
   endgenerate
endmodule

Lab3/verilog/alu_gate/slt_gate/slt_testbench.v
/*
Author: Ian Gilman
Title: SLT Testebench
Summary: Test bench for set less than test, dumps waveform data
*/

// Module Dependencies
`include "../adder_gate/full_adder_gate.v"
`include "../adder_gate/adder_gate.v"
`include "../subtract_gate/subtract_gate.v"
`include "../subtract_gate/one_complement.v"
`include "slt_tester.v"
`include "slt_gate.v"

module slt_testbench();
   wire [31:0] operand0, operand1;
   wire [31:0] result;
   
   // SLT device under test
   slt_gate slt_dut(
                  .operand0(operand0),
                  .operand1(operand1),
                  .result(result)
               );
   // SLT tester
   slt_tester slt_test(
                  .operand0(operand0),
                  .operand1(operand1),
                  .result(result)                  
                  );
   
   // Waveform data   
   initial begin
      $dumpfile("slt_gate.vcd");
      $dumpvars(1, slt_dut);
   end
   
endmodule

Lab3/verilog/gate_level/slt_gate/slt_gate.vcd
$date
	Wed Apr 27 01:12:32 2016
$end
$version
	Icarus Verilog
$end
$timescale
	1s
$end
$scope module slt_testbench $end
$scope module slt_dut $end
$var wire 1 ! fast_calc $end
$var wire 1 " msb_same $end
$var wire 1 # slow $end
$var wire 30 $ valid_less_than [29:0] $end
$var wire 30 % sum_valid_less_than [29:0] $end
$var wire 30 & sum_less_eq [29:0] $end
$var wire 32 ' result [31:0] $end
$var wire 32 ( operand1 [31:0] $end
$var wire 32 ) operand0 [31:0] $end
$var wire 32 * neg_op1 [31:0] $end
$var wire 32 + neg_op0 [31:0] $end
$var wire 31 , digit_lesser [30:0] $end
$var wire 31 - digit_less_eq [30:0] $end
$upscope $end
$upscope $end
$enddefinitions $end
#0
$dumpvars
bx -
bx ,
bx +
bx *
bx )
bx (
b0x '
bx &
bx %
bx $
x#
x"
x!
$end
#5
b0 '
0#
b0 %
b111111111111111111111111111111 &
b0 $
b1111111111111111111111111111111 -
b0 ,
b11111111111111111111111111111111 *
1"
0!
b11111111111111111111111111111111 +
b0 (
b0 )
#10
b0 %
b0 &
b0 $
b1110 -
b1 '
b10 ,
b11111111111111111111111111111101 *
0"
1!
b1110 +
b10 (
b11111111111111111111111111110001 )
#15
1#
b11 %
b10 $
b1 '
b111111111111111111111111111111 &
0!
1"
b1111111111111111111111111111111 -
b1100 *
b11111111111111111111111111110011 (
#20
b1 '
1#
b111111111111111111111111111111 %
b0 $
b111111111111111111111111100000 &
b1000000000000000000000000000000 ,
b1111111111111111111111111101111 -
b10111111111111111111111110111111 *
b11111111111111111111111110101111 +
b1000000000000000000000001000000 (
b1010000 )
#25
b11111111111111111111111111111 %
b111110000000000000000000000000 &
b10010000000000000000000000000 $
b1111110011111111011101111111111 -
b10010001100001001000100000001 ,
b10101001110011110110110010001010 *
b10111010011111111011100110001011 +
b1010110001100001001001101110101 (
b1000101100000000100011001110100 )
#30
b0 '
0#
b0 %
b0 $
b111111111111111111111111000000 &
b1000 ,
b1111111111111111111111111001011 -
b11111111111111111111111110110110 *
b11111111111111111111111110001010 +
b1001001 (
b1110101 )
#35
b111111111111111111111111111000 &
b0 '
b10 ,
b1111111111111111111111111111011 -
b1111111111111111111111111111101 *
0!
b1111111111111111111111111111011 +
b10000000000000000000000000000010 (
b10000000000000000000000000000100 )
#40
b0 %
b0 $
b111111111111111111111111000000 &
b1 ,
b1111111111111111111111111001111 -
b1111111111111111111111111111010 *
0"
b11111111111111111111111111001011 +
b10000000000000000000000000000101 (
b110100 )
#45
b0 '
0#
b0 %
b0 $
b0 &
1"
b10 ,
b111111111111111111111111111110 -
b11111111111111111111111111111101 *
b10111111111111111111111111111110 +
b10 (
b1000000000000000000000000000001 )
#50
b111111111111111111111111111111 %
b111111111111111111111111110000 &
b111111111111111111111111110000 $
0"
b1111111111111111111111111110000 ,
b1111111111111111111111111110001 -
b1110 *
b11111111111111111111111111110000 +
b11111111111111111111111111110001 (
b1111 )
