Lab1/verilog/2_FourBitRC/FourBitRCTester.v
// Title:  4-bit Ripple Down Counter Tester File
// Author: Adolfo Pineda
// A testing module for the 4-bit ripple down counter
// that gets the counter to start counting

module FourBitRCTester (clk, rst, q0, q1, q2, q3);

	integer i;
	input q0, q1, q2, q3;
	output reg clk, rst;
	parameter stimDelay = 1;
	wire [3:0] count;
	assign count = {q3, q2, q1, q0};
	
	initial // Response
	begin
	// Displays the labels and data
	$display("\t\t clk \t rst \t q3 \t q2 \t q1 \t q0 \t Count \t Time ");
	$monitor("\t\t %b \t %b \t %b \t %b \t %b \t %b \t %d \t %g", clk, rst, q3, q2, q1, q0, count, $time );
	end

	initial // Stimulus
	begin
	clk = 0; 
	rst = 1;
	#stimDelay;
	rst = 0;
	#stimDelay;
	// Counting starts at this point
	rst = 1;
	#stimDelay;
	for (i = 0; i < 32; i = i + 1) begin
		#stimDelay;
		clk = ~clk;
	end
	
	rst = 0;
	#stimDelay;
	rst = 1;
	#stimDelay;
	for (i = 0; i < 8; i = i + 1) begin
		#stimDelay;
		clk = ~clk;
	end

	#(2*stimDelay); // needed to see END of simulation
	$finish; // finish simulation
	end
	endmodule

Lab_1/verilog/1_SupCounter/DFlipFlop.v
/*
Author: Lab-provided code
Title: D flip-flop
Summary: Behavioral model of a d flip-flop
*/


module DFlipFlop(q, qBar, D, clk, rst);
   input D, clk, rst; // DFF input, clock, reset
   output q, qBar; // DFF output, DFF negated output
   reg q;

   not n1 (qBar, q); // negate q

   // flip-flop storage logic
   always@ (negedge rst or posedge clk)
   begin
      if(!rst)
         q = 0;
      else
         q = D;
   end
endmodule

Lab1/verilog/2_FourBitRC/FourBitRC.v
// Title:  4-bit Ripple Down Counter
// Author: Adolfo Pineda
// This module is the 4-bit ripple down counter with active low reset

module FourBitRC(q0, q1, q2, q3, clk, rst);
input clk, rst;
output wire q0, q1, q2, q3;
wire w1, w2, w3, w4;
	
	// Flip flops connected in such a way that
    // emulate a 4-bit ripple down counter
	DFlipFlop d1(.q(q0), .qBar(w1), .D(w1), .clk(clk), .rst(rst));
	DFlipFlop d2(.q(q1), .qBar(w2), .D(w2), .clk(q0), .rst(rst));
	DFlipFlop d3(.q(q2), .qBar(w3), .D(w3), .clk(q1), .rst(rst));
	DFlipFlop d4(.q(q3), .qBar(w4), .D(w4), .clk(q2), .rst(rst));

endmodule

Lab_1/verilog/2_FourBitRC/FourBitRC_tb.v
// Title:  4-bit Ripple Down Counter Test Bench
// Author: Adolfo Pineda
// A test bench module for the 4-bit Ripple Down Counter
// that makes sure it is working perfectly

// All files used
`include "FourBitRC.v"
`include "FourBitRCTester.v"
`include "DFlipFlop.v"

module FourBitRC_tb;
	wire q0, q1, q2, q3, clk, rst;

	// Declare an instance of the FourBitRC module
	FourBitRC four (q0, q1, q2, q3, clk, rst);
	
	// Declare an instance of the FourBitRCTester module
	FourBitRCTester aTester (clk, rst, q0, q1, q2, q3);

	// File for gtkwave
	initial begin
		$dumpfile("FourBitRC.vcd");
		$dumpvars(1, four);
		
	end
endmodule

Lab1/verilog/2_FourBitRC/FourBitRC.vcd
$date
	Mon Apr 04 12:08:23 2016
$end
$version
	Icarus Verilog
$end
$timescale
	1s
$end
$scope module FourBitRC_tb $end
$scope module four $end
$var wire 1 ! clk $end
$var wire 1 " rst $end
$var wire 1 # w4 $end
$var wire 1 $ w3 $end
$var wire 1 % w2 $end
$var wire 1 & w1 $end
$var wire 1 ' q3 $end
$var wire 1 ( q2 $end
$var wire 1 ) q1 $end
$var wire 1 * q0 $end
$upscope $end
$upscope $end
$enddefinitions $end
#0
$dumpvars
x*
x)
x(
x'
x&
x%
x$
x#
1"
0!
$end
#1
1&
1%
1$
1#
0*
0)
0(
0'
0"
#2
1"
#4
0#
0$
1'
0%
1(
0&
1)
1*
1!
#5
0!
#6
1&
0*
1!
#7
0!
#8
1%
0&
0)
1*
1!
#9
0!
#10
1&
0*
1!
#11
0!
#12
1$
0%
0(
0&
1)
1*
1!
#13
0!
#14
1&
0*
1!
#15
0!
#16
1%
0&
0)
1*
1!
#17
0!
#18
1&
0*
1!
#19
0!
#20
1#
0$
0'
0%
1(
0&
1)
1*
1!
#21
0!
#22
1&
0*
1!
#23
0!
#24
1%
0&
0)
1*
1!
#25
0!
#26
1&
0*
1!
#27
0!
#28
1$
0%
0(
0&
1)
1*
1!
#29
0!
#30
1&
0*
1!
#31
0!
#32
1%
0&
0)
1*
1!
#33
0!
#34
1&
0*
1!
#35
0"
0!
#36
1"
#38
0#
0$
1'
0%
1(
0&
1)
1*
1!
#39
0!
#40
1&
0*
1!
#41
0!
#42
1%
0&
0)
1*
1!
#43
0!
#44
1&
0*
1!
